Workbook

Sheet GANANCIA
A2: FECHA | B2: CLIENTE | C2: NUMERO CLIENTE | D2: PRODUCTO | E2: TAMAÑO | F2: ESTILO | G2: IMAGEN | H2: TEMÁTICA | I2: PRECIO | J2: COSTE | K2: GANANCIA
A3: 45717 | B3: SANDRA-SINCLAIR | D3: TARTA FRUTA | E3: 20 | F3: ARTESANAL | H3: FRUTA | I3: 35 | J3: 15.59 | K3: =SUM(I3-J3) -> 19.41
A4: 45705 | B4: SUSI | D4: TARTA | E4: 20 | F4: TEMATICA | H4: WEED-BEER | I4: 40 | J4: 14.25 | K4: =SUM(I4-J4) -> 25.75
A5: 45703 | B5: SANDRA DELGADO | D5: TARTA | E5: 20 | F5: TEMATICA | G5: SI | H5: BATMAN | I5: 50 | J5: 30.55 | K5: =SUM(I5-J5) -> 19.45
A6: 45704 | B6: CRISTINA- SUSI | D6: TARTA | E6: 18 | F6: TEMATICA | G6: SI | H6: KITTY | I6: 45 | J6: 29.95 | K6: =SUM(I6-J6) -> 15.05
A7: 45710 | B7: ISA | D7: GALLETA | E7: 20 | F7: CASITA | H7: MAMA | I7: 20 | J7: 9.08 | K7: =SUM(I7-J7) -> 10.92
A8: 45718 | B8: VERONICA | D8: TARTA | E8: 24 | F8: TEMATICA | G8: SI | H8: DAYSI | I8: 65 | J8: 40.23 | K8: =SUM(I8-J8) -> 24.77
A9: 29-2 | B9: SARA - ISA | D9: TARTA | E9: 20 | F9: NUMERO | H9: NUMERO 25 | I9: 45 | J9: 15.27 | K9: =SUM(I9-J9) -> 29.73
A10: 45688 | B10: ERIKA | D10: TARTA | E10: 20 | F10: TEMATICA | H10: POKER | I10: 35 | J10: 30.55 | K10: =SUM(I10-J10) -> 4.45
A11: 45682 | B11: ESTEFANIA | D11: TARTA | E11: 20 | F11: TEMATICA | G11: SI | H11: BARBIE | I11: 45 | J11: 30.55 | K11: =SUM(I11-J11) -> 14.45
A12: 45682 | B12: ESTEFANIA | D12: TARTA | E12: 20 | F12: TEMATICA | G12: SI | H12: BLACK PINK | I12: 45 | J12: 30.55 | K12: =SUM(I12-J12) -> 14.45
A13: 45686 | B13: SANDRA - SINCLAIR | D13: TARTA | E13: 24 | F13: TEMATICA | G13: SI | H13: MASHA | I13: 50 | J13: 40.23 | K13: =SUM(I13-J13) -> 9.77
A14: 45686 | B14: ISA | D14: TARTA | E14: 18 | F14: TEMATICA | H14: CAZA | I14: 40 | J14: 29.95 | K14: =SUM(I14-J14) -> 10.05
A15: 45684 | B15: ESTEFANIA | D15: TARTA | E15: 20 | F15: TEMATICA | G15: SI | H15: BEBE JEFAZO | I15: 50 | J15: 30.55 | K15: =SUM(I15-J15) -> 19.45
A16: 45684 | B16: SUSI | D16: TARTA | E16: 20-15 | F16: TEMATICA | G16: SI | H16: PRINCESAS | I16: 60 | J16: 32.46 | K16: =SUM(I16-J16) -> 27.54
A17: 45719 | B17: ERIKA | D17: TARTA | E17: 20 | F17: TEMATICA | G17: SI | H17: BABY SHARK | I17: 40 | J17: 30.55 | K17: =SUM(I17-J17) -> 9.45
A18: 45684 | B18: SUSI | D18: GALLETA | E18: 35 | F18: TEMATICA | H18: MINIONS | I18: 20 | J18: 9.08 | K18: =SUM(I18-J18) -> 10.92
A19: 45733 | B19: SUSI | D19: TARTA | E19: 20 | F19: TEMATICA | G19: SI | H19: SPIDERMAN | I19: 30 | J19: 30.55 | K19: =SUM(I19-J19) -> -0.55
A20: 45684 | B20: ESTEFANIA | D20: TARTA | E20: 20-15 | F20: TEMATICA | G20: SI | H20: TALKING TOM | I20: 70 | J20: 32.46 | K20: =SUM(I20-J20) -> 37.54
A21: 45738 | B21: ISA | D21: PASTAS DE TE | E21: 450 GR | F21: MASA FINA | I21: 12 | J21: 6.44 | K21: =SUM(I21-J21) -> 5.56
A22: 45740 | B22: ISA | D22: CHEESECAKE DDL | E22: 20 | I22: 22 | K22: =SUM(I22-J22) -> 22
A23: 45734 | B23: BEA - AINARA | D23: TARTA | E23: 20 | F23: TEMATICA | H23: UNICORNIOS | I23: 40 | J23: 30.55 | K23: =SUM(I23-J23) -> 9.45
A24: 45734 | B24: JENNY | D24: TARTA | E24: 20 | F24: TEMATICA | H24: BEBE 1 MES | I24: 40 | J24: 30.55 | K24: =SUM(I24-J24) -> 9.45
A25: 45740 | B25: BEA - AINARA | D25: TARTA | E25: 20 | F25: TEMATICA | H25: UNICORNIOS | I25: 30 | J25: 30.55 | K25: =SUM(I25-J25) -> -0.55
A26: 45722 | B26: ESTEFANIA | D26: COOKIES | E26: 15 | I26: 20 | J26: 7.63 | K26: =SUM(I26-J26) -> 12.37
A27: 45722 | B27: ESTEFANIA | D27: GALLETAS RELLENAS | E27: 36 | I27: 40 | J27: 6.13 | K27: =SUM(I27-J27) -> 33.87
A28: 45731 | B28: NIEVES | D28: PASTAS DE TE | I28: 15 | J28: 6.44 | K28: =SUM(I28-J28) -> 8.56
A29: 45777 | B29: MARTA GLS | D29: TARTA | E29: 20-15 | F29: TEMATICA | G29: SI | H29: LILO Y STICH | I29: 70 | J29: 32.46 | K29: =SUM(I29-J29) -> 37.54
A30: 45777 | B30: MARTA GLS | D30: TARTA | E30: 30 | F30: TEMATICA | G30: SI | H30: LILO Y STICH | I30: 30 | J30: 40.24 | K30: =SUM(I30-J30) -> -10.24
A31: 45722 | B31: SONIA ALCALDESA | D31: TARTA | E31: 20 | F31: ARTESANAL | H31: MACETA | I31: 30 | J31: 15.27 | K31: =SUM(I31-J31) -> 14.73
A32: 45738 | B32: MARISA | D32: TARTA | E32: 16 | F32: TEMATICA | H32: BARTOLITO | I32: 40 | J32: 26.56 | K32: =SUM(I32-J32) -> 13.44
A33: 45732 | B33: BARBARA | D33: TARTA | E33: 20 | F33: ARTESANAL | H33: FUTBOL | I33: 35 | J33: 15.27 | K33: =SUM(I33-J33) -> 19.73
A34: 45777 | B34: CHELO | D34: GALLETAS | E34: 45 | F34: TEMATICA | H34: LILO Y STICH | I34: 40 | J34: 9.08 | K34: =SUM(I34-J34) -> 30.92
A35: 45731 | B35: NIEVES | D35: TARTA | E35: 16 | F35: TEMATICA | G35: SI | H35: COLACAO | I35: 35 | J35: 26.56 | K35: =SUM(I35-J35) -> 8.44
A36: 45787 | B36: ISA | D36: TARTA | E36: 16 | F36: ARTESANAL | G36: SI | H36: BOTELLIN | I36: 25 | J36: 12.46 | K36: =SUM(I36-J36) -> 12.54
A37: 45781 | B37: SUSI | D37: GALLETAS | E37: 25 | F37: TEMATICA | H37: LILO Y STICH | I37: 20 | J37: 9.08 | K37: =SUM(I37-J37) -> 10.92
A38: 45779 | B38: SUSI | D38: TARTA | E38: 20 | F38: ARTESANAL | H38: LILO Y STICH | I38: 30 | J38: 15.27 | K38: =SUM(I38-J38) -> 14.73
A39: 45766 | B39: MARI DM | D39: CHEESECAKE SOLO | E39: 18 | I39: 15 | J39: 12 | K39: =SUM(I39-J39) -> 3
A40: 45766 | B40: MARI DM | D40: CHEESECAKE F.ROJOS | E40: 18 | I40: 15 | J40: 13.19 | K40: =SUM(I40-J40) -> 1.81
A41: 45758 | B41: SANDRA - SINCLAIR | D41: T.COCO Y DDL | E41: 20 | I41: 18 | K41: =SUM(I41-J41) -> 18
A42: 45763 | B42: BEA - IZAN | D42: GALLETAS | E42: 40 | F42: TEMATICA | H42: CACAS | I42: 20 | J42: 9.08 | K42: =SUM(I42-J42) -> 10.92
A43: 45769 | B43: SINCLAIR | D43: PASTA FROLLA | E43: 20 | I43: 20 | K43: =SUM(I43-J43) -> 20
A44: 45779 | B44: CORAL BARRIOS | D44: GALLETAS | F44: TEMATICA | H44: RAMO FLORES | I44: 20 | J44: 9.08 | K44: =SUM(I44-J44) -> 10.92
A45: 45773 | B45: MARI DM | D45: CARROT CAKE | E45: 20 | F45: ARTESANAL | I45: 40 | K45: =SUM(I45-J45) -> 40
A46: 45777 | B46: LARA - ISA | D46: FACTURAS | E46: 1 DOCENA | I46: 15 | K46: =SUM(I46-J46) -> 15
A47: 45791 | B47: RAQUEL COLE | D47: TARTA 2 PISOS | E47: 20-15 | F47: TEMATICA | H47: PADEL | I47: 70 | J47: 32.46 | K47: =SUM(I47-J47) -> 37.54
A48: 45808 | B48: SASKYA | D48: TARTA FORMA | E48: 20-15 | F48: TEMATICA | H48: PATITO | I48: 60 | J48: 32.46 | K48: =SUM(I48-J48) -> 27.54
A49: 45786 | B49: JORGE GLS | D49: GALLETAS | H49: RAMO FLORES | I49: 20 | J49: 9.08 | K49: =SUM(I49-J49) -> 10.92
A50: 45801 | B50: MARI DM | D50: CHEESECAKE F.ROJOS | E50: 16 | I50: 20 | J50: 10.96 | K50: =SUM(I50-J50) -> 9.04
A51: 45801 | B51: MARI DM | D51: CARROT CAKE | E51: 16 | F51: ARTESANAL | I51: 20 | K51: =SUM(I51-J51) -> 20
A52: 45807 | B52: SANDRA SUPECO | D52: TARTA | E52: 18 | F52: TEMATICA | H52: DINOSAURIOS | I52: 46 | J52: 29.95 | K52: =SUM(I52-J52) -> 16.05
A53: 45779 | B53: SUSI | D53: TARTA | E53: 30 | F53: ARTESANAL | H53: CHOCOLATINAS | I53: 35 | J53: 16.46 | K53: =SUM(I53-J53) -> 18.54
A54: 45816 | B54: MARI DM | D54: TARTA | E54: 16 | F54: ARTESANAL | I54: 20 | J54: 12.46 | K54: =SUM(I54-J54) -> 7.54
A55: 45822 | B55: ALBA | D55: TARTA | E55: 18 | F55: ARTESANAL | I55: 35 | J55: 13.78 | K55: =SUM(I55-J55) -> 21.22
A56: 45792 | B56: SUSI | D56: TARTA | E56: 20 | F56: ARTESANAL | H56: FELIZ | I56: 30 | J56: 15.27 | K56: =SUM(I56-J56) -> 14.73
A57: 45822 | B57: MARIA ERUSTES | D57: PASTAS DE TE | E57: 1 KILO | I57: 20 | J57: 15.21 | K57: =SUM(I57-J57) -> 4.79
A58: 45821 | B58: ERIKA | D58: TARTA | E58: 20 | F58: TEMATICA | H58: MINNIE | I58: 35 | J58: 30.55 | K58: =SUM(I58-J58) -> 4.45
A59: 45823 | B59: susi | D59: TARTA | E59: 20 | F59: FELIX | I59: 30
A60: 45826 | B60: SOLEDAD | D60: TARTA | E60: 18 | F60: FONDANT | H60: GRADUACION | I60: 60
A61: 45830 | B61: ANA ESQUINA | D61: TARTA | E61: 24 | F61: GANACHE | G61: SI | H61: FROZEN | I61: 65
A62: 45830 | B62: ANA ESQUINA | D62: GALLETAS | E62: 35 | F62: GLASE | H62: FROZEN | I62: 20
I64: =SUM(I3:I58) -> 1933 | K64: =SUM(K3:K58) -> 868.07

Sheet Compras

Sheet COSTES TODOS
A2: PRODUCTO | C2: COSTE POR TAMAÑO | H2: PRECIO DE VENTA | M2: GANANCIA
B3: 16 CM | C3: 18 CM | D3: 20 CM | E3: 22 CM | F3: OTRO | G3: 16 CM | H3: 18 CM | I3: 20 CM | J3: 24 cm | K3: OTRO | L3: 16 | M3: 18 | N3: 20 | O3: 24 | P3: OTRO
A4: TARTA TEMATICA PERSONALIZADA GANACHE Y FONDANT | B4: ='TEMATICA GANACHE REDONDA'!I55 -> 24.773308 | C4: ='TEMATICA GANACHE REDONDA'!J55 -> 28.157677 | D4: ='TEMATICA GANACHE REDONDA'!K55 -> 30.548767 | E4: ='TEMATICA GANACHE REDONDA'!L55 -> 37.549319 | G4: 45 | H4: 50 | I4: 55 | J4: 60 | L4: =SUM(G4-B4) -> 20.226692 | M4: =SUM(H4-C4) -> 21.842323 | N4: =SUM(I4-D4) -> 24.451233 | O4: =SUM(J4-E4) -> 22.450681 | P4: =SUM(K4-F4) -> 0
A5: TARTA TEMATICA PERSONALIZADA FONDANT | B5: ='TEMATICA FONDANT REDONDA'!I55 -> 26.923308 | C5: ='TEMATICA FONDANT REDONDA'!J55 -> 31.113927 | D5: ='TEMATICA FONDANT REDONDA'!K55 -> 34.311267 | E5: ='TEMATICA FONDANT REDONDA'!L55 -> 42.118069 | G5: 48 | H5: 55 | I5: 60 | J5: 70 | L5: =SUM(G5-B5) -> 21.076692 | M5: =SUM(H5-C5) -> 23.886073 | N5: =SUM(I5-D5) -> 25.688733 | O5: =SUM(J5-E5) -> 27.881931 | P5: =SUM(K5-F5) -> 0
A6: BASICA NATA Y CHOCOLATE | B6: ='Masas basicas'!C94 -> 12.460308 | C6: ='Masas basicas'!D94 -> 13.776105 | D6: ='Masas basicas'!E94 -> 14.245887 | E6: ='Masas basicas'!F94 -> 16.461264 | G6: 30 | H6: 35 | I6: 40 | J6: 50 | L6: =SUM(G6-B6) -> 17.539692 | M6: =SUM(H6-C6) -> 21.223895 | N6: =SUM(I6-D6) -> 25.754113 | O6: =SUM(J6-E6) -> 33.538736 | P6: =SUM(K6-F6) -> 0
A7: TARTA CHOCOLATE SUAVE | B7: ='Masas basicas'!C95 -> 13.319108 | C7: ='Masas basicas'!D95 -> 14.353232 | D7: ='Masas basicas'!E95 -> 15.269937 | E7: ='Masas basicas'!F95 -> 16.461264 | G7: 30 | H7: 35 | I7: 40 | J7: 50 | L7: =SUM(G7-B7) -> 16.680892 | M7: =SUM(H7-C7) -> 20.646768 | N7: =SUM(I7-D7) -> 24.730063 | O7: =SUM(J7-E7) -> 33.538736 | P7: =SUM(K7-F7) -> 0
A8: TARTA ART. BV/ DDL Y FRUTA | B8: ='Masas basicas'!C99 -> 13.610495 | C8: ='Masas basicas'!D99 -> 14.795424 | D8: ='Masas basicas'!E99 -> 15.585715 | E8: ='Masas basicas'!F99 -> 17.990733 | G8: 30 | H8: 35 | I8: 40 | J8: 50 | L8: =SUM(G8-B8) -> 16.389505 | M8: =SUM(H8-C8) -> 20.204576 | N8: =SUM(I8-D8) -> 24.414285 | O8: =SUM(J8-E8) -> 32.009267 | P8: =SUM(K8-F8) -> 0
A9: TARTA MOUSSE FRUTOS ROJOS | B9: ='Masas basicas'!C100 -> 11.716362 | C9: ='Masas basicas'!D100 -> 12.614992 | D9: ='Masas basicas'!E100 -> 15.129715 | E9: ='Masas basicas'!F100 -> 17.367733 | G9: 30 | H9: 35 | I9: 40 | J9: 50 | L9: =SUM(G9-B9) -> 18.283638 | M9: =SUM(H9-C9) -> 22.385008 | N9: =SUM(I9-D9) -> 24.870285 | O9: =SUM(J9-E9) -> 32.632267 | P9: =SUM(K9-F9) -> 0
A10: TARTA MOUSSE FRUTOS ROJOS CHOCOLATE | B10: ='Masas basicas'!C101 -> 13.761495 | C10: ='Masas basicas'!D101 -> 14.660124 | D10: ='Masas basicas'!E101 -> 15.129715 | E10: ='Masas basicas'!F101 -> 17.367733 | G10: 30 | H10: 35 | I10: 40 | J10: 50 | L10: =SUM(G10-B10) -> 16.238505 | M10: =SUM(H10-C10) -> 20.339876 | N10: =SUM(I10-D10) -> 24.870285 | O10: =SUM(J10-E10) -> 32.632267 | P10: =SUM(K10-F10) -> 0
A11: TARTA DE LIMON | B11: ='Masas basicas'!C98 -> 14.616911 | C11: ='Masas basicas'!D98 -> 15.515541 | D11: ='Masas basicas'!E98 -> 16.656381 | E11: ='Masas basicas'!F98 -> 20.773566 | G11: 30 | H11: 35 | I11: 40 | J11: 50 | L11: =SUM(G11-B11) -> 15.383089 | M11: =SUM(H11-C11) -> 19.484459 | N11: =SUM(I11-D11) -> 23.343619 | O11: =SUM(J11-E11) -> 29.226434 | P11: =SUM(K11-F11) -> 0
A12: TARTA ARTESANAL OREO SUAVE | B12: ='Masas basicas'!C97 -> 13.075295 | C12: ='Masas basicas'!D97 -> 13.969002 | D12: ='Masas basicas'!E97 -> 14.991265 | E12: ='Masas basicas'!F97 -> 17.265596 | G12: 30 | H12: 35 | I12: 40 | J12: 50 | L12: =SUM(G12-B12) -> 16.924705 | M12: =SUM(H12-C12) -> 21.030998 | N12: =SUM(I12-D12) -> 25.008735 | O12: =SUM(J12-E12) -> 32.734404 | P12: =SUM(K12-F12) -> 0
A13: TARTA LOTUS | B13: ='Masas basicas'!C96 -> 12.216495 | C13: ='Masas basicas'!D96 -> 13.391874 | D13: ='Masas basicas'!E96 -> 13.967215 | E13: ='Masas basicas'!F96 -> 16.147733 | G13: 30 | H13: 35 | I13: 40 | J13: 50 | L13: =SUM(G13-B13) -> 17.783505 | M13: =SUM(H13-C13) -> 21.608126 | N13: =SUM(I13-D13) -> 26.032785 | O13: =SUM(J13-E13) -> 33.852267 | P13: =SUM(K13-F13) -> 0
A14: TARTA DE ZANAHORIA | B14: ='CARROT CAKE'!I55 -> 13.201637 | C14: ='CARROT CAKE'!J55 -> 16.245324 | D14: ='CARROT CAKE'!K55 -> 17.083127 | E14: ='CARROT CAKE'!L55 -> 23.467369 | G14: 35 | H14: 40 | I14: 45 | J14: 50 | L14: =SUM(G14-B14) -> 21.798363 | M14: =SUM(H14-C14) -> 23.754676 | N14: =SUM(I14-D14) -> 27.916873 | O14: =SUM(J14-E14) -> 26.532631 | P14: =SUM(K14-F14) -> 0
A15: TARTA KINDER | B15: ='TARTA KINDER'!I54 -> 29.175345 | C15: ='TARTA KINDER'!J54 -> 33.074436 | D15: ='TARTA KINDER'!K54 -> 36.302657 | E15: ='TARTA KINDER'!L54 -> 43.199213 | G15: 35 | H15: 40 | I15: 45 | J15: 50 | L15: =SUM(G15-B15) -> 5.8246549 | M15: =SUM(H15-C15) -> 6.925564 | N15: =SUM(I15-D15) -> 8.6973429 | O15: =SUM(J15-E15) -> 6.8007866 | P15: =SUM(K15-F15) -> 0
A16: TARTA OREO | B16: ='TARTA OREO'!I58 -> 21.906944 | C16: ='TARTA OREO'!J58 -> 24.807049 | D16: ='TARTA OREO'!K58 -> 27.036283 | E16: ='TARTA OREO'!L58 -> 32.985426 | G16: 35 | H16: 40 | I16: 45 | J16: 50 | L16: =SUM(G16-B16) -> 13.093056 | M16: =SUM(H16-C16) -> 15.192951 | N16: =SUM(I16-D16) -> 17.963717 | O16: =SUM(J16-E16) -> 17.014574 | P16: =SUM(K16-F16) -> 0
A17: TARTA SAN MARCOS | B17: ='SAN MARCOS'!I50 -> 12.534375 | C17: ='SAN MARCOS'!J50 -> 15.186171 | D17: ='SAN MARCOS'!K50 -> 19.099677 | E17: ='SAN MARCOS'!L50 -> 26.198321 | G17: 30 | H17: 35 | I17: 40 | J17: 50 | L17: =SUM(G17-B17) -> 17.465625 | M17: =SUM(H17-C17) -> 19.813829 | N17: =SUM(I17-D17) -> 20.900323 | O17: =SUM(J17-E17) -> 23.801679 | P17: =SUM(K17-F17) -> 0
A18: TARTA RED VELVET | G18: 35 | H18: 40 | I18: 45 | J18: 50
A19: TARTA CHAJA | B19: =CHAJA!I50 -> 15.071361 | C19: =CHAJA!J50 -> 16.406958 | D19: =CHAJA!K50 -> 18.478105 | E19: =CHAJA!L50 -> 25.599723 | G19: 35 | H19: 40 | I19: 45 | J19: 55 | L19: =SUM(G19-B19) -> 19.928639 | M19: =SUM(H19-C19) -> 23.593042 | N19: =SUM(I19-D19) -> 26.521895 | O19: =SUM(J19-E19) -> 29.400277 | P19: =SUM(K19-F19) -> 0
A20: TARTA FRESAS CON NATA | B20: ='TARTA FRESAS CON NATA'!I51 -> 12.678995 | C20: ='TARTA FRESAS CON NATA'!J51 -> 13.870124 | D20: ='TARTA FRESAS CON NATA'!K51 -> 15.989405 | E20: ='TARTA FRESAS CON NATA'!L51 -> 18.384089 | G20: 30 | H20: 35 | I20: 40 | J20: 50 | L20: =SUM(G20-B20) -> 17.321005 | M20: =SUM(H20-C20) -> 21.129876 | N20: =SUM(I20-D20) -> 24.010595 | O20: =SUM(J20-E20) -> 31.615911 | P20: =SUM(K20-F20) -> 0
A21: TARTA FULL CHOCOLATE | B21: ='TARTA FULL CHOCOLATE'!I56 -> 20.657677 | C21: ='TARTA FULL CHOCOLATE'!J56 -> 25.605933 | D21: ='TARTA FULL CHOCOLATE'!K56 -> 30.13591 | E21: ='TARTA FULL CHOCOLATE'!L56 -> 33.373615 | G21: 35 | H21: 40 | I21: 45 | J21: 60 | L21: =SUM(G21-B21) -> 14.342323 | M21: =SUM(H21-C21) -> 14.394067 | N21: =SUM(I21-D21) -> 14.86409 | O21: =SUM(J21-E21) -> 26.626385 | P21: =SUM(K21-F21) -> 0
A22: PASTA DE TE MASA FINA - CAJA CHICA- 400 GR - 60 PIEZAS | F22: ='PASTAS DE TE'!G14 -> 8.9473956 | K22: 14 | L22: =SUM(G22-B22) -> 0 | M22: =SUM(H22-C22) -> 0 | N22: =SUM(I22-D22) -> 0 | O22: =SUM(J22-E22) -> 0 | P22: =SUM(K22-F22) -> 5.0526044
A23: PASTAS DE TE MASA FINA - CAJA GRANDE - 900 GR - 100 PIEZAS | F23: ='PASTAS DE TE'!G18 -> 14.631318 | K23: 20 | L23: =SUM(G23-B23) -> 0 | M23: =SUM(H23-C23) -> 0 | N23: =SUM(I23-D23) -> 0 | O23: =SUM(J23-E23) -> 0 | P23: =SUM(K23-F23) -> 5.3686822
A24: PASTAS DE TE ELABORADAS CAJA CHICA 500 GR - 30 | F24: ='PASTAS DE TE'!G34 -> 12.064196 | K24: 20 | L24: =SUM(G24-B24) -> 0 | M24: =SUM(H24-C24) -> 0 | N24: =SUM(I24-D24) -> 0 | O24: =SUM(J24-E24) -> 0 | P24: =SUM(K24-F24) -> 7.9358044
A25: PASTAS DE TE ELABORADAS CAJA GRANDE 1 KILO - 60PIEZAS | F25: ='PASTAS DE TE'!G38 -> 17.232584 | K25: 28 | L25: =SUM(G25-B25) -> 0 | M25: =SUM(H25-C25) -> 0 | N25: =SUM(I25-D25) -> 0 | O25: =SUM(J25-E25) -> 0 | P25: =SUM(K25-F25) -> 10.767416
A26: CAJA MIX PASTAS DE TE 1 KILO - 90 PIEZAS | F26: ='PASTAS DE TE'!J54 -> 17.748118 | K26: 23 | L26: =SUM(G26-B26) -> 0 | M26: =SUM(H26-C26) -> 0 | N26: =SUM(I26-D26) -> 0 | O26: =SUM(J26-E26) -> 0 | P26: =SUM(K26-F26) -> 5.2518822
A27: CAJA MIX PASTAS DE TE 2 KILOS | F27: ='PASTAS DE TE'!J55 -> 23.43204 | K27: 30 | L27: =SUM(G27-B27) -> 0 | M27: =SUM(H27-C27) -> 0 | N27: =SUM(I27-D27) -> 0 | O27: =SUM(J27-E27) -> 0 | P27: =SUM(K27-F27) -> 6.56796
A28: GALLETAS PERSONALIZADAS PACK COLE 35 TODAS IGUALES -GLASE | F28: ='GALLETAS BASE'!G47 -> 9.5364416 | G28: 25 | L28: =SUM(G28-B28) -> 25 | M28: =SUM(H28-C28) -> 0 | N28: =SUM(I28-D28) -> 0 | O28: =SUM(J28-E28) -> 0 | P28: =SUM(K28-F28) -> -9.5364416
A29: GALLETAS PERSONALIZADAS PACK CUMPLEAÑOS -4 DISEÑOS -35 -GLASE | F29: ='GALLETAS BASE'!G47 -> 9.5364416 | G29: 30 | L29: =SUM(G29-B29) -> 30 | M29: =SUM(H29-C29) -> 0 | N29: =SUM(I29-D29) -> 0 | O29: =SUM(J29-E29) -> 0 | P29: =SUM(K29-F29) -> -9.5364416
A30: GALLETAS PERSONALIZADAS PACK TEMATICOS - SET 1 KG 25-30 -GLASE | F30: ='GALLETAS BASE'!G47 -> 9.5364416 | G30: 30 | L30: =SUM(G30-B30) -> 30 | M30: =SUM(H30-C30) -> 0 | N30: =SUM(I30-D30) -> 0 | O30: =SUM(J30-E30) -> 0 | P30: =SUM(K30-F30) -> -9.5364416
A31: GALLETAS PERSONALZIADAS PACK PUZZLE - 30 GALLETAS - IGUALES - GLASE | F31: ='GALLETAS BASE'!G47 -> 9.5364416 | G31: 30 | L31: =SUM(G31-B31) -> 30 | M31: =SUM(H31-C31) -> 0 | N31: =SUM(I31-D31) -> 0 | O31: =SUM(J31-E31) -> 0 | P31: =SUM(K31-F31) -> -9.5364416
A32: GALLETAS RAMO DE FLORES - GLASE - 8 FLORES GRANDES | F32: ='RAMO DE FLORES'!G47 -> 8.3345086 | G32: 20 | L32: =SUM(G32-B32) -> 20 | M32: =SUM(H32-C32) -> 0 | N32: =SUM(I32-D32) -> 0 | O32: =SUM(J32-E32) -> 0 | P32: =SUM(K32-F32) -> -8.3345086
A33: GALLETAS RAMO DE FLORES + MINI CAJITA 10 GALLETAS - GLASE | F33: ='GALLETAS BASE'!G47 -> 9.5364416 | G33: 22 | L33: =SUM(G33-B33) -> 22 | M33: =SUM(H33-C33) -> 0 | N33: =SUM(I33-D33) -> 0 | O33: =SUM(J33-E33) -> 0 | P33: =SUM(K33-F33) -> -9.5364416
A34: GALLETAS EN CASITA + 6 MINI GALLETAS - GLASE | F34: ='GALLETAS BASE'!G47 -> 9.5364416 | G34: 30 | L34: =SUM(G34-B34) -> 30 | M34: =SUM(H34-C34) -> 0 | N34: =SUM(I34-D34) -> 0 | O34: =SUM(J34-E34) -> 0 | P34: =SUM(K34-F34) -> -9.5364416
A35: GALLETAS PERSONALIZADAS FONDANT - 35 IGUAL FORMA | F35: ='GALLETAS BASE'!G28 -> 8.5409416 | G35: 30 | L35: =SUM(G35-B35) -> 30 | M35: =SUM(H35-C35) -> 0 | N35: =SUM(I35-D35) -> 0 | O35: =SUM(J35-E35) -> 0 | P35: =SUM(K35-F35) -> -8.5409416
A36: GALLETAS PERSONALIZADAS FONDANT - SET 25 GRANDES | F36: ='GALLETAS BASE'!G28 -> 8.5409416 | G36: 35 | L36: =SUM(G36-B36) -> 35 | M36: =SUM(H36-C36) -> 0 | N36: =SUM(I36-D36) -> 0 | O36: =SUM(J36-E36) -> 0 | P36: =SUM(K36-F36) -> -8.5409416
A37: GALLETAS CORAZON CRISTAL - PACK COLE 35 UN | G37: 20 | L37: =SUM(G37-B37) -> 20 | M37: =SUM(H37-C37) -> 0 | N37: =SUM(I37-D37) -> 0 | O37: =SUM(J37-E37) -> 0 | P37: =SUM(K37-F37) -> 0
A38: GALLETAS PACK DOBLE COLE - 30 PAQUETES - MERMELADAS Y CRISTAL | G38: 30 | L38: =SUM(G38-B38) -> 30 | M38: =SUM(H38-C38) -> 0 | N38: =SUM(I38-D38) -> 0 | O38: =SUM(J38-E38) -> 0 | P38: =SUM(K38-F38) -> 0
A39: CRUMBLE COOKIES - GRANDES 100GR - 15 UNIDADES | F39: ='CRUMBLE COOKIES'!K11 -> 16.67894 | G39: 20 | K39: 20 | L39: =SUM(G39-B39) -> 20 | M39: =SUM(H39-C39) -> 0 | N39: =SUM(I39-D39) -> 0 | O39: =SUM(J39-E39) -> 0 | P39: =SUM(K39-F39) -> 3.32106
A40: CRUMBLE COOKIES - GRANDES 100GR - 6 UNIDADES | F40: ='CRUMBLE COOKIES'!K12 -> 9.5204733 | G40: 12 | K40: 15 | L40: =SUM(G40-B40) -> 12 | M40: =SUM(H40-C40) -> 0 | N40: =SUM(I40-D40) -> 0 | O40: =SUM(J40-E40) -> 0 | P40: =SUM(K40-F40) -> 5.4795267
A41: COOKIES PACK COLE MINI 50GR, 35 UNIDADES | F41: ='CRUMBLE COOKIES'!K9 -> 16.67894 | G41: 20 | K41: 22 | L41: =SUM(G41-B41) -> 20 | M41: =SUM(H41-C41) -> 0 | N41: =SUM(I41-D41) -> 0 | O41: =SUM(J41-E41) -> 0 | P41: =SUM(K41-F41) -> 5.32106
A42: COOKIES CAJA 15 UNIDADES 50 GR | F42: ='CRUMBLE COOKIES'!K10 -> 9.5204733 | G42: 15 | K42: 15 | L42: =SUM(G42-B42) -> 15 | M42: =SUM(H42-C42) -> 0 | N42: =SUM(I42-D42) -> 0 | O42: =SUM(J42-E42) -> 0 | P42: =SUM(K42-F42) -> 5.4795267
A43: GALLETAS OJITOS CON MEREMELADAS -LOTUS O DDL 1/2 KG | G43: 15 | L43: =SUM(G43-B43) -> 15 | M43: =SUM(H43-C43) -> 0 | N43: =SUM(I43-D43) -> 0 | O43: =SUM(J43-E43) -> 0 | P43: =SUM(K43-F43) -> 0
A44: GALLETAS OJITOS CON MEREMELADAS -LOTUS O DDL 1 KG | G44: 22 | L44: =SUM(G44-B44) -> 22 | M44: =SUM(H44-C44) -> 0 | N44: =SUM(I44-D44) -> 0 | O44: =SUM(J44-E44) -> 0 | P44: =SUM(K44-F44) -> 0
A45: TARTA ALFAJOR DE MAICENA | L45: =SUM(G45-B45) -> 0 | M45: =SUM(H45-C45) -> 0 | N45: =SUM(I45-D45) -> 0 | O45: =SUM(J45-E45) -> 0 | P45: =SUM(K45-F45) -> 0
A46: CHEESECAKE FRUTOS ROJOS | B46: =CHEESECAKE!H26 -> 10.969132 | C46: =CHEESECAKE!I26 -> 13.194544 | D46: =CHEESECAKE!J26 -> 17.785616 | E46: =CHEESECAKE!K26 -> 18.030439 | G46: 18 | H46: 22 | I46: 28 | J46: 30 | L46: =SUM(G46-B46) -> 7.030868 | M46: =SUM(H46-C46) -> 8.8054564 | N46: =SUM(I46-D46) -> 10.214384 | O46: =SUM(J46-E46) -> 11.969561 | P46: =SUM(K46-F46) -> 0
A47: CHEESECAKE DULCE DE LECHE | B47: =CHEESECAKE!H55 -> 9.203132 | C47: =CHEESECAKE!I55 -> 11.928544 | D47: =CHEESECAKE!J55 -> 17.019616 | E47: =CHEESECAKE!K55 -> 17.484439 | G47: 18 | H47: 22 | I47: 28 | J47: 30 | L47: =SUM(G47-B47) -> 8.796868 | M47: =SUM(H47-C47) -> 10.071456 | N47: =SUM(I47-D47) -> 10.980384 | O47: =SUM(J47-E47) -> 12.515561 | P47: =SUM(K47-F47) -> 0
A48: CHEESECAKE LOTUS | B48: =CHEESECAKE!H55 -> 9.203132 | C48: =CHEESECAKE!I55 -> 11.928544 | D48: =CHEESECAKE!J55 -> 17.019616 | E48: =CHEESECAKE!K55 -> 17.484439 | G48: 18 | H48: 22 | I48: 28 | J48: 30 | L48: =SUM(G48-B48) -> 8.796868 | M48: =SUM(H48-C48) -> 10.071456 | N48: =SUM(I48-D48) -> 10.980384 | O48: =SUM(J48-E48) -> 12.515561 | P48: =SUM(K48-F48) -> 0
A49: CHEESE CAKE LIMON | L49: =SUM(G49-B49) -> 0 | M49: =SUM(H49-C49) -> 0 | N49: =SUM(I49-D49) -> 0 | O49: =SUM(J49-E49) -> 0 | P49: =SUM(K49-F49) -> 0
A50: CHEESECAKE MANGO | L50: =SUM(G50-B50) -> 0 | M50: =SUM(H50-C50) -> 0 | N50: =SUM(I50-D50) -> 0 | O50: =SUM(J50-E50) -> 0 | P50: =SUM(K50-F50) -> 0
A51: LEMON PIE 20 CM 8-10 PORCIONES | D51: ='LEMON PIE'!J9 -> 8.7700185 | I51: 20 | L51: =SUM(G51-B51) -> 0 | M51: =SUM(H51-C51) -> 0 | N51: =SUM(I51-D51) -> 11.229981 | O51: =SUM(J51-E51) -> 0 | P51: =SUM(K51-F51) -> 0
A52: LEMON PIE 22 CM 15 PORCIONES | E52: ='LEMON PIE'!J10 -> 8.2423852 | J52: 22 | L52: =SUM(G52-B52) -> 0 | M52: =SUM(H52-C52) -> 0 | N52: =SUM(I52-D52) -> 0 | O52: =SUM(J52-E52) -> 13.757615 | P52: =SUM(K52-F52) -> 0
A53: PASTA FROLLA 20 CM 12 PORCIONES | D53: ='PASTA FROLLA'!F28 -> 14.213325 | I53: 20 | L53: =SUM(G53-B53) -> 0 | M53: =SUM(H53-C53) -> 0 | N53: =SUM(I53-D53) -> 5.7866751 | O53: =SUM(J53-E53) -> 0 | P53: =SUM(K53-F53) -> 0
A54: PASTA FROLLA 22 CM 15 PORCIONES | E54: ='PASTA FROLLA'!G28 -> 12.980471 | J54: 22 | L54: =SUM(G54-B54) -> 0 | M54: =SUM(H54-C54) -> 0 | N54: =SUM(I54-D54) -> 0 | O54: =SUM(J54-E54) -> 9.0195289 | P54: =SUM(K54-F54) -> 0
A55: TARTA COCO Y DULCE DE LECHE | L55: =SUM(G55-B55) -> 0 | M55: =SUM(H55-C55) -> 0 | N55: =SUM(I55-D55) -> 0 | O55: =SUM(J55-E55) -> 0 | P55: =SUM(K55-F55) -> 0
A56: KEYLIME PIE 18 CM 15 PORCIONES | B56: ='KEYLIME PIE'!G16 -> 15.480405 | L56: =SUM(G56-B56) -> -15.480405 | M56: =SUM(H56-C56) -> 0 | N56: =SUM(I56-D56) -> 0 | O56: =SUM(J56-E56) -> 0 | P56: =SUM(K56-F56) -> 0
A57: KEYLIME PIE 20 CM 20 PORCIONES | B57: =B56 -> 15.480405 | L57: =SUM(G57-B57) -> -15.480405 | M57: =SUM(H57-C57) -> 0 | N57: =SUM(I57-D57) -> 0 | O57: =SUM(J57-E57) -> 0 | P57: =SUM(K57-F57) -> 0
A58: TARTA DE MANZANA | L58: =SUM(G58-B58) -> 0 | M58: =SUM(H58-C58) -> 0 | N58: =SUM(I58-D58) -> 0 | O58: =SUM(J58-E58) -> 0 | P58: =SUM(K58-F58) -> 0
A59: BROWNIE | B59: =BROWNIE!H8 -> 10.154478 | L59: =SUM(G59-B59) -> -10.154478 | M59: =SUM(H59-C59) -> 0 | N59: =SUM(I59-D59) -> 0 | O59: =SUM(J59-E59) -> 0 | P59: =SUM(K59-F59) -> 0
A60: CUPCAKES 12 RED VELVET FROSTING QUESO CREMA | B60: ='CUPCAKES RED VELVET'!D40 -> 12.759823 | L60: =SUM(G60-B60) -> -12.759823 | M60: =SUM(H60-C60) -> 0 | N60: =SUM(I60-D60) -> 0 | O60: =SUM(J60-E60) -> 0 | P60: =SUM(K60-F60) -> 0
A61: CUPCAKES 12 RED VELVET FROSTING GANACHE | B61: ='CUPCAKES RED VELVET'!D41 -> 13.27987 | L61: =SUM(G61-B61) -> -13.27987 | M61: =SUM(H61-C61) -> 0 | N61: =SUM(I61-D61) -> 0 | O61: =SUM(J61-E61) -> 0 | P61: =SUM(K61-F61) -> 0
A62: CUPCAKES 24 RED VELVET FROSTING QUESO | B62: ='CUPCAKES RED VELVET'!D39 -> 17.264746 | L62: =SUM(G62-B62) -> -17.264746 | M62: =SUM(H62-C62) -> 0 | N62: =SUM(I62-D62) -> 0 | O62: =SUM(J62-E62) -> 0 | P62: =SUM(K62-F62) -> 0
A63: CUPCAKES 24 RED VELVET FROSTING GANACHE | B63: ='CUPCAKES RED VELVET'!D42 -> 18.30484 | L63: =SUM(G63-B63) -> -18.30484 | M63: =SUM(H63-C63) -> 0 | N63: =SUM(I63-D63) -> 0 | O63: =SUM(J63-E63) -> 0 | P63: =SUM(K63-F63) -> 0
A64: CUPCAKES 12 ZANAHORIA FROSTING QUESO CREMA | L64: =SUM(G64-B64) -> 0 | M64: =SUM(H64-C64) -> 0 | N64: =SUM(I64-D64) -> 0 | O64: =SUM(J64-E64) -> 0 | P64: =SUM(K64-F64) -> 0
A65: CUPCAKES 12 ZANAHORIA FROSTING GANACHE | L65: =SUM(G65-B65) -> 0 | M65: =SUM(H65-C65) -> 0 | N65: =SUM(I65-D65) -> 0 | O65: =SUM(J65-E65) -> 0 | P65: =SUM(K65-F65) -> 0
A66: CUPACKES 24 ZANAHORIA FROSTING QUESO CREMA | L66: =SUM(G66-B66) -> 0 | M66: =SUM(H66-C66) -> 0 | N66: =SUM(I66-D66) -> 0 | O66: =SUM(J66-E66) -> 0 | P66: =SUM(K66-F66) -> 0
A67: CUPCAKES 24 ZANAHORIA FROSTING GANACHE | L67: =SUM(G67-B67) -> 0 | M67: =SUM(H67-C67) -> 0 | N67: =SUM(I67-D67) -> 0 | O67: =SUM(J67-E67) -> 0 | P67: =SUM(K67-F67) -> 0
A68: CUPCAKES 12 VAINILLA Y FROSTING QUESO CREMA | L68: =SUM(G68-B68) -> 0 | M68: =SUM(H68-C68) -> 0 | N68: =SUM(I68-D68) -> 0 | O68: =SUM(J68-E68) -> 0 | P68: =SUM(K68-F68) -> 0
A69: CUPCAKES 12 VAINILLA Y FROSTING GANACHE | L69: =SUM(G69-B69) -> 0 | M69: =SUM(H69-C69) -> 0 | N69: =SUM(I69-D69) -> 0 | O69: =SUM(J69-E69) -> 0 | P69: =SUM(K69-F69) -> 0
A70: CUPCAKES 24 VAINILLA FRISTING CREMA DE QUESO | L70: =SUM(G70-B70) -> 0 | M70: =SUM(H70-C70) -> 0 | N70: =SUM(I70-D70) -> 0 | O70: =SUM(J70-E70) -> 0 | P70: =SUM(K70-F70) -> 0
A71: CUPCAKES 24 VAINILLA FROSTING GANACHE | L71: =SUM(G71-B71) -> 0 | M71: =SUM(H71-C71) -> 0 | N71: =SUM(I71-D71) -> 0 | O71: =SUM(J71-E71) -> 0 | P71: =SUM(K71-F71) -> 0

Sheet PASTAS DE TE
E1: Sablee de manga - Pastas de te
A2: SABLEE DE MANGA
A3: INGREDIENTES | B3: CANTIDAD | C3: UNIDADES | D3: PRECIO | E3: COSTO 900 GR | G3: INGREDIENTES | H3: CANTIDAD | I3: UNIDADES | J3: PRECIO | K3: COSTO
G4: CAJA | H4: 1 | I4: 1 | J4: 2.2 | K4: =H4*J4/I4 -> 2.2
A5: Mantequilla | B5: 180 | C5: 250 | D5: 2.56 | E5: =B5*D5/C5 -> 1.8432 | G5: Papel horno | H5: 1 | I5: 20 | J5: 1.13 | K5: =H5*J5/I5 -> 0.0565
A6: Azucar glass | B6: 100 | C6: 1000 | D6: 5 | E6: =B6*D6/C6 -> 0.5 | G6: Gastos herram | H6: 1 | I6: 100 | J6: 10 | K6: =H6*J6/I6 -> 0.1
A7: Huevos | B7: 2 | C7: 12 | D7: 2.5 | E7: =B7*D7/C7 -> 0.41666667 | G7: Horno | H7: 30 | I7: 60 | J7: 1 | K7: =H7*J7/I7 -> 0.5
A8: Harina | B8: 250 | C8: 1000 | D8: 1.46 | E8: =B8*D8/C8 -> 0.365 | G8: Agua | H8: 12 | I8: 1000 | J8: 1.97 | K8: =H8*J8/I8 -> 0.02364
A9: Vainilla | B9: 10 | C9: 200 | D9: 6.9 | E9: =B9*D9/C9 -> 0.345 | G9: Batidora | H9: 5 | I9: 60 | J9: 1 | K9: =H9*J9/I9 -> 0.083333333
A10: Citricos | B10: 10 | C10: 1000 | D10: 1 | E10: =B10*D10/C10 -> 0.01 | G10: MANGAS | H10: 2 | I10: 20 | J10: 3 | K10: =H10*J10/I10 -> 0.3
A11: Chocolate blanco | B11: 30 | C11: 100 | D11: 1.15 | E11: =B11*D11/C11 -> 0.345 | K11: =SUM(K4:K10) -> 3.2634733
A12: Chocolate NEGRO | B12: 30 | C12: 1000 | D12: 1.15 | E12: =B12*D12/C12 -> 0.0345 | G12: MASAS FINAS
A13: Pistachos | C13: 1000 | D13: 19.95 | E13: =B13*D13/C13 -> 0 | G13: COSTES 450KG | H13: PVP 450 | I13: profit
A14: Nueces | C14: 1000 | D14: 15.89 | E14: =B14*D14/C14 -> 0 | G14: =E19+K11 -> 8.9473956 | H14: 14 | I14: =H14-G14 -> 5.0526044
A15: Almendras | C15: 1000 | D15: 17.25 | E15: =B15*D15/C15 -> 0
A16: mix frutos secos | B16: 20 | C16: 40 | D16: 0.85 | E16: =B16*D16/C16 -> 0.425
A17: caja | B17: 1 | C17: 1 | D17: 1.2 | E17: =B17*D17/C17 -> 1.2 | G17: COSTES 900 KG | H17: PVP 900
A18: cacao | B18: 20 | C18: 450 | D18: 4.49 | E18: =B18*D18/C18 -> 0.19955556 | G18: =(E19*2)+K11 -> 14.631318 | H18: 20 | I18: =H18-G18 -> 5.3686822
E19: =SUM(E5+E6+E7+E8+E9+E10+E11+E12+E13+E14+E15+E16+E17+E18) -> 5.6839222
A21: De esta masa sale 400gr de masitas | F21: MITAD DE CHOCOLATE Y MITAD DE VAINILLA O CITRICO
A22: En una caja de 400gr entran 60-70 unidades | F22: DECOS EN CHOCOLATE ,FRUTOS SECOS, FRUTA ABRILLANTADA
A25: SABLEE DURA - PASTAS RELLENAS
A26: INGREDIENTES | B26: CANTIDAD | C26: UNIDADES | D26: PRECIO | E26: COSTO
A28: Mantequilla | B28: 150 | C28: 250 | D28: 2.56 | E28: =B28*D28/C28 -> 1.536
A29: Azucar glass | B29: 100 | C29: 1000 | D29: 5 | E29: =B29*D29/C29 -> 0.5
A30: Huevos | B30: 1 | C30: 12 | D30: 2.5 | E30: =B30*D30/C30 -> 0.20833333
A31: Harina | B31: 250 | C31: 1000 | D31: 1.46 | E31: =B31*D31/C31 -> 0.365
A32: Vainilla | B32: 10 | C32: 200 | D32: 6.9 | E32: =B32*D32/C32 -> 0.345 | G32: PASTAS DE TE RELLENAS
A33: Citricos | B33: 10 | C33: 1000 | D33: 1 | E33: =B33*D33/C33 -> 0.01 | G33: COSTES 500 KG | H33: PVP 450 | I33: profit | J33: hs pagadas
A34: Chocolate blanco | B34: 30 | C34: 100 | D34: 1.15 | E34: =B34*D34/C34 -> 0.345 | G34: =SUM(E42+E51+K50) -> 12.064196 | H34: 20 | I34: =SUM(H34-G34) -> 7.9358044 | J34: =K30
A35: Chocolate NEGRO | B35: 30 | C35: 1000 | D35: 1.15 | E35: =B35*D35/C35 -> 0.0345
A36: Pistachos | C36: 1000 | D36: 19.95 | E36: =B36*D36/C36 -> 0
A37: Nueces | C37: 1000 | D37: 15.89 | E37: =B37*D37/C37 -> 0 | G37: COSTES 1 KG | H37: PVP 900
A38: Almendras | C38: 1000 | D38: 17.25 | E38: =B38*D38/C38 -> 0 | G38: =(E42*2)+E51+K50 -> 17.232584 | H38: 28 | I38: =H38-G38 -> 10.767416 | J38: =K30
A39: mix frutos secos | B39: 20 | C39: 40 | D39: 0.85 | E39: =B39*D39/C39 -> 0.425
A40: caja | B40: 1 | C40: 1 | D40: 1.2 | E40: =B40*D40/C40 -> 1.2
A41: cacao | B41: 20 | C41: 450 | D41: 4.49 | E41: =B41*D41/C41 -> 0.19955556
E42: =SUM(E28+E29+E30+E31+E32+E33+E34+E35+E36+E37+E38+E39+E40+E41) -> 5.1683889 | G42: INGREDIENTES | H42: CANTIDAD | I42: UNIDADES | J42: PRECIO | K42: COSTO
G43: CAJA | H43: 1 | I43: 1 | J43: 2.2 | K43: =H43*J43/I43 -> 2.2
B44: RELLENOS | G44: Papel horno | H44: 1 | I44: 20 | J44: 1.13 | K44: =H44*J44/I44 -> 0.0565
A45: INGREDIENTES | B45: CANTIDAD | C45: UNIDADES | D45: PRECIO | E45: COSTO | G45: Gastos herram | H45: 1 | I45: 100 | J45: 10 | K45: =H45*J45/I45 -> 0.1
G46: Horno | H46: 30 | I46: 60 | J46: 1 | K46: =H46*J46/I46 -> 0.5
A47: Dulce de leche | B47: 100 | C47: 1000 | D47: 4.99 | E47: =B47*D47/C47 -> 0.499 | G47: Agua | H47: 12 | I47: 1000 | J47: 1.97 | K47: =H47*J47/I47 -> 0.02364
A48: Chocolate blanco | B48: 100 | C48: 100 | D48: 1.15 | E48: =B48*D48/C48 -> 1.15 | G48: Batidora | H48: 5 | I48: 60 | J48: 1 | K48: =H48*J48/I48 -> 0.083333333
A49: Chocolate negro | B49: 100 | C49: 100 | D49: 1.15 | E49: =B49*D49/C49 -> 1.15 | G49: MANGAS | H49: 2 | I49: 20 | J49: 3 | K49: =H49*J49/I49 -> 0.3
A50: Mermelada | B50: 100 | C50: 240 | D50: 2 | E50: =B50*D50/C50 -> 0.83333333 | K50: =SUM(K43:K49) -> 3.2634733
E51: =SUM(E47:E50) -> 3.6323333
J53: COSTE | K53: PVP | L53: PROFIT
G54: COMBINADA, 500 DE MANGA Y 500 DE PASTAS | J54: =SUM(E19+E42+E51+K50) -> 17.748118 | K54: 23 | L54: =SUM(K54-J54) -> 5.2518822
G55: COMBINADA 2 KILOS | J55: =SUM(E19*2)+E42+E51+K50 -> 23.43204 | K55: 30 | L55: =SUM(K55-J55) -> 6.56796
C65: sablee nueva dura
C89: Pepas
A91: INGREDIENTES | B91: CANTIDAD | C91: UNIDADES | D91: PRECIO | E91: COSTO
A93: Mantequilla | B93: 150 | C93: 250 | D93: 2.56 | E93: =B93*D93/C93 -> 1.536
A94: Azucar glass | B94: 100 | C94: 1000 | D94: 5 | E94: =B94*D94/C94 -> 0.5
A95: Huevos | B95: 1 | C95: 12 | D95: 2.5 | E95: =B95*D95/C95 -> 0.20833333
A96: Harina | B96: 200 | C96: 1000 | D96: 1.46 | E96: =B96*D96/C96 -> 0.292
A97: Vainilla | B97: 10 | C97: 200 | D97: 6.9 | E97: =B97*D97/C97 -> 0.345
A98: Citricos | B98: 10 | C98: 1000 | D98: 1 | E98: =B98*D98/C98 -> 0.01
A99: Maicena | B99: 50 | C99: 400 | D99: 3 | E99: =B99*D99/C99 -> 0.375
A100: Chocolate NEGRO | C100: 1000 | D100: 1.15 | E100: =B100*D100/C100 -> 0
A101: Membrillo | B101: 100 | C101: 250 | D101: 2.1 | E101: =B101*D101/C101 -> 0.84
A102: Nueces | C102: 1000 | D102: 15.89 | E102: =B102*D102/C102 -> 0
A103: Almendras | C103: 1000 | D103: 17.25 | E103: =B103*D103/C103 -> 0
A104: mix frutos secos | C104: 40 | D104: 0.85 | E104: =B104*D104/C104 -> 0
A105: caja | B105: 1 | C105: 1 | D105: 1.2 | E105: =B105*D105/C105 -> 1.2
A106: cacao | C106: 450 | D106: 4.49 | E106: =B106*D106/C106 -> 0
E107: =SUM(E93+E94+E95+E96+E97+E98+E99+E100+E101+E102+E103+E104+E105+E106) -> 5.3063333

Sheet PASTA FROLLA
A2: MASA FROLLA
A3: INGREDIENTES | B3: 20 CM | C3: 22 CM | D3: UNIDADES PAQ | E3: PRECIO | F3: COSTO 8-10 p | G3: COSTO 12-15
A4: MANTECA | B4: 200 | C4: 300 | D4: 250 | E4: 2.56 | F4: =(B4*E4)/D4 -> 2.048 | G4: =C5*E5/D5 -> 0.33525
A5: AZUCAR BLANCA | B5: 150 | C5: 225 | D5: 1000 | E5: 1.49 | F5: =(B5*E5)/D5 -> 0.2235 | G5: =C6*E6/D6 -> 0.625
A6: HUEVOS | B6: 2 | C6: 3 | D6: 12 | E6: 2.5 | F6: =(B6*E6)/D6 -> 0.41666667 | G6: =C7*E7/D7 -> 0.149
A7: LIMON RALLADURA | B7: 1 | C7: 1 | D7: 10 | E7: 1.49 | F7: =(B7*E7)/D7 -> 0.149 | G7: =C8*E8/D8 -> 0.14618644
A8: VAINILLA | B8: 5 | C8: 5 | D8: 236 | E8: 6.9 | F8: =(B8*E8)/D8 -> 0.14618644 | G8: =C8*E8/D8 -> 0.14618644
A9: HARINA | B9: 300 | C9: 500 | D9: 1000 | E9: 1.49 | F9: =SUM(F5:F8) -> 0.93535311 | G9: =SUM(G5:G8) -> 1.0663729
A10: MAICENA | B10: 100 | C10: 100 | D10: 400 | E10: 4 | F10: =SUM(F6:F9) -> 1.6472062 | G10: =SUM(G6:G9) -> 1.5077458
A11: SAL | B11: 3 | C11: 3 | D11: 1000 | E11: 1 | F11: =SUM(F7:F10) -> 2.8777458 | G11: =SUM(G7:G10) -> 2.8664915
F12: =SUM(F4:F11) -> 8.4436582 | G12: =SUM(G4:G11) -> 6.8422331
A13: RELLENO
A14: INGREDIENTES | B14: 20 CM | C14: 22 CM | D14: UNIDADES PAQ | E14: PRECIO | F14: COSTO 8-10 p | G14: COSTO 12-15
A15: MEMBRILLO | B15: 350 | C15: 450 | D15: 350 | E15: 1.29 | F15: =(B15*E15)/D15 -> 1.29 | G15: =(C15*E15/D15) -> 1.6585714
F16: =F15 -> 1.29 | G16: =G15 -> 1.6585714
A18: GASTOS INDIRECTOS
A19: PRODUCTO | B19: 20 CM | C19: 22 CM | D19: UNIDADES | E19: PRECIO | F19: COSTO 20CM | G19: COSTO 22CM
A20: BATIDORA | B20: 10 | C20: 10 | D20: 60 | E20: 1 | F20: =(B20*E20/D20) -> 0.16666667 | G20: =(C20*E20/D20) -> 0.16666667
A21: PAPEL HORNO | B21: 2 | C21: 2 | D21: 20 | E21: 1.13 | F21: =(B21*E21/D21) -> 0.113 | G21: =(C21*E21/D21) -> 0.113
A22: NEVERA | B22: 30 | C22: 30 | D22: 60 | E22: 1 | F22: =(B22*E22/D22) -> 0.5 | G22: =(C22*E22/D22) -> 0.5
A23: HORNO | B23: 30 | C23: 30 | D23: 60 | E23: 1 | F23: =(B23*E23/D23) -> 0.5 | G23: =(C23*E23/D23) -> 0.5
A24: PLATO 25 CM | B24: 1 | C24: 1 | D24: 1 | E24: 1 | F24: =(B24*E24/D24) -> 1 | G24: =(C24*E24/D24) -> 1
A25: CAJA 25 | B25: 1 | C25: 1 | D25: 1 | E25: 2.2 | F25: =(B25*E25/D25) -> 2.2 | G25: =(C25*E25/D25) -> 2.2
F26: =SUM(F20:F25) -> 4.4796667 | G26: =SUM(G20:G25) -> 4.4796667
D28: COSTE TOTAL | F28: =SUM(F12+F16+F26) -> 14.213325 | G28: =SUM(G12+G16+G26) -> 12.980471
D29: PRECIO VENTA | F29: 20 | G29: 22
D30: GANANCIA | F30: =SUM(F29-F28) -> 5.7866751 | G30: =SUM(G29-G28) -> 9.0195289

Sheet RAMO DE FLORES
C2: MASA BASE DE GALLETAS
A3: INGREDIENTES | B3: CANTIDAD | C3: UNIDADES | D3: PRECIO | E3: COSTO
G4: DE ESTA MASA SALEN 7 FLORES Y 1 HOJA
A5: Mantequilla | B5: 100 | C5: 1000 | D5: 2.56 | E5: =B5*D5/C5 -> 0.256
A6: Azucar glass | B6: 100 | C6: 1000 | D6: 5 | E6: =B6*D6/C6 -> 0.5
A7: Huevos | B7: 1 | C7: 12 | D7: 2.5 | E7: =B7*D7/C7 -> 0.20833333
A8: Harina | B8: 200 | C8: 1000 | D8: 1.46 | E8: =B8*D8/C8 -> 0.292
A9: Vainilla | B9: 5 | C9: 200 | D9: 6.9 | E9: =B9*D9/C9 -> 0.1725
A10: Citricos | B10: 5 | C10: 1000 | D10: 1 | E10: =B10*D10/C10 -> 0.005
A11: Cacao | B11: 0 | C11: 450 | D11: 4.99 | E11: =B11*D11/C11 -> 0
E12: =SUM(E5:E11) -> 1.4338333
B13: =SUM(B5:B11) -> 411
B15: GLASE REAL
A16: INGREDIENTES | B16: CANTIDAD | C16: UNIDADES | D16: PRECIO | E16: COSTO | H16: GASTOS INDIRECTOS
G17: INGREDIENTES | H17: CANTIDAD | I17: UNIDADES | J17: PRECIO | K17: COSTO
A18: PALITOS | B18: 8 | C18: 1000 | D18: 2.56 | E18: =B18*D18/C18 -> 0.02048
A19: PAPEL ENVOLTORIO | B19: 1 | C19: 1000 | D19: 5 | E19: =B19*D19/C19 -> 0.005 | G19: Papel horno | H19: 1 | I19: 20 | J19: 1.13 | K19: =H19*J19/I19 -> 0.0565
A20: BOLSITAS | B20: 8 | C20: 12 | D20: 2.5 | E20: =B20*D20/C20 -> 1.6666667 | G20: Gastos herram | H20: 1 | I20: 100 | J20: 10 | K20: =H20*J20/I20 -> 0.1
A21: CUERDA | B21: 1 | C21: 1000 | D21: 1.46 | E21: =B21*D21/C21 -> 0.00146 | G21: Horno | H21: 30 | I21: 60 | J21: 1 | K21: =H21*J21/I21 -> 0.5
A22: ETIQUETA | B22: 2 | C22: 200 | D22: 6.9 | E22: =B22*D22/C22 -> 0.069 | G22: Agua | H22: 12 | I22: 1000 | J22: 1.97 | K22: =H22*J22/I22 -> 0.02364
A23: Glase | B23: 450 | C23: 900 | D23: 6.34 | E23: =B23*D23/C23 -> 3.17 | G23: Batidora | H23: 5 | I23: 60 | J23: 1 | K23: =H23*J23/I23 -> 0.083333333
A24: Colorantes | B24: 4 | C24: 28 | D24: 2.6 | E24: =B24*D24/C24 -> 0.37142857
A25: POLVOS | B25: 4 | C25: 1000 | D25: 1 | E25: =B25*D25/C25 -> 0.004 | K25: =SUM(K19:K24) -> 0.76347333
A26: CAJA | B26: 1 | C26: 1 | D26: 1.75 | E26: 2.2
B27: 0 | C27: 100 | D27: 11 | E27: =B27*D27/C27 -> 0 | G27: COSTES 1KG | H27: PVP 20-25
B28: 0 | C28: 450 | D28: 4.99 | E28: =B28*D28/C28 -> 0 | G28: =SUM(#REF!+K25) -> #REF! | H28: 25
E29: =SUM(E18:E28) -> 7.5080352
G31: COSTES 2 KG | H31: PVP 40-50
G32: =(#REF!*2)+K25 -> #REF! | H32: 40
H35: GASTOS INDIRECTOS
G36: INGREDIENTES | H36: CANTIDAD | I36: UNIDADES | J36: PRECIO | K36: COSTO
G38: Papel horno | H38: 1 | I38: 20 | J38: 1.13 | K38: =H38*J38/I38 -> 0.0565
G39: Mangas | H39: 10 | I39: 100 | J39: 1.63 | K39: =H39*J39/I39 -> 0.163
G40: Horno | H40: 30 | I40: 60 | J40: 1 | K40: =H40*J40/I40 -> 0.5
G41: Agua | H41: 12 | I41: 1000 | J41: 1.97 | K41: =H41*J41/I41 -> 0.02364
G42: Batidora | H42: 5 | I42: 60 | J42: 1 | K42: =H42*J42/I42 -> 0.083333333
K44: =SUM(K38:K43) -> 0.82647333
G46: COSTES 1KG | H46: PVP 20-25 | I46: profit | J46: hs pagadas
G47: =SUM(E29+K44) -> 8.3345086 | H47: 30 | I47: =H47-G47 -> 21.665491 | J47: =K43
G50: COSTES 2 KG | H50: PVP 40-50
G51: =(E29*2)+K44 -> 15.842544 | H51: 50 | I51: =H51-G51 -> 34.157456 | J51: =K43

Sheet GALLETAS BASE
C2: MASA BASE DE GALLETAS
A3: INGREDIENTES | B3: CANTIDAD | C3: UNIDADES | D3: PRECIO | E3: COSTO
G4: de esta masa base sale un kilo de galletas
A5: Mantequilla | B5: 200 | C5: 1000 | D5: 2.56 | E5: =B5*D5/C5 -> 0.512 | G5: dependiendo del tamaño del cortador
A6: Azucar glass | B6: 200 | C6: 1000 | D6: 5 | E6: =B6*D6/C6 -> 1 | G6: en circular pequeño 50
A7: Huevos | B7: 1 | C7: 12 | D7: 2.5 | E7: =B7*D7/C7 -> 0.20833333 | G7: halloween 30
A8: Harina | B8: 500 | C8: 1000 | D8: 1.46 | E8: =B8*D8/C8 -> 0.73
A9: Vainilla | B9: 10 | C9: 200 | D9: 6.9 | E9: =B9*D9/C9 -> 0.345
A10: Citricos | B10: 10 | C10: 1000 | D10: 1 | E10: =B10*D10/C10 -> 0.01
A11: Cacao | B11: 20 | C11: 450 | D11: 4.99 | E11: =B11*D11/C11 -> 0.22177778
E12: =SUM(E5:E11) -> 3.0271111
B13: =SUM(B5:B11) -> 941
B16: FONDANT | H16: GASTOS INDIRECTOS
A17: INGREDIENTES | B17: CANTIDAD | C17: UNIDADES | D17: PRECIO | E17: COSTO | G17: INGREDIENTES | H17: CANTIDAD | I17: UNIDADES | J17: PRECIO | K17: COSTO
A19: Mantequilla | B19: 200 | C19: 1000 | D19: 2.56 | E19: =B19*D19/C19 -> 0.512 | G19: Papel horno | H19: 1 | I19: 20 | J19: 1.13 | K19: =H19*J19/I19 -> 0.0565
A20: Azucar glass | B20: 200 | C20: 1000 | D20: 5 | E20: =B20*D20/C20 -> 1 | G20: Gastos herram | H20: 1 | I20: 100 | J20: 10 | K20: =H20*J20/I20 -> 0.1
A21: Huevos | B21: 1 | C21: 12 | D21: 2.5 | E21: =B21*D21/C21 -> 0.20833333 | G21: Horno | H21: 30 | I21: 60 | J21: 1 | K21: =H21*J21/I21 -> 0.5
A22: Harina | B22: 500 | C22: 1000 | D22: 1.46 | E22: =B22*D22/C22 -> 0.73 | G22: Agua | H22: 12 | I22: 1000 | J22: 1.97 | K22: =H22*J22/I22 -> 0.02364
A23: Vainilla | B23: 10 | C23: 200 | D23: 6.9 | E23: =B23*D23/C23 -> 0.345 | G23: Batidora | H23: 5 | I23: 60 | J23: 1 | K23: =H23*J23/I23 -> 0.083333333
A24: Fondant | B24: 500 | C24: 2000 | D24: 10.75 | E24: =B24*D24/C24 -> 2.6875
A25: Colorantes | B25: 1 | C25: 28 | D25: 2.6 | E25: =B25*D25/C25 -> 0.092857143 | K25: =SUM(K19:K24) -> 0.76347333
A26: Citricos | B26: 10 | C26: 1000 | D26: 1 | E26: =B26*D26/C26 -> 0.01
A27: Caja 26x26x10 dcora | B27: 1 | C27: 1 | D27: 1.75 | E27: =B27*D27/C27 -> 1.75 | G27: COSTES 1KG | H27: PVP 20-25
A28: Blonda | B28: 2 | C28: 100 | D28: 11 | E28: =B28*D28/C28 -> 0.22 | G28: =SUM(E30+K25) -> 8.5409416 | H28: 25
A29: Cacao | B29: 20 | C29: 450 | D29: 4.99 | E29: =B29*D29/C29 -> 0.22177778
E30: =SUM(E19:E29) -> 7.7774683
G31: COSTES 2 KG | H31: PVP 40-50
G32: =(E30*2)+K25 -> 16.31841 | H32: 40
B35: GLASE REAL | H35: GASTOS INDIRECTOS
A36: INGREDIENTES | B36: CANTIDAD | C36: UNIDADES | D36: PRECIO | E36: COSTO | G36: INGREDIENTES | H36: CANTIDAD | I36: UNIDADES | J36: PRECIO | K36: COSTO
A38: Mantequilla | B38: 200 | C38: 1000 | D38: 2.56 | E38: =B38*D38/C38 -> 0.512 | G38: Papel horno | H38: 1 | I38: 20 | J38: 1.13 | K38: =H38*J38/I38 -> 0.0565
A39: Azucar glass | B39: 200 | C39: 1000 | D39: 5 | E39: =B39*D39/C39 -> 1 | G39: Mangas | H39: 10 | I39: 100 | J39: 1.63 | K39: =H39*J39/I39 -> 0.163
A40: Huevos | B40: 1 | C40: 12 | D40: 2.5 | E40: =B40*D40/C40 -> 0.20833333 | G40: Horno | H40: 30 | I40: 60 | J40: 1 | K40: =H40*J40/I40 -> 0.5
A41: Harina | B41: 500 | C41: 1000 | D41: 1.46 | E41: =B41*D41/C41 -> 0.73 | G41: Agua | H41: 12 | I41: 1000 | J41: 1.97 | K41: =H41*J41/I41 -> 0.02364
A42: Vainilla | B42: 10 | C42: 200 | D42: 6.9 | E42: =B42*D42/C42 -> 0.345 | G42: Batidora | H42: 5 | I42: 60 | J42: 1 | K42: =H42*J42/I42 -> 0.083333333
A43: Glase | B43: 450 | C43: 900 | D43: 6.34 | E43: =B43*D43/C43 -> 3.17
A44: Colorantes | B44: 1 | C44: 28 | D44: 2.6 | E44: =B44*D44/C44 -> 0.092857143 | K44: =SUM(K38:K43) -> 0.82647333
A45: Citricos | B45: 10 | C45: 1000 | D45: 1 | E45: =B45*D45/C45 -> 0.01
A46: Caja 26x26x10 dcora | B46: 1 | C46: 1 | D46: 1.75 | E46: 2.2 | G46: COSTES 1KG | H46: PVP 20-25 | I46: profit | J46: hs pagadas
A47: Blonda | B47: 2 | C47: 100 | D47: 11 | E47: =B47*D47/C47 -> 0.22 | G47: =SUM(E49+K44) -> 9.5364416 | H47: 30 | I47: =H47-G47 -> 20.463558 | J47: =K43
A48: Cacao | B48: 20 | C48: 450 | D48: 4.99 | E48: =B48*D48/C48 -> 0.22177778
E49: =SUM(E38:E48) -> 8.7099683
G50: COSTES 2 KG | H50: PVP 40-50
G51: =(E49*2)+K44 -> 18.24641 | H51: 50 | I51: =H51-G51 -> 31.75359 | J51: =K43

Sheet SAN MARCOS
B3: INGREDIENTES | C3: CANT 8-10 p | D3: CANT 12-15 | E3: CANT 18-20 p | F3: CANT 25-28 | G3: UNIDADES PAQ | H3: PRECIO | I3: COSTO 8-10 p | J3: COSTO 12-15 | K3: COSTO 18-20 p | L3: COSTO 25-28
A5: BIZCOCHO | B5: Harina | C5: 150 | D5: 180 | E5: 240 | F5: 270 | G5: 1000 | H5: 1.07 | I5: =(C5*H5)/G5 -> 0.1605 | J5: =D6*H6/G6 -> 1.25 | K5: =(E5*H5)/G5 -> 0.2568 | L5: =(F5*H5)/G5 -> 0.2889
A6: VAINILLA | B6: Huevos | C6: 5 | D6: 6 | E6: 8 | F6: 9 | G6: 12 | H6: 2.5 | I6: =(C6*H6)/G6 -> 1.0416667 | J6: =D7*H7/G7 -> 0.2682 | K6: =(E6*H6)/G6 -> 1.6666667 | L6: =(F6*H6)/G6 -> 1.875
B7: Azucar | C7: 150 | D7: 180 | E7: 240 | F7: 270 | G7: 1000 | H7: 1.49 | I7: =(C7*H7)/G7 -> 0.2235 | J7: =D8*H8/G8 -> 0.29237288 | K7: =(E7*H7)/G7 -> 0.3576 | L7: =(F7*H7)/G7 -> 0.4023
B8: Vainilla | C8: 5 | D8: 10 | E8: 10 | F8: 15 | G8: 236 | H8: 6.9 | I8: =(C8*H8)/G8 -> 0.14618644 | J8: =D8*H8/G8 -> 0.29237288 | K8: =(E8*H8)/G8 -> 0.29237288 | L8: =(F8*H8)/G8 -> 0.43855932
I9: =SUM(I5:I8) -> 1.5718531 | J9: =SUM(J5:J8) -> 2.1029458 | K9: =SUM(K5:K8) -> 2.5734395 | L9: =SUM(L5:L8) -> 3.0047593
B11: Azucar | C11: 100 | D11: 120 | E11: 150 | F11: 200 | G11: 1000 | H11: 1.49 | I11: =(C11*H11)/G11 -> 0.149 | J11: =D11*H11/G11 -> 0.1788 | K11: =(E11*H11)/G11 -> 0.2235 | L11: =(F11*H11)/G11 -> 0.298
A12: ALMIBAR | B12: Agua | C12: 100 | D12: 120 | E12: 150 | F12: 200 | G12: 1000 | H12: 0.25 | I12: =(C12*H12)/G12 -> 0.025 | J12: =D12*H12/G12 -> 0.03 | K12: =(E12*H12)/G12 -> 0.0375 | L12: =(F12*H12)/G12 -> 0.05
B13: Vainilla | C13: 3 | D13: 4 | E13: 5 | F13: 9 | G13: 236 | H13: 6.9 | I13: =(C13*H13)/G13 -> 0.087711864 | J13: =D13*H13/G13 -> 0.11694915 | K13: =(E13*H13)/G13 -> 0.14618644 | L13: =(F13*H13)/G13 -> 0.26313559
I14: =SUM(I11:I13) -> 0.26171186 | J14: =SUM(J11:J13) -> 0.32574915 | K14: =SUM(K11:K13) -> 0.40718644 | L14: =SUM(L11:L13) -> 0.61113559
A16: RELLENO | B16: CHOCOLATE | C16: 100 | D16: 200 | E16: 300 | F16: 400 | G16: 100 | H16: 1.27 | I16: =(C16*H16)/G16 -> 1.27 | J16: =D16*H16/G16 -> 2.54 | K16: =(E16*H16)/G16 -> 3.81 | L16: =(F16*H16)/G16 -> 5.08
A17: TRUFA Y | B17: Nata | C17: 100 | D17: 200 | E17: 300 | F17: 400 | G17: 600 | H17: 2.36 | I17: =(C17*H17)/G17 -> 0.39333333 | J17: =D17*H17/G17 -> 0.78666667 | K17: =(E17*H17)/G17 -> 1.18 | L17: =(F17*H17)/G17 -> 1.5733333
A18: NATA | B18: Azucar | C18: 80 | D18: 80 | E18: 90 | F18: 100 | G18: 1000 | H18: 1.49 | I18: =(C18*H18)/G18 -> 0.1192 | J18: =D18*H18/G18 -> 0.1192 | K18: =(E18*H18)/G18 -> 0.1341 | L18: =(F18*H18)/G18 -> 0.149
B19: Vainilla | C19: 5 | D19: 5 | E19: 7 | F19: 9 | G19: 236 | H19: 6.9 | I19: =(C19*H19)/G19 -> 0.14618644 | J19: =D19*H19/G19 -> 0.14618644 | K19: =(E19*H19)/G19 -> 0.20466102 | L19: =(F19*H19)/G19 -> 0.26313559
B20: nata | C20: 100 | D20: 200 | E20: 300 | F20: 400 | G20: 600 | H20: 2.36 | I20: =(C20*H20)/G20 -> 0.39333333 | J20: =D20*H20/G20 -> 0.78666667 | K20: =(E20*H20)/G20 -> 1.18 | L20: =(F20*H20)/G20 -> 1.5733333
I21: =SUM(I16:I20) -> 2.3220531 | J21: =SUM(J16:J20) -> 4.3787198 | K21: =SUM(K16:K20) -> 6.508761 | L21: =SUM(L16:L20) -> 8.6388023
A23: COBERTURA | B23: AZUCAR | C23: 180 | D23: 180 | E23: 360 | F23: 360 | G23: 1000 | H23: 1.49 | I23: =(C23*H23)/G23 -> 0.2682 | J23: =D23*H23/G23 -> 0.2682 | K23: =(E23*H23)/G23 -> 0.5364 | L23: =(F23*H23)/G23 -> 0.5364
A24: YEMA | B24: AGUA | C24: 60 | D24: 60 | E24: 120 | F24: 120 | G24: 1000 | H24: 1 | I24: =(C24*H24)/G24 -> 0.06 | J24: =D24*H24/G24 -> 0.06 | K24: =(E24*H24)/G24 -> 0.12 | L24: =(F24*H24)/G24 -> 0.12
A25: Y NATA | B25: YEMAS | C25: 4 | D25: 4 | E25: 8 | F25: 8 | G25: 12 | H25: 2.5 | I25: =(C25*H25)/G25 -> 0.83333333 | J25: =D25*H25/G25 -> 0.83333333 | K25: =(E25*H25)/G25 -> 1.6666667 | L25: =(F25*H25)/G25 -> 1.6666667
B26: MAICENA | C26: 7 | D26: 7 | E26: 14 | F26: 14 | G26: 400 | H26: 4 | I26: =(C26*H26)/G26 -> 0.07 | J26: =D26*H26/G26 -> 0.07 | K26: =(E26*H26)/G26 -> 0.14 | L26: =(F26*H26)/G26 -> 0.14
I27: =SUM(I23:I26) -> 1.2315333 | J27: =SUM(J23:J26) -> 1.2315333 | K27: =SUM(K23:K26) -> 2.4630667 | L27: =SUM(L23:L26) -> 2.4630667
B29: papel horno | C29: 1 | D29: 1 | E29: 1 | F29: 1 | G29: 20 | H29: 1.13 | I29: =(C29*H29)/G29 -> 0.0565 | J29: =D29*H29/G29 -> 0.0565 | K29: =(C29*H29)/G29 -> 0.0565 | L29: =(F29*H29)/G29 -> 0.0565
B30: Papel plata | C30: 1 | D30: 1 | E30: 1 | F30: 1 | G30: 1000 | H30: 2.05 | I30: =(C30*H30)/G30 -> 0.00205 | J30: =D30*H30/G30 -> 0.00205 | K30: =(C30*H30)/G30 -> 0.00205 | L30: =(F30*H30)/G30 -> 0.00205
B31: Horno | C31: 30 | D31: 30 | E31: 35 | F31: 40 | G31: 60 | H31: 1 | I31: =(C31*H31)/G31 -> 0.5 | J31: =D31*H31/G31 -> 0.5 | K31: =(C31*H31)/G31 -> 0.5 | L31: =(F31*H31)/G31 -> 0.66666667
A32: COSTES | B32: Agua | C32: 12 | D32: 12 | E32: 12 | F32: 12 | G32: 1000 | H32: 1.97 | I32: =(C32*H32)/G32 -> 0.02364 | J32: =D32*H32/G32 -> 0.02364 | K32: =(C32*H32)/G32 -> 0.02364 | L32: =(F32*H32)/G32 -> 0.02364
A33: INDIRECTOS | B33: Batidora | C33: 12 | D33: 12 | E33: 12 | F33: 12 | G33: 60 | H33: 1 | I33: =(C33*H33)/G33 -> 0.2 | J33: =D33*H33/G33 -> 0.2 | K33: =(C33*H33)/G33 -> 0.2 | L33: =(F33*H33)/G33 -> 0.2
B34: CLARAS | C34: 2 | D34: 2 | E34: 2 | F34: 22 | G34: 12 | H34: 2.5 | I34: =(C34*H34)/G34 -> 0.41666667 | J34: =D34*H34/G34 -> 0.41666667 | K34: =(C34*H34)/G34 -> 0.41666667 | L34: =(F34*H34)/G34 -> 4.5833333
I37: =SUM(I29:I36) -> 1.1988567 | J37: =SUM(J29:J36) -> 1.1988567 | K37: =SUM(K29:K36) -> 1.1988567 | L37: =SUM(L29:L36) -> 5.53219
B40: Topper | C40: 1 | D40: 1 | E40: 1 | F40: 1 | G40: 1 | H40: 1.8 | I40: =(C40*H40)/G40 -> 1.8 | J40: =D40*H40/G40 -> 1.8 | K40: =(C40*H40)/G40 -> 1.8 | L40: =(F40*H40)/G40 -> 1.8
B41: Vela | C41: 1 | D41: 1 | E41: 1 | F41: 1 | G41: 6 | H41: 1 | I41: =(C41*H41)/G41 -> 0.16666667 | J41: =D41*H41/G41 -> 0.16666667 | K41: =(C41*H41)/G41 -> 0.16666667 | L41: =(F41*H41)/G41 -> 0.16666667
B42: Plato 25 cm | C42: 1 | D42: 1 | E42: 1 | F42: 1 | G42: 1 | H42: 0.9 | I42: =(C42*H42)/G42 -> 0.9 | J42: =D42*H42/G42 -> 0.9 | K42: =(C42*H42)/G42 -> 0.9 | L42: =(F42*H42)/G42 -> 0.9
A43: EXTRAS | B43: Caja 25,5 | C43: 1 | D43: 1 | E43: 1 | F43: 1 | G43: 1 | H43: 2 | I43: =(C43*H43)/G43 -> 2 | J43: =D43*H43/G43 -> 2 | K43: =(C43*H43)/G43 -> 2 | L43: =(F43*H43)/G43 -> 2
B44: Etiqueta | C44: 1 | D44: 1 | E44: 1 | F44: 1 | G44: 500 | H44: 0.85 | I44: =(C44*H44)/G44 -> 0.0017 | J44: =D44*H44/G44 -> 0.0017 | K44: =(C44*H44)/G44 -> 0.0017 | L44: =(F44*H44)/G44 -> 0.0017
B45: Banda | C45: 2 | D45: 2 | E45: 2 | F45: 2 | G45: 2 | H45: 0.18 | I45: =(C45*H45)/G45 -> 0.18 | J45: =D45*H45/G45 -> 0.18 | K45: =(C45*H45)/G45 -> 0.18 | L45: =(F45*H45)/G45 -> 0.18
B46: Sprinkles | C46: 10 | D46: 10 | E46: 10 | F46: 10 | G46: 100 | H46: 6 | I46: =(C46*H46)/G46 -> 0.6 | J46: =D46*H46/G46 -> 0.6 | K46: =(C46*H46)/G46 -> 0.6 | L46: =(F46*H46)/G46 -> 0.6
B47: Decoraciones | C47: 3 | D47: 3 | E47: 3 | F47: 3 | G47: 10 | H47: 1 | I47: =(C47*H47)/G47 -> 0.3 | J47: =D47*H47/G47 -> 0.3 | K47: =(C47*H47)/G47 -> 0.3 | L47: =(F47*H47)/G47 -> 0.3
I48: =SUM(I40:I47) -> 5.9483667 | J48: =SUM(J40:J47) -> 5.9483667 | K48: =SUM(K40:K47) -> 5.9483667 | L48: =SUM(L40:L47) -> 5.9483667
H50: COSTE PROD | I50: =SUM(I9+I14+I21+I27+I37+I48) -> 12.534375 | J50: =SUM(J9+J14+J21+J27+J37+J48) -> 15.186171 | K50: =SUM(K9+K14+K21+K27+K37+K48) -> 19.099677 | L50: =SUM(L9+L14+L21+L27+L37+L48) -> 26.198321
H51: PVP | I51: 30 | J51: 35 | K51: 40 | L51: 45
H52: GANANCIA | I52: =I51-I50 -> 17.465625 | J52: =J51-J50 -> 19.813829 | K52: =K51-K50 -> 20.900323 | L52: =L51-L50 -> 18.801679

Sheet TARTA OREO
C3: 8-10P | D3: 12-15 P | E3: 20 P | F3: 25P
B4: INGREDIENTES | C4: 16 CM | D4: 18,5 CM | E4: 20 CM | F4: 24 CM | G4: UNIDADES PAQ | H4: PRECIO | I4: COSTO 16 | J4: COSTO 18 | K4: COSTO 20 | L4: COSTO 24
B5: Harina | C5: 140 | D5: 170 | E5: 230 | F5: 260 | G5: 1000 | H5: 1.07 | I5: =(C5*H5)/G5 -> 0.1498 | J5: =D6*H6/G6 -> 1.25 | K5: =(E5*H5)/G5 -> 0.2461 | L5: =(F5*H5)/G5 -> 0.2782
A6: BiZCOCHO | B6: Huevos | C6: 5 | D6: 6 | E6: 8 | F6: 9 | G6: 12 | H6: 2.5 | I6: =(C6*H6)/G6 -> 1.0416667 | J6: =D7*H7/G7 -> 0.225 | K6: =(E6*H6)/G6 -> 1.6666667 | L6: =(F6*H6)/G6 -> 1.875
A7: CHOCOLATE | B7: Azucar | C7: 150 | D7: 180 | E7: 240 | F7: 270 | G7: 1000 | H7: 1.25 | I7: =(C7*H7)/G7 -> 0.1875 | J7: =D8*H8/G8 -> 0.29237288 | K7: =(E7*H7)/G7 -> 0.3 | L7: =(F7*H7)/G7 -> 0.3375
B8: Vainilla | C8: 5 | D8: 10 | E8: 10 | F8: 10 | G8: 236 | H8: 6.9 | I8: =(C8*H8)/G8 -> 0.14618644 | J8: =D9*H9/G9 -> 0.22727273 | K8: =(E8*H8)/G8 -> 0.29237288 | L8: =(F8*H8)/G8 -> 0.29237288
B9: GALLETA OREO | C9: 40 | D9: 50 | E9: 60 | F9: 70 | G9: 220 | H9: 1 | I9: =(C9*H9)/G9 -> 0.18181818 | J9: =D10*H10/G10 -> 0.72 | K9: =(E9*H9)/G9 -> 0.27272727 | L9: =(F9*H9)/G9 -> 0.31818182
B10: Cacao | C10: 30 | D10: 30 | E10: 40 | F10: 50 | G10: 250 | H10: 6 | I10: =(C10*H10)/G10 -> 0.72 | J10: =D11*H11/G11 -> 0.07475 | K10: =(E10*H10)/G10 -> 0.96 | L10: =(F10*H10)/G10 -> 1.2
B11: Maicena | C11: 20 | D11: 10 | E11: 10 | F11: 10 | G11: 400 | H11: 2.99 | I11: =(C11*H11)/G11 -> 0.1495 | J11: =D11*H11/G11 -> 0.07475 | K11: =(E11*H11)/G11 -> 0.07475 | L11: =(F11*H11)/G11 -> 0.07475
I12: =SUM(I5:I11) -> 2.5764713 | J12: =SUM(J5:J11) -> 2.8641456 | K12: =SUM(K5:K11) -> 3.8126168 | L12: =SUM(L5:L11) -> 4.3760047
B14: Azucar | C14: 100 | D14: 120 | E14: 150 | F14: 200 | G14: 1000 | H14: 1.25 | I14: =(C14*H14)/G14 -> 0.125 | J14: =D14*H14/G14 -> 0.15 | K14: =(E14*H14)/G14 -> 0.1875 | L14: =(F14*H14)/G14 -> 0.25
A15: ALMIBAR | B15: Agua | C15: 100 | D15: 120 | E15: 150 | F15: 200 | G15: 1000 | H15: 0.25 | I15: =(C15*H15)/G15 -> 0.025 | J15: =D15*H15/G15 -> 0.03 | K15: =(E15*H15)/G15 -> 0.0375 | L15: =(F15*H15)/G15 -> 0.05
B16: Vainilla | C16: 3 | D16: 4 | E16: 5 | F16: 9 | G16: 236 | H16: 6.9 | I16: =(C16*H16)/G16 -> 0.087711864 | J16: =D16*H16/G16 -> 0.11694915 | K16: =(E16*H16)/G16 -> 0.14618644 | L16: =(F16*H16)/G16 -> 0.26313559
I17: =SUM(I14:I16) -> 0.23771186 | J17: =SUM(J14:J16) -> 0.29694915 | K17: =SUM(K14:K16) -> 0.37118644 | L17: =SUM(L14:L16) -> 0.56313559
B19: Nata | C19: 300 | D19: 400 | E19: 500 | F19: 600 | G19: 600 | H19: 2.36 | I19: =(C19*H19)/G19 -> 1.18 | J19: =(D19*H19)/G19 -> 1.5733333 | K19: =(E19*H19)/G19 -> 1.9666667 | L19: =(F19*H19)/G19 -> 2.36
A20: RELLENO | B20: Queso phila | C20: 100 | D20: 150 | E20: 200 | F20: 200 | G20: 250 | H20: 2 | I20: =(C20*H20)/G20 -> 0.8 | J20: =(D20*H20)/G20 -> 1.2 | K20: =(E20*H20)/G20 -> 1.6 | L20: =(F20*H20)/G20 -> 1.6
A21: OREO | B21: OREO GALLETA | C21: 100 | D21: 120 | E21: 140 | F21: 150 | G21: 220 | H21: 1 | I21: =(C21*H21)/G21 -> 0.45454545 | J21: =(D21*H21)/G21 -> 0.54545455 | K21: =(E21*H21)/G21 -> 0.63636364 | L21: =(F21*H21)/G21 -> 0.68181818
B22: Azucar blanca | C22: 80 | D22: 90 | E22: 100 | F22: 120 | G22: 1000 | H22: 1.49 | I22: =(C22*H22)/G22 -> 0.1192 | J22: =(D22*H22)/G22 -> 0.1341 | K22: =(E22*H22)/G22 -> 0.149 | L22: =(F22*H22)/G22 -> 0.1788
B23: Vainilla | C23: 5 | D23: 7 | E23: 9 | F23: 8 | G23: 236 | H23: 6.9 | I23: =(C23*H23)/G23 -> 0.14618644 | J23: =(D23*H23)/G23 -> 0.20466102 | K23: =(E23*H23)/G23 -> 0.26313559 | L23: =(F23*H23)/G23 -> 0.23389831
I24: =SUM(I19:I23) -> 2.6999319 | J24: =SUM(J19:J23) -> 3.6575489 | K24: =SUM(K19:K23) -> 4.6151659 | L24: =SUM(L19:L23) -> 5.0545165
A26: COBERTURA | B26: Nata | C26: 150 | D26: 200 | E26: 200 | F26: 450 | G26: 600 | H26: 2.36 | I26: =(C26*H26)/G26 -> 0.59 | J26: =(D26*H26)/G26 -> 0.78666667 | K26: =(E26*H26)/G26 -> 0.78666667 | L26: =(F26*H26)/G26 -> 1.77
A27: CREMA DE | B27: CHOCOLATE | C27: 500 | D27: 600 | E27: 600 | F27: 900 | G27: 100 | H27: 1.15 | I27: =(C27*H27)/G27 -> 5.75 | J27: =(D27*H27)/G27 -> 6.9 | K27: =(E27*H27)/G27 -> 6.9 | L27: =(F27*H27)/G27 -> 10.35
A28: GANACHE | B28: OREO DECORAR | C28: 50 | D28: 70 | E28: 90 | F28: 100 | G28: 100 | H28: 0.79 | I28: =(C28*H28)/G28 -> 0.395 | J28: =(D28*H28)/G28 -> 0.553 | K28: =(E28*H28)/G28 -> 0.711 | L28: =(F28*H28)/G28 -> 0.79
B29: OREO DECORAR | C29: 50 | D29: 70 | E29: 90 | F29: 100 | G29: 220 | H29: 1 | I29: =(C29*H29)/G29 -> 0.22727273 | J29: =(D29*H29)/G29 -> 0.31818182 | K29: =(E29*H29)/G29 -> 0.40909091 | L29: =(F29*H29)/G29 -> 0.45454545
I30: =SUM(I26:I29) -> 6.9622727 | J30: =SUM(J26:J29) -> 8.5578485 | K30: =SUM(K26:K29) -> 8.8067576 | L30: =SUM(L26:L29) -> 13.364545
B32: papel horno | C32: 1 | D32: 1 | E32: 1 | F32: 1 | G32: 20 | H32: 1.13 | I32: =(C32*H32)/G32 -> 0.0565 | J32: =D32*H32/G32 -> 0.0565 | K32: =(C32*H32)/G32 -> 0.0565 | L32: =(F32*H32)/G32 -> 0.0565
B33: Papel plata | C33: 1 | D33: 1 | E33: 1 | F33: 1 | G33: 1000 | H33: 2.05 | I33: =(C33*H33)/G33 -> 0.00205 | J33: =D33*H33/G33 -> 0.00205 | K33: =(C33*H33)/G33 -> 0.00205 | L33: =(F33*H33)/G33 -> 0.00205
B34: Horno | C34: 30 | D34: 30 | E34: 35 | F34: 40 | G34: 60 | H34: 1 | I34: =(C34*H34)/G34 -> 0.5 | J34: =D34*H34/G34 -> 0.5 | K34: =(C34*H34)/G34 -> 0.5 | L34: =(F34*H34)/G34 -> 0.66666667
A35: COSTES | B35: Agua | C35: 12 | D35: 12 | E35: 12 | F35: 12 | G35: 1000 | H35: 1.97 | I35: =(C35*H35)/G35 -> 0.02364 | J35: =D35*H35/G35 -> 0.02364 | K35: =(C35*H35)/G35 -> 0.02364 | L35: =(F35*H35)/G35 -> 0.02364
A36: INDIRECTOS | B36: Batidora | C36: 12 | D36: 12 | E36: 12 | F36: 12 | G36: 60 | H36: 1 | I36: =(C36*H36)/G36 -> 0.2 | J36: =D36*H36/G36 -> 0.2 | K36: =(C36*H36)/G36 -> 0.2 | L36: =(F36*H36)/G36 -> 0.2
I40: =SUM(I32:I39) -> 0.78219 | J40: =SUM(J32:J39) -> 0.78219 | K40: =SUM(K32:K39) -> 0.78219 | L40: =SUM(L32:L39) -> 0.94885667
B43: Topper | C43: 1 | D43: 1 | E43: 1 | F43: 1 | G43: 1 | H43: 1.8 | I43: =(C43*H43)/G43 -> 1.8 | J43: =(C43*H43)/G43 -> 1.8 | K43: =(E43*H43)/G43 -> 1.8 | L43: =(F43*H43)/G43 -> 1.8
B44: Vela | C44: 1 | D44: 1 | E44: 1 | F44: 1 | G44: 6 | H44: 1 | I44: =(C44*H44)/G44 -> 0.16666667 | J44: =(C44*H44)/G44 -> 0.16666667 | K44: =(E44*H44)/G44 -> 0.16666667 | L44: =(F44*H44)/G44 -> 0.16666667
B45: Plato 25 cm | C45: 1 | D45: 1 | E45: 1 | F45: 0 | G45: 1 | H45: 0.9 | I45: =(C45*H45)/G45 -> 0.9 | J45: =(C45*H45)/G45 -> 0.9 | K45: =(E45*H45)/G45 -> 0.9 | L45: =(F45*H45)/G45 -> 0
A46: EXTRAS | B46: Caja 25,5 | C46: 1 | D46: 1 | E46: 1 | F46: 0 | G46: 1 | H46: 2 | I46: =(C46*H46)/G46 -> 2 | J46: =(C46*H46)/G46 -> 2 | K46: =(E46*H46)/G46 -> 2 | L46: =(F46*H46)/G46 -> 0
B47: Etiqueta | C47: 1 | D47: 1 | E47: 1 | F47: 1 | G47: 500 | H47: 0.85 | I47: =(C47*H47)/G47 -> 0.0017 | J47: =(C47*H47)/G47 -> 0.0017 | K47: =(E47*H47)/G47 -> 0.0017 | L47: =(F47*H47)/G47 -> 0.0017
B48: Banda | C48: 2 | D48: 2 | E48: 2 | F48: 1 | G48: 2 | H48: 0.18 | I48: =(C48*H48)/G48 -> 0.18 | J48: =(C48*H48)/G48 -> 0.18 | K48: =(E48*H48)/G48 -> 0.18 | L48: =(F48*H48)/G48 -> 0.09
B49: plato 28 cm | C49: 0 | D49: 0 | E49: 0 | F49: 1 | G49: 1 | H49: 0.9 | I49: =(C49*H49)/G49 -> 0 | J49: =(C49*H49)/G49 -> 0 | K49: =(E49*H49)/G49 -> 0 | L49: =(F49*H49)/G49 -> 0.9
B50: caja 28 cm | C50: 0 | D50: 0 | E50: 0 | F50: 1 | G50: 1 | H50: 2 | I50: =(C50*H50)/G50 -> 0 | J50: =(C50*H50)/G50 -> 0 | K50: =(E50*H50)/G50 -> 0 | L50: =(F50*H50)/G50 -> 2
B51: Sprinkles | C51: 10 | D51: 10 | E51: 10 | F51: 12 | G51: 100 | H51: 6 | I51: =(C51*H51)/G51 -> 0.6 | J51: =(C51*H51)/G51 -> 0.6 | K51: =(E51*H51)/G51 -> 0.6 | L51: =(F51*H51)/G51 -> 0.72
B52: Decoraciones | C52: 3 | D52: 3 | E52: 3 | F52: 3 | G52: 10 | H52: 10 | I52: =(C52*H52)/G52 -> 3 | J52: =(C52*H52)/G52 -> 3 | K52: =(E52*H52)/G52 -> 3 | L52: =(F52*H52)/G52 -> 3
I53: =SUM(I43:I52) -> 8.6483667 | J53: =SUM(J43:J52) -> 8.6483667 | K53: =SUM(K43:K52) -> 8.6483667 | L53: =SUM(L43:L52) -> 8.6783667
I54: 8-10 PORCIONES | J54: 12-15 PORCIONES | K54: 20 PORCIONES
H58: COSTE PROD | I58: =SUM(I12+I17+I24+I30+I40+I53) -> 21.906944 | J58: =SUM(J12+J17+J24+J30+J40+J53) -> 24.807049 | K58: =SUM(K12+K17+K24+K30+K40+K53) -> 27.036283 | L58: =SUM(L12+L17+L24+L30+L40+L53) -> 32.985426
H59: PVP | I59: 40 | J59: 45 | K59: 50 | L59: 55
H60: GANACIA | I60: =I59-I58 -> 18.093056 | J60: =J59-J58 -> 20.192951 | K60: =K59-K58 -> 22.963717 | L60: =SUM(L59-L58) -> 22.014574

Sheet CHEESECAKE
C2: FRUTOS ROJOS
A3: INGREDIENTES | B3: 16 CM | C3: 18 CM | D3: 20CM | E3: 24 CM | F3: PRECIO | G3: UN PAQUETE | H3: COSTE 16 CM | I3: COSTE 18 CM | J3: COSTE 20 CM | K3: COSTE 24 CM
A4: GALLETA RELIEVE | B4: 125 | C4: 175 | D4: 245 | E4: 345 | F4: 1.65 | G4: 735 | H4: =B4*F4/G4 -> 0.28061224 | I4: =C4*F4/G4 -> 0.39285714 | J4: =D4*F4/G4 -> 0.55 | K4: =E4*F4/G4 -> 0.7744898
A5: MANTEQUILLA | B5: 100 | C5: 150 | D5: 200 | E5: 300 | F5: 2.39 | G5: 250 | H5: =B5*F5/G5 -> 0.956 | I5: =C5*F5/G5 -> 1.434 | J5: =D5*F5/G5 -> 1.912 | K5: =E5*F5/G5 -> 2.868
A6: QUESO MASCARPONE | B6: 150 | C6: 200 | D6: 250 | E6: 300 | F6: 2.65 | G6: 250 | H6: =B6*F6/G6 -> 1.59 | I6: =C6*F6/G6 -> 2.12 | J6: =D6*F6/G6 -> 2.65 | K6: =E6*F6/G6 -> 3.18
A7: QUESO PHILA | B7: 150 | C7: 200 | D7: 250 | E7: 300 | F7: 2.78 | G7: 250 | H7: =B7*F7/G7 -> 1.668 | I7: =C7*F7/G7 -> 2.224 | J7: =D7*F7/G7 -> 2.78 | K7: =E7*F7/G7 -> 3.336
A8: NATA | B8: 100 | C8: 150 | D8: 200 | E8: 300 | F8: 2.39 | G8: 600 | H8: =B8*F8/G8 -> 0.39833333 | I8: =C8*F8/G8 -> 0.5975 | J8: =D8*F8/G8 -> 0.79666667 | K8: =E8*F8/G8 -> 1.195
A9: LIMON | B9: 1 | C9: 1 | D9: 1 | E9: 1 | F9: 0.59 | G9: 1 | H9: =B9*F9/G9 -> 0.59 | I9: =C9*F9/G9 -> 0.59 | J9: =D9*F9/G9 -> 0.59 | K9: =E9*F9/G9 -> 0.59
A10: VAINILLA | B10: 5 | C10: 5 | D10: 4 | E10: 4 | F10: 6.9 | G10: 236 | H10: =B10*F10/G10 -> 0.14618644 | I10: =C10*F10/G10 -> 0.14618644 | J10: =D10*F10/G10 -> 0.11694915 | K10: =E10*F10/G10 -> 0.11694915
A11: FRUTOS ROJOS | B11: 300 | C11: 300 | D11: 300 | E11: 350 | F11: 1.68 | G11: 300 | H11: =B11*F11/G11 -> 1.68 | I11: =C11*F11/G11 -> 1.68 | J11: =D11*F11/G11 -> 1.68 | K11: =E11*F11/G11 -> 1.96
H12: =SUM(H4:H11) -> 7.309132 | I12: =SUM(I4:I11) -> 9.1845436 | J12: =SUM(J4:J11) -> 11.075616 | K12: =SUM(K4:K11) -> 14.020439
A14: PAPEL PLATA | B14: 0.6 | C14: 0.6 | D14: 0.6 | E14: 0.6 | F14: 2.35 | G14: 30 | H14: =B14*F14/G14 -> 0.047 | I14: =C14*F14/G14 -> 0.047 | J14: =D14*F14/G14 -> 0.047 | K14: =E14*F14/G14 -> 0.047
A15: HORNO | B15: 1 | C15: 1 | D15: 1 | E15: 1 | F15: 1.13 | G15: 20 | H15: =B15*F15/G15 -> 0.0565 | I15: =C15*F15/G15 -> 0.0565 | J15: =D15*F15/G15 -> 0.0565 | K15: =E15*F15/G15 -> 0.0565
A16: NEVERA | B16: 1 | C16: 1 | D16: 1 | E16: 1 | F16: 1.13 | G16: 20 | H16: =B16*F16/G16 -> 0.0565 | I16: =C16*F16/G16 -> 0.0565 | J16: =D16*F16/G16 -> 0.0565 | K16: =E16*F16/G16 -> 0.0565
A17: TOPPER | B17: 1 | C17: 1 | D17: 1 | E17: 1 | F17: 0.75 | G17: 1 | H17: =B17*F17/G17 -> 0.75 | I17: =C17*F17/G17 -> 0.75 | J17: =D17*F17/G17 -> 0.75 | K17: =E17*F17/G17 -> 0.75
A18: VELA | B18: 1 | C18: 1 | D18: 1 | E18: 1 | F18: 1 | G18: 20 | H18: =B18*F18/G18 -> 0.05 | I18: =C18*F18/G18 -> 0.05 | J18: =D18*F18/G18 -> 0.05 | K18: =E18*F18/G18 -> 0.05
A19: PLATO 20 CM | B19: 1 | D19: 1 | F19: 0.75 | G19: 1 | H19: =B19*F19/G19 -> 0.75 | I19: =C19*F19/G19 -> 0 | J19: =D19*F19/G19 -> 0.75 | K19: =E19*F19/G19 -> 0
A20: PLATO 25-24 CM | C20: 1 | D20: 1 | E20: 1 | F20: 0.85 | G20: 1 | H20: =B20*F20/G20 -> 0 | I20: =C20*F20/G20 -> 0.85 | J20: =D20*F20/G20 -> 0.85 | K20: =E20*F20/G20 -> 0.85
A21: CAJA 20 CM | B21: 1 | D21: 1 | F21: 1.95 | G21: 1 | H21: =B21*F21/G21 -> 1.95 | I21: =C21*F21/G21 -> 0 | J21: =D21*F21/G21 -> 1.95 | K21: =E21*F21/G21 -> 0
A22: CAJA 25X25 | C22: 1 | D22: 1 | E22: 1 | F22: 2.2 | G22: 1 | H22: =B22*F22/G22 -> 0 | I22: =C22*F22/G22 -> 2.2 | J22: =D22*F22/G22 -> 2.2 | K22: =E22*F22/G22 -> 2.2
H23: =SUM( H14:H22) -> 3.66 | I23: =SUM(I14:I22) -> 4.01 | J23: =SUM(J14:J22) -> 6.71 | K23: =SUM(K14:K22) -> 4.01
G26: COSTE TOTAL | H26: =SUM(H12+H23) -> 10.969132 | I26: =SUM(I12+I23) -> 13.194544 | J26: =SUM(J12+J23) -> 17.785616 | K26: =SUM(K12+K23) -> 18.030439
G27: PRECIO VENTA | H27: 18 | I27: 22 | J27: 28 | K27: 30
G28: GANANCIA | H28: =H27-H26 -> 7.030868 | I28: =I27-I26 -> 8.8054564 | J28: =J27-J26 -> 10.214384 | K28: =K27-K26 -> 11.969561
C32: DULCE DE LECHE O LOTUS
A33: INGREDIENTES | B33: 16 CM | C33: 18 CM | D33: 20CM | E33: 24 CM | F33: PRECIO | G33: UN PAQUETE | H33: COSTE 16 CM | I33: COSTE 18 CM | J33: COSTE 20 CM | K33: COSTE 24 CM
A34: GALLETA RELIEVE | B34: 125 | C34: 175 | D34: 245 | E34: 345 | F34: 1.65 | G34: 735 | H34: =B34*F34/G34 -> 0.28061224 | I34: =C34*F34/G34 -> 0.39285714 | J34: =D34*F34/G34 -> 0.55 | K34: =E34*F34/G34 -> 0.7744898
A35: MANTEQUILLA | B35: 100 | C35: 150 | D35: 200 | E35: 300 | F35: 2.39 | G35: 250 | H35: =B35*F35/G35 -> 0.956 | I35: =C35*F35/G35 -> 1.434 | J35: =D35*F35/G35 -> 1.912 | K35: =E35*F35/G35 -> 2.868
A36: QUESO MASCARPONE | B36: 100 | C36: 150 | D36: 200 | E36: 250 | F36: 2.65 | G36: 250 | H36: =B36*F36/G36 -> 1.06 | I36: =C36*F36/G36 -> 1.59 | J36: =D36*F36/G36 -> 2.12 | K36: =E36*F36/G36 -> 2.65
A37: DULCE DE LECHE | B37: 100 | C37: 150 | D37: 200 | E37: 250 | F37: 5 | G37: 1000 | H37: =B37*F37/G37 -> 0.5 | I37: =C37*F37/G37 -> 0.75 | J37: =D37*F37/G37 -> 1 | K37: =E37*F37/G37 -> 1.25
A38: QUESO PHILA | B38: 100 | C38: 150 | D38: 200 | E38: 250 | F38: 2.78 | G38: 250 | H38: =B38*F38/G38 -> 1.112 | I38: =C38*F38/G38 -> 1.668 | J38: =D38*F38/G38 -> 2.224 | K38: =E38*F38/G38 -> 2.78
A39: NATA | B39: 100 | C39: 150 | D39: 200 | E39: 300 | F39: 2.39 | G39: 600 | H39: =B39*F39/G39 -> 0.39833333 | I39: =C39*F39/G39 -> 0.5975 | J39: =D39*F39/G39 -> 0.79666667 | K39: =E39*F39/G39 -> 1.195
A40: LIMON | B40: 1 | C40: 1 | D40: 1 | E40: 1 | F40: 0.59 | G40: 1 | H40: =B40*F40/G40 -> 0.59 | I40: =C40*F40/G40 -> 0.59 | J40: =D40*F40/G40 -> 0.59 | K40: =E40*F40/G40 -> 0.59
A41: VAINILLA | B41: 5 | C41: 5 | D41: 4 | E41: 4 | F41: 6.9 | G41: 236 | H41: =B41*F41/G41 -> 0.14618644 | I41: =C41*F41/G41 -> 0.14618644 | J41: =D41*F41/G41 -> 0.11694915 | K41: =E41*F41/G41 -> 0.11694915
A42: DDL DECORACION | B42: 100 | C42: 150 | D42: 200 | E42: 250 | F42: 5 | G42: 1000 | H42: =B42*F42/G42 -> 0.5 | I42: =C42*F42/G42 -> 0.75 | J42: =D42*F42/G42 -> 1 | K42: =E42*F42/G42 -> 1.25
H43: =SUM(H34:H42) -> 5.543132 | I43: =SUM(I34:I42) -> 7.9185436 | J43: =SUM(J34:J42) -> 10.309616 | K43: =SUM(K34:K42) -> 13.474439
A44: PAPEL PLATA | B44: 0.6 | C44: 0.6 | D44: 0.6 | E44: 0.6 | F44: 2.35 | G44: 30 | H44: =B44*F44/G44 -> 0.047 | I44: =C44*F44/G44 -> 0.047 | J44: =D44*F44/G44 -> 0.047 | K44: =E44*F44/G44 -> 0.047
A45: HORNO | B45: 1 | C45: 1 | D45: 1 | E45: 1 | F45: 1.13 | G45: 20 | H45: =B45*F45/G45 -> 0.0565 | I45: =C45*F45/G45 -> 0.0565 | J45: =D45*F45/G45 -> 0.0565 | K45: =E45*F45/G45 -> 0.0565
A46: NEVERA | B46: 1 | C46: 1 | D46: 1 | E46: 1 | F46: 1.13 | G46: 20 | H46: =B46*F46/G46 -> 0.0565 | I46: =C46*F46/G46 -> 0.0565 | J46: =D46*F46/G46 -> 0.0565 | K46: =E46*F46/G46 -> 0.0565
A47: TOPPER | B47: 1 | C47: 1 | D47: 1 | E47: 1 | F47: 0.75 | G47: 1 | H47: =B47*F47/G47 -> 0.75 | I47: =C47*F47/G47 -> 0.75 | J47: =D47*F47/G47 -> 0.75 | K47: =E47*F47/G47 -> 0.75
A48: VELA | B48: 1 | C48: 1 | D48: 1 | E48: 1 | F48: 1 | G48: 20 | H48: =B48*F48/G48 -> 0.05 | I48: =C48*F48/G48 -> 0.05 | J48: =D48*F48/G48 -> 0.05 | K48: =E48*F48/G48 -> 0.05
A49: PLATO 20 CM | B49: 1 | D49: 1 | F49: 0.75 | G49: 1 | H49: =B49*F49/G49 -> 0.75 | I49: =C49*F49/G49 -> 0 | J49: =D49*F49/G49 -> 0.75 | K49: =E49*F49/G49 -> 0
A50: PLATO 25-24 CM | C50: 1 | D50: 1 | E50: 1 | F50: 0.85 | G50: 1 | H50: =B50*F50/G50 -> 0 | I50: =C50*F50/G50 -> 0.85 | J50: =D50*F50/G50 -> 0.85 | K50: =E50*F50/G50 -> 0.85
A51: CAJA 20 CM | B51: 1 | D51: 1 | F51: 1.95 | G51: 1 | H51: =B51*F51/G51 -> 1.95 | I51: =C51*F51/G51 -> 0 | J51: =D51*F51/G51 -> 1.95 | K51: =E51*F51/G51 -> 0
A52: CAJA 25X25 | C52: 1 | D52: 1 | E52: 1 | F52: 2.2 | G52: 1 | H52: =B52*F52/G52 -> 0 | I52: =C52*F52/G52 -> 2.2 | J52: =D52*F52/G52 -> 2.2 | K52: =E52*F52/G52 -> 2.2
H53: =SUM( H44:H52) -> 3.66 | I53: =SUM(I44:I52) -> 4.01 | J53: =SUM(J44:J52) -> 6.71 | K53: =SUM(K44:K52) -> 4.01
G55: COSTE TOTAL | H55: =SUM(H43+H53) -> 9.203132 | I55: =SUM(I43+I53) -> 11.928544 | J55: =SUM(J43+J53) -> 17.019616 | K55: =SUM(K43+K53) -> 17.484439
G56: PRECIO VENTA | H56: 18 | I56: 22 | J56: 28 | K56: 30
G57: GANANCIA | H57: =SUM(H56-H55) -> 8.796868 | I57: =SUM(I56-I55) -> 10.071456 | J57: =SUM(J56-J55) -> 10.980384 | K57: =SUM(K56-K55) -> 12.515561

Sheet TARTA FRESAS CON NATA
A1: TARTA FRESAS CON NATA
B3: INGREDIENTES | C3: CANT 8-10 p | D3: CANT 12-15 | E3: CANT 18-20 p | F3: CANT 25-28 | G3: UNIDADES PAQ | H3: PRECIO | I3: COSTO 8-10 p | J3: COSTO 12-15 | K3: COSTO 18-20 p | L3: COSTO 25-28
A5: BIZCOCHO | B5: Harina | C5: 150 | D5: 180 | E5: 240 | F5: 270 | G5: 1000 | H5: 1.07 | I5: =(C5*H5)/G5 -> 0.1605 | J5: =D6*H6/G6 -> 1.25 | K5: =(E5*H5)/G5 -> 0.2568 | L5: =(F5*H5)/G5 -> 0.2889
A6: VAINILLA | B6: Huevos | C6: 5 | D6: 6 | E6: 8 | F6: 9 | G6: 12 | H6: 2.5 | I6: =(C6*H6)/G6 -> 1.0416667 | J6: =D7*H7/G7 -> 0.225 | K6: =(E6*H6)/G6 -> 1.6666667 | L6: =(F6*H6)/G6 -> 1.875
B7: Azucar | C7: 150 | D7: 180 | E7: 240 | F7: 270 | G7: 1000 | H7: 1.25 | I7: =(C7*H7)/G7 -> 0.1875 | J7: =D8*H8/G8 -> 0.29237288 | K7: =(E7*H7)/G7 -> 0.3 | L7: =(F7*H7)/G7 -> 0.3375
B8: Vainilla | C8: 5 | D8: 10 | E8: 10 | F8: 15 | G8: 236 | H8: 6.9 | I8: =(C8*H8)/G8 -> 0.14618644 | J8: =D8*H8/G8 -> 0.29237288 | K8: =(E8*H8)/G8 -> 0.29237288 | L8: =(F8*H8)/G8 -> 0.43855932
I9: =SUM(I5:I8) -> 1.5358531 | J9: =SUM(J5:J8) -> 2.0597458 | K9: =SUM(K5:K8) -> 2.5158395 | L9: =SUM(L5:L8) -> 2.9399593
B11: Azucar | C11: 100 | D11: 120 | E11: 150 | F11: 200 | G11: 1000 | H11: 1.25 | I11: =(C11*H11)/G11 -> 0.125 | J11: =D11*H11/G11 -> 0.15 | K11: =(E11*H11)/G11 -> 0.1875 | L11: =(F11*H11)/G11 -> 0.25
A12: ALMIBAR | B12: Agua | C12: 100 | D12: 120 | E12: 150 | F12: 200 | G12: 1000 | H12: 0.25 | I12: =(C12*H12)/G12 -> 0.025 | J12: =D12*H12/G12 -> 0.03 | K12: =(E12*H12)/G12 -> 0.0375 | L12: =(F12*H12)/G12 -> 0.05
B13: Vainilla | C13: 3 | D13: 4 | E13: 5 | F13: 9 | G13: 236 | H13: 6.9 | I13: =(C13*H13)/G13 -> 0.087711864 | J13: =D13*H13/G13 -> 0.11694915 | K13: =(E13*H13)/G13 -> 0.14618644 | L13: =(F13*H13)/G13 -> 0.26313559
I14: =SUM(I11:I13) -> 0.23771186 | J14: =SUM(J11:J13) -> 0.29694915 | K14: =SUM(K11:K13) -> 0.37118644 | L14: =SUM(L11:L13) -> 0.56313559
A15: RELLENO | B15: QUESO | C15: 150 | D15: 200 | E15: 200 | F15: 250 | G15: 1000 | H15: 3.85 | I15: =(C15*H15)/G15 -> 0.5775 | J15: =D15*H15/G15 -> 0.77 | K15: =(E15*H15)/G15 -> 0.77 | L15: =(F15*H15)/G15 -> 0.9625
A16: D.D.L Y | B16: Nata | C16: 300 | D16: 300 | E16: 600 | F16: 700 | G16: 600 | H16: 2.19 | I16: =(C16*H16)/G16 -> 1.095 | J16: =D16*H16/G16 -> 1.095 | K16: =(E16*H16)/G16 -> 2.19 | L16: =(F16*H16)/G16 -> 2.555
A17: NATA + melocoton | B17: Azucar | C17: 80 | D17: 80 | E17: 90 | F17: 100 | G17: 1000 | H17: 1.25 | I17: =(C17*H17)/G17 -> 0.1 | J17: =D17*H17/G17 -> 0.1 | K17: =(E17*H17)/G17 -> 0.1125 | L17: =(F17*H17)/G17 -> 0.125
B18: Vainilla | C18: 5 | D18: 5 | E18: 7 | F18: 9 | G18: 236 | H18: 6.9 | I18: =(C18*H18)/G18 -> 0.14618644 | J18: =D18*H18/G18 -> 0.14618644 | K18: =(E18*H18)/G18 -> 0.20466102 | L18: =(F18*H18)/G18 -> 0.26313559
B19: FRESAS | C19: 100 | D19: 120 | E19: 150 | F19: 200 | G19: 1000 | H19: 5 | I19: =(C19*H19)/G19 -> 0.5 | J19: =D19*H19/G19 -> 0.6 | K19: =(E19*H19)/G19 -> 0.75 | L19: =(F19*H19)/G19 -> 1
I20: =SUM(I15:I19) -> 2.4186864 | J20: =SUM(J15:J19) -> 2.7111864 | K20: =SUM(K15:K19) -> 4.027161 | L20: =SUM(L15:L19) -> 4.9056356
A22: COBERTURA | B22: Nata | C22: 300 | D22: 350 | E22: 300 | F22: 400 | G22: 600 | H22: 2.19 | I22: =(C22*H22)/G22 -> 1.095 | J22: =D22*H22/G22 -> 1.2775 | K22: =(E22*H22)/G22 -> 1.095 | L22: =(F22*H22)/G22 -> 1.46
A23: CREMA DE | B23: Queso phila | C23: 100 | D23: 120 | E23: 200 | F23: 250 | G23: 250 | H23: 1.1 | I23: =(C23*H23)/G23 -> 0.44 | J23: =D23*H23/G23 -> 0.528 | K23: =(E23*H23)/G23 -> 0.88 | L23: =(F23*H23)/G23 -> 1.1
A24: QUESO | B24: Azucar glass | C24: 50 | D24: 60 | E24: 70 | F24: 90 | G24: 1000 | H24: 4.5 | I24: =(C24*H24)/G24 -> 0.225 | J24: =D24*H24/G24 -> 0.27 | K24: =(E24*H24)/G24 -> 0.315 | L24: =(F24*H24)/G24 -> 0.405
B25: Vainilla | C25: 5 | D25: 5 | E25: 7 | F25: 9 | G25: 236 | H25: 6.9 | I25: =(C25*H25)/G25 -> 0.14618644 | J25: =D25*H25/G25 -> 0.14618644 | K25: =(E25*H25)/G25 -> 0.20466102 | L25: =(F25*H25)/G25 -> 0.26313559
I26: =SUM(I22:I25) -> 1.9061864 | J26: =SUM(J22:J25) -> 2.2216864 | K26: =SUM(K22:K25) -> 2.494661 | L26: =SUM(L22:L25) -> 3.2281356
B28: papel horno | C28: 1 | D28: 1 | E28: 1 | F28: 1 | G28: 20 | H28: 1.13 | I28: =(C28*H28)/G28 -> 0.0565 | J28: =D28*H28/G28 -> 0.0565 | K28: =(C28*H28)/G28 -> 0.0565 | L28: =(F28*H28)/G28 -> 0.0565
B29: Papel plata | C29: 1 | D29: 1 | E29: 1 | F29: 1 | G29: 1000 | H29: 2.05 | I29: =(C29*H29)/G29 -> 0.00205 | J29: =D29*H29/G29 -> 0.00205 | K29: =(C29*H29)/G29 -> 0.00205 | L29: =(F29*H29)/G29 -> 0.00205
B30: Horno | C30: 30 | D30: 30 | E30: 35 | F30: 40 | G30: 60 | H30: 1 | I30: =(C30*H30)/G30 -> 0.5 | J30: =D30*H30/G30 -> 0.5 | K30: =(C30*H30)/G30 -> 0.5 | L30: =(F30*H30)/G30 -> 0.66666667
A31: COSTES | B31: Agua | C31: 12 | D31: 12 | E31: 12 | F31: 12 | G31: 1000 | H31: 1.97 | I31: =(C31*H31)/G31 -> 0.02364 | J31: =D31*H31/G31 -> 0.02364 | K31: =(C31*H31)/G31 -> 0.02364 | L31: =(F31*H31)/G31 -> 0.02364
A32: INDIRECTOS | B32: Batidora | C32: 12 | D32: 12 | E32: 12 | F32: 12 | G32: 60 | H32: 1 | I32: =(C32*H32)/G32 -> 0.2 | J32: =D32*H32/G32 -> 0.2 | K32: =(C32*H32)/G32 -> 0.2 | L32: =(F32*H32)/G32 -> 0.2
I36: =SUM(I28:I35) -> 0.78219 | J36: =SUM(J28:J35) -> 0.78219 | K36: =SUM(K28:K35) -> 0.78219 | L36: =SUM(L28:L35) -> 0.94885667
B39: Topper | C39: 1 | D39: 1 | E39: 1 | F39: 1 | G39: 1 | H39: 1.8 | I39: =(C39*H39)/G39 -> 1.8 | J39: =D39*H39/G39 -> 1.8 | K39: =(C39*H39)/G39 -> 1.8 | L39: =(F39*H39)/G39 -> 1.8
B40: Vela | C40: 1 | D40: 1 | E40: 1 | F40: 1 | G40: 6 | H40: 1 | I40: =(C40*H40)/G40 -> 0.16666667 | J40: =D40*H40/G40 -> 0.16666667 | K40: =(C40*H40)/G40 -> 0.16666667 | L40: =(F40*H40)/G40 -> 0.16666667
B41: Plato 25 cm | C41: 1 | D41: 1 | E41: 1 | F41: 1 | G41: 1 | H41: 0.9 | I41: =(C41*H41)/G41 -> 0.9 | J41: =D41*H41/G41 -> 0.9 | K41: =(C41*H41)/G41 -> 0.9 | L41: =(F41*H41)/G41 -> 0.9
A42: EXTRAS | B42: Caja 25,5 | C42: 1 | D42: 1 | E42: 1 | F42: 1 | G42: 1 | H42: 1.85 | I42: =(C42*H42)/G42 -> 1.85 | J42: =D42*H42/G42 -> 1.85 | K42: =(C42*H42)/G42 -> 1.85 | L42: =(F42*H42)/G42 -> 1.85
B43: Etiqueta | C43: 1 | D43: 1 | E43: 1 | F43: 1 | G43: 500 | H43: 0.85 | I43: =(C43*H43)/G43 -> 0.0017 | J43: =D43*H43/G43 -> 0.0017 | K43: =(C43*H43)/G43 -> 0.0017 | L43: =(F43*H43)/G43 -> 0.0017
B44: Banda | C44: 2 | D44: 2 | E44: 2 | F44: 2 | G44: 2 | H44: 0.18 | I44: =(C44*H44)/G44 -> 0.18 | J44: =D44*H44/G44 -> 0.18 | K44: =(C44*H44)/G44 -> 0.18 | L44: =(F44*H44)/G44 -> 0.18
B45: Sprinkles | C45: 10 | D45: 10 | E45: 10 | F45: 10 | G45: 100 | H45: 6 | I45: =(C45*H45)/G45 -> 0.6 | J45: =D45*H45/G45 -> 0.6 | K45: =(C45*H45)/G45 -> 0.6 | L45: =(F45*H45)/G45 -> 0.6
B46: Decoraciones | C46: 3 | D46: 3 | E46: 3 | F46: 3 | G46: 10 | H46: 1 | I46: =(C46*H46)/G46 -> 0.3 | J46: =D46*H46/G46 -> 0.3 | K46: =(C46*H46)/G46 -> 0.3 | L46: =(F46*H46)/G46 -> 0.3
I47: =SUM(I39:I46) -> 5.7983667 | J47: =SUM(J39:J46) -> 5.7983667 | K47: =SUM(K39:K46) -> 5.7983667 | L47: =SUM(L39:L46) -> 5.7983667
I50: COSTE 16 | J50: COSTE 18 | K50: COSTE 20 | L50: COSTE 24
I51: =SUM(I9+I14+I20+I26+I36+I47) -> 12.678995 | J51: =SUM(J9+J14+J20+J26+J36+J47) -> 13.870124 | K51: =SUM(K9+K14+K20+K26+K36+K47) -> 15.989405 | L51: =SUM(L9+L14+L20+L26+L36+L47) -> 18.384089
H52: PVP | I52: 30 | J52: 35 | K52: 40 | L52: 50
H53: PROFIT | I53: =SUM(I52-I51) -> 17.321005 | J53: =SUM(J52-J51) -> 21.129876 | K53: =SUM(K52-K51) -> 24.010595 | L53: =SUM(L52-L51) -> 31.615911

Sheet CRUMBLE COOKIES
C1: MASA GALLETAS
A2: INGREDIENTES | B2: 1 MASA | C2: MEDIA MASA | D2: UNIDADES | E2: PRECIO | F2: COSTO 1 MASA | G2: COSTO MEDIA MASA
A3: MANTEQUILLA | B3: 280 | C3: 140 | D3: 250 | E3: 2.5 | F3: =B3*E3/D3 -> 2.8 | G3: =(C3*E3/D3) -> 1.4 | I3: CANT MASA
A4: AZUCAR BLANCA | B4: 115 | C4: 60 | D4: 1000 | E4: 1.49 | F4: =B4*E4/D4 -> 0.17135 | G4: =(C4*E4/D4) -> 0.0894 | I4: 1 MASA ENTERA | J4: 30-35 | K4: 5O GR | L4: COOKIES
A5: AZUCAR MORENA | B5: 285 | C5: 140 | D5: 1000 | E5: 1.85 | F5: =B5*E5/D5 -> 0.52725 | G5: =(C5*E5/D5) -> 0.259 | I5: 1 MASA ENTERA | J5: 15 | K5: 100-120 GR | L5: CRUMBLE
A6: CHOCOLATE BARRA | B6: 200 | C6: 100 | D6: 100 | E6: 1.2 | F6: =B6*E6/D6 -> 2.4 | G6: =(C6*E6/D6) -> 1.2 | I6: 1 MASA ENTERA | J6: 50 | K6: 25GR | L6: MINI COOKIES
A7: CHOCO NOVA SUC | B7: 250 | C7: 125 | D7: 1000 | E7: 6 | F7: =B7*E7/D7 -> 1.5 | G7: =(C7*E7/D7) -> 0.75
A8: HARINA 000 | B8: 275 | C8: 165 | D8: 1000 | E8: 1.1 | F8: =B8*E8/D8 -> 0.3025 | G8: =(C8*E8/D8) -> 0.1815 | I8: PRODUCTO | J8: CANT GOOKIES | K8: COSTE | L8: PVP | M8: PROFIT
A9: HARINA 0000 | B9: 230 | C9: 115 | D9: 1000 | E9: 1.5 | F9: =B9*E9/D9 -> 0.345 | G9: =(C9*E9/D9) -> 0.1725 | I9: COOKIES 50 GR | J9: 35 | K9: =SUM(F14+F21+F30) -> 16.67894 | L9: 22 | M9: =SUM(L9-K9) -> 5.32106 | N9: PACK COLE
A10: SAL | B10: 5 | C10: 3 | D10: 1000 | E10: 0.7 | F10: =B10*E10/D10 -> 0.0035 | G10: =(C10*E10/D10) -> 0.0021 | I10: COOKIES 50 GR | J10: 15 | K10: =SUM(G14+G21+G30) -> 9.5204733 | L10: 15 | M10: =SUM(L10-K10) -> 5.4795267
A11: BICARBONATO | B11: 6 | C11: 3 | D11: 1000 | E11: 0.9 | F11: =B11*E11/D11 -> 0.0054 | G11: =(C11*E11/D11) -> 0.0027 | I11: CRUMBLE | J11: 15 | K11: =SUM(F14+F21+F30) -> 16.67894 | L11: 20 | M11: =SUM(L11-K11) -> 3.32106
A12: YEMAS | B12: 3 | C12: 2 | D12: 12 | E12: 2.5 | F12: =B12*E12/D12 -> 0.625 | G12: =(C12*E12/D12) -> 0.41666667 | I12: CRUMBLE | J12: 6 | K12: =SUM(G14+G21+G30) -> 9.5204733 | L12: 15 | M12: =SUM(L12-K12) -> 5.4795267
A13: HUEVO | B13: 2 | C13: 1 | D13: 12 | E13: 2.5 | F13: =B13*E13/D13 -> 0.41666667 | G13: =(C13*E13/D13) -> 0.20833333
F14: =SUM(F3:F13) -> 9.0966667 | G14: =SUM(G3:G13) -> 4.6822
A15: GASTOS INDIRECTOS
A16: INGREDIENTES | B16: 1 MASA | C16: MEDIA MASA | D16: UNIDADES | E16: PRECIO | F16: COSTO 1 MASA | G16: COSTO MEDIA MASA
A17: PAPEL HORNO | B17: 1 | C17: 1 | D17: 20 | E17: 1.13 | F17: =B17*E17/D17 -> 0.0565 | G17: =SUM(C17*E17/D17) -> 0.0565
A18: HORNO | B18: 30 | C18: 30 | D18: 60 | E18: 1 | F18: =B18*E18/D18 -> 0.5 | G18: =SUM(C18*E18/D18) -> 0.5
A19: AGUA | B19: 12 | C19: 12 | D19: 1000 | E19: 1.97 | F19: =B19*E19/D19 -> 0.02364 | G19: =SUM(C19*E19/D19) -> 0.02364
A20: BATIDORA | B20: 5 | C20: 5 | D20: 60 | E20: 1 | F20: =B20*E20/D20 -> 0.083333333 | G20: =SUM(C20*E20/D20) -> 0.083333333
F21: =SUM(F17:F20) -> 0.66347333 | G21: =SUM(G17:G20) -> 0.66347333
A23: PACKAGING
A24: INGREDIENTES | B24: 1 MASA | C24: MEDIA MASA | D24: UNIDADES | E24: PRECIO | F24: COSTO 1 MASA | G24: COSTO 1/2 MASA
A25: CAJA MINI 20X20 | B25: 0 | C25: 1 | D25: 1 | E25: 2.2 | F25: =B25*E25/D25 -> 0 | G25: =C25*E25/D25 -> 2.2
A26: CAJA GRANDE 30X30 | B26: 1 | C26: 0 | D26: 1 | E26: 2.2 | F26: =B26*E26/D26 -> 2.2 | G26: =C26*E26/D26 -> 0
A27: PAPEL PARAF | B27: 35 | C27: 16 | D27: 100 | E27: 2 | F27: =B27*E27/D27 -> 0.7 | G27: =C27*E27/D27 -> 0.32
A28: BOLSAS 100 GR | B28: 16 | C28: 6 | D28: 25 | E28: 1.97 | F28: =B28*E28/D28 -> 1.2608 | G28: =C28*E28/D28 -> 0.4728
A29: BOLSAS 50 GR | B29: 35 | C29: 15 | D29: 25 | E29: 1.97 | F29: =B29*E29/D29 -> 2.758 | G29: =C29*E29/D29 -> 1.182
F30: =SUM(F25:F29) -> 6.9188 | G30: =SUM(G25:G29) -> 4.1748

Sheet Masas basicas
E1: Redondo
C4: 16 cm - | D4: 18.5 | E4: 20 cm | F4: 24 cm | I4: 16 CM | J4: 18.5 | K4: 20 cm | L4: 24
B5: INGREDIENTES | C5: CANT 8-10 p | D5: CANT 12-15 | E5: CANT 18-20 p | F5: CANT 25-28 | G5: UNIDADES PAQ | H5: PRECIO | I5: COSTO 8-10 p | J5: COSTO 12-15 | K5: COSTO 18-20 p | L5: COSTO 25-28 | N5: CANT 10-12 p | O5: CANT 18-20 p | P5: CANT 22-26 | Q5: UNIDADES PAQ | R5: PRECIO | S5: COSTO 10-12 p | T5: COSTO 18-20 p | U5: COSTO 22-26 | V5: INGREDIENTES | W5: CANT 10-12 p | X5: CANT 18-20 p | Y5: CANT 22-27 | Z5: UNIDADES PAQ | AA5: PRECIO | AB5: COSTO 10-12 p | AC5: COSTO 18-20 p | AD5: COSTO 22-27 | AE5: INGREDIENTES
A7: BIZCOCHO | B7: Harina | C7: 150 | D7: 180 | E7: 240 | F7: 270 | G7: 1000 | H7: 1.07 | I7: =(C7*H7)/G7 -> 0.1605 | J7: =D8*H8/G8 -> 1.25 | K7: =(E7*H7)/G7 -> 0.2568 | L7: =(F7*H7)/G7 -> 0.2889
A8: VAINILLA | B8: Huevos | C8: 5 | D8: 6 | E8: 8 | F8: 9 | G8: 12 | H8: 2.5 | I8: =(C8*H8)/G8 -> 1.0416667 | J8: =D9*H9/G9 -> 0.225 | K8: =(E8*H8)/G8 -> 1.6666667 | L8: =(F8*H8)/G8 -> 1.875
B9: Azucar | C9: 150 | D9: 180 | E9: 240 | F9: 270 | G9: 1000 | H9: 1.25 | I9: =(C9*H9)/G9 -> 0.1875 | J9: =D10*H10/G10 -> 0.29237288 | K9: =(E9*H9)/G9 -> 0.3 | L9: =(F9*H9)/G9 -> 0.3375
B10: Vainilla | C10: 5 | D10: 10 | E10: 10 | F10: 15 | G10: 236 | H10: 6.9 | I10: =(C10*H10)/G10 -> 0.14618644 | J10: =D10*H10/G10 -> 0.29237288 | K10: =(E10*H10)/G10 -> 0.29237288 | L10: =(F10*H10)/G10 -> 0.43855932
I11: =SUM(I7:I10) -> 1.5358531 | J11: =SUM(J7:J10) -> 2.0597458 | K11: =SUM(K7:K10) -> 2.5158395 | L11: =SUM(L7:L10) -> 2.9399593
B13: Harina | C13: 140 | D13: 170 | E13: 230 | F13: 260 | G13: 1000 | H13: 1.07 | I13: =(C13*H13)/G13 -> 0.1498 | J13: =D14*H14/G14 -> 1.25 | K13: =(E13*H13)/G13 -> 0.2461 | L13: =(F13*H13)/G13 -> 0.2782
A14: BiZCOCHO | B14: Huevos | C14: 5 | D14: 6 | E14: 8 | F14: 9 | G14: 12 | H14: 2.5 | I14: =(C14*H14)/G14 -> 1.0416667 | J14: =D15*H15/G15 -> 0.225 | K14: =(E14*H14)/G14 -> 1.6666667 | L14: =(F14*H14)/G14 -> 1.875
A15: CHOCOLATE | B15: Azucar | C15: 150 | D15: 180 | E15: 240 | F15: 270 | G15: 1000 | H15: 1.25 | I15: =(C15*H15)/G15 -> 0.1875 | J15: =D16*H16/G16 -> 0.29237288 | K15: =(E15*H15)/G15 -> 0.3 | L15: =(F15*H15)/G15 -> 0.3375
B16: Vainilla | C16: 5 | D16: 10 | E16: 10 | F16: 10 | G16: 236 | H16: 6.9 | I16: =(C16*H16)/G16 -> 0.14618644 | J16: =D17*H17/G17 -> 0.72 | K16: =(E16*H16)/G16 -> 0.29237288 | L16: =(F16*H16)/G16 -> 0.29237288
B17: Cacao | C17: 30 | D17: 30 | E17: 40 | F17: 50 | G17: 250 | H17: 6 | I17: =(C17*H17)/G17 -> 0.72 | J17: =D18*H18/G18 -> 0.07475 | K17: =(E17*H17)/G17 -> 0.96 | L17: =(F17*H17)/G17 -> 1.2
B18: Maicena | C18: 20 | D18: 10 | E18: 10 | F18: 10 | G18: 400 | H18: 2.99 | I18: =(C18*H18)/G18 -> 0.1495 | J18: =D18*H18/G18 -> 0.07475 | K18: =(E18*H18)/G18 -> 0.07475 | L18: =(F18*H18)/G18 -> 0.07475
I19: =SUM(I13:I18) -> 2.3946531 | J19: =SUM(J13:J18) -> 2.6368729 | K19: =SUM(K13:K18) -> 3.5398895 | L19: =SUM(L13:L18) -> 4.0578229
B21: Azucar | C21: 100 | D21: 120 | E21: 150 | F21: 200 | G21: 1000 | H21: 1.25 | I21: =(C21*H21)/G21 -> 0.125 | J21: =D21*H21/G21 -> 0.15 | K21: =(E21*H21)/G21 -> 0.1875 | L21: =(F21*H21)/G21 -> 0.25
A22: ALMIBAR | B22: Agua | C22: 100 | D22: 120 | E22: 150 | F22: 200 | G22: 1000 | H22: 0.25 | I22: =(C22*H22)/G22 -> 0.025 | J22: =D22*H22/G22 -> 0.03 | K22: =(E22*H22)/G22 -> 0.0375 | L22: =(F22*H22)/G22 -> 0.05
B23: Vainilla | C23: 3 | D23: 4 | E23: 5 | F23: 9 | G23: 236 | H23: 6.9 | I23: =(C23*H23)/G23 -> 0.087711864 | J23: =D23*H23/G23 -> 0.11694915 | K23: =(E23*H23)/G23 -> 0.14618644 | L23: =(F23*H23)/G23 -> 0.26313559
I24: =SUM(I21:I23) -> 0.23771186 | J24: =SUM(J21:J23) -> 0.29694915 | K24: =SUM(K21:K23) -> 0.37118644 | L24: =SUM(L21:L23) -> 0.56313559
A26: RELLENO | B26: Nata | C26: 300 | D26: 350 | E26: 400 | F26: 500 | G26: 600 | H26: 2.36 | I26: =(C26*H26)/G26 -> 1.18 | J26: =D26*H26/G26 -> 1.3766667 | K26: =(E26*H26)/G26 -> 1.5733333 | L26: =(F26*H26)/G26 -> 1.9666667
A27: NATA Y MOUSSE | B27: Queso phila | C27: 100 | D27: 120 | E27: 150 | F27: 200 | G27: 250 | H27: 1.1 | I27: =(C27*H27)/G27 -> 0.44 | J27: =D27*H27/G27 -> 0.528 | K27: =(E27*H27)/G27 -> 0.66 | L27: =(F27*H27)/G27 -> 0.88
A28: CHOCOLATE | B28: Cacao | C28: 20 | D28: 25 | E28: 30 | F28: 40 | G28: 250 | H28: 6 | I28: =(C28*H28)/G28 -> 0.48 | J28: =D28*H28/G28 -> 0.6 | K28: =(E28*H28)/G28 -> 0.72 | L28: =(F28*H28)/G28 -> 0.96
B29: Azucar blanca | C29: 80 | D29: 90 | E29: 90 | F29: 100 | G29: 1000 | H29: 1.25 | I29: =(C29*H29)/G29 -> 0.1 | J29: =D29*H29/G29 -> 0.1125 | K29: =(E29*H29)/G29 -> 0.1125 | L29: =(F29*H29)/G29 -> 0.125
I30: =SUM(I26:I29) -> 2.2 | J30: =SUM(J26:J29) -> 2.6171667 | K30: =SUM(K26:K29) -> 3.0658333 | L30: =SUM(L26:L29) -> 3.9316667
B32: Nata | C32: 300 | D32: 350 | E32: 400 | F32: 500 | G32: 600 | H32: 2.19 | I32: =(C32*H32)/G32 -> 1.095 | J32: =D32*H32/G32 -> 1.2775 | K32: =(E32*H32)/G32 -> 1.46 | L32: =(F32*H32)/G32 -> 1.825
A33: RELLENO | B33: Queso phila | C33: 100 | D33: 120 | E33: 150 | F33: 200 | G33: 250 | H33: 1.1 | I33: =(C33*H33)/G33 -> 0.44 | J33: =D33*H33/G33 -> 0.528 | K33: =(E33*H33)/G33 -> 0.66 | L33: =(F33*H33)/G33 -> 0.88
A34: CREMA | B34: Galleta oreo | C34: 1 | D34: 1 | E34: 2 | F34: 3 | G34: 6 | H34: 1.05 | I34: =(C34*H34)/G34 -> 0.175 | J34: =D34*H34/G34 -> 0.175 | K34: =(E34*H34)/G34 -> 0.35 | L34: =(F34*H34)/G34 -> 0.525
A35: OREO-LOTUS | B35: Azucar blanca | C35: 80 | D35: 85 | E35: 90 | F35: 100 | G35: 1000 | H35: 1.25 | I35: =(C35*H35)/G35 -> 0.1 | J35: =D35*H35/G35 -> 0.10625 | K35: =(E35*H35)/G35 -> 0.1125 | L35: =(F35*H35)/G35 -> 0.125
B36: Vainilla | C36: 5 | D36: 5 | E36: 7 | F36: 9 | G36: 236 | H36: 6.9 | I36: =(C36*H36)/G36 -> 0.14618644 | J36: =D36*H36/G36 -> 0.14618644 | K36: =(E36*H36)/G36 -> 0.20466102 | L36: =(F36*H36)/G36 -> 0.26313559
I37: =SUM(I32:I36) -> 1.9561864 | J37: =SUM(J32:J36) -> 2.2329364 | K37: =SUM(K32:K36) -> 2.787161 | L37: =SUM(L32:L36) -> 3.6181356
A39: RELLENO | B39: Nata | C39: 300 | D39: 300 | E39: 400 | F39: 500 | G39: 600 | H39: 2.19 | I39: =(C39*H39)/G39 -> 1.095 | J39: =D39*H39/G39 -> 1.095 | K39: =(E39*H39)/G39 -> 1.46 | L39: =(F39*H39)/G39 -> 1.825
A40: LEMON | B40: Queso phila | C40: 100 | D40: 100 | E40: 100 | F40: 200 | G40: 250 | H40: 1.1 | I40: =(C40*H40)/G40 -> 0.44 | J40: =D40*H40/G40 -> 0.44 | K40: =(E40*H40)/G40 -> 0.44 | L40: =(F40*H40)/G40 -> 0.88
A41: CURD | B41: Azucar | C41: 80 | D41: 80 | E41: 90 | F41: 100 | G41: 1000 | H41: 1.25 | I41: =(C41*H41)/G41 -> 0.1 | J41: =D41*H41/G41 -> 0.1 | K41: =(E41*H41)/G41 -> 0.1125 | L41: =(F41*H41)/G41 -> 0.125
B42: Limon zumo | C42: 1 | D42: 1 | E42: 1 | F42: 2 | G42: 6 | H42: 2.03 | I42: =(C42*H42)/G42 -> 0.33833333 | J42: =D42*H42/G42 -> 0.33833333 | K42: =(E42*H42)/G42 -> 0.33833333 | L42: =(F42*H42)/G42 -> 0.67666667
B43: Limon cascara | C43: 1 | D43: 1 | E43: 1 | F43: 2 | G43: 6 | H43: 2.03 | I43: =(C43*H43)/G43 -> 0.33833333 | J43: =D43*H43/G43 -> 0.33833333 | K43: =(E43*H43)/G43 -> 0.33833333 | L43: =(F43*H43)/G43 -> 0.67666667
B44: Vainilla | C44: 5 | D44: 5 | E44: 7 | F44: 9 | G44: 236 | H44: 6.9 | I44: =(C44*H44)/G44 -> 0.14618644 | J44: =D44*H44/G44 -> 0.14618644 | K44: =(E44*H44)/G44 -> 0.20466102 | L44: =(F44*H44)/G44 -> 0.26313559
B45: Huevos | C45: 4 | D45: 4 | E45: 6 | F45: 8 | G45: 12 | H45: 2.31 | I45: =(C45*H45)/G45 -> 0.77 | J45: =D45*H45/G45 -> 0.77 | K45: =(E45*H45)/G45 -> 1.155 | L45: =(F45*H45)/G45 -> 1.54
B46: Azucar | C46: 215 | D46: 215 | E46: 110 | F46: 430 | G46: 1000 | H46: 1.25 | I46: =(C46*H46)/G46 -> 0.26875 | J46: =D46*H46/G46 -> 0.26875 | K46: =(E46*H46)/G46 -> 0.1375 | L46: =(F46*H46)/G46 -> 0.5375
B47: Manteca | C47: 100 | D47: 100 | E47: 150 | F47: 200 | G47: 250 | H47: 2.15 | I47: =(C47*H47)/G47 -> 0.86 | J47: =D47*H47/G47 -> 0.86 | K47: =(E47*H47)/G47 -> 1.29 | L47: =(F47*H47)/G47 -> 1.72
I48: =SUM(I39:I47) -> 4.3566031 | J48: =SUM(J39:J47) -> 4.3566031 | K48: =SUM(K39:K47) -> 5.4763277 | L48: =SUM(L39:L47) -> 8.2439689
A50: RELLENO | B50: Nata | C50: 300 | D50: 300 | E50: 400 | F50: 500 | G50: 600 | H50: 2.19 | I50: =(C50*H50)/G50 -> 1.095 | J50: =D50*H50/G50 -> 1.095 | K50: =(E50*H50)/G50 -> 1.46 | L50: =(F50*H50)/G50 -> 1.825
A51: MOUSSE | B51: Queso phila | C51: 100 | D51: 100 | E51: 100 | F51: 200 | G51: 250 | H51: 1.1 | I51: =(C51*H51)/G51 -> 0.44 | J51: =D51*H51/G51 -> 0.44 | K51: =(E51*H51)/G51 -> 0.44 | L51: =(F51*H51)/G51 -> 0.88
A52: MERMELADA | B52: Azucar | C52: 80 | D52: 80 | E52: 90 | F52: 100 | G52: 1000 | H52: 1.25 | I52: =(C52*H52)/G52 -> 0.1 | J52: =D52*H52/G52 -> 0.1 | K52: =(E52*H52)/G52 -> 0.1125 | L52: =(F52*H52)/G52 -> 0.125
B53: Vainilla | C53: 5 | D53: 5 | E53: 7 | F53: 9 | G53: 236 | H53: 6.9 | I53: =(C53*H53)/G53 -> 0.14618644 | J53: =D53*H53/G53 -> 0.14618644 | K53: =(E53*H53)/G53 -> 0.20466102 | L53: =(F53*H53)/G53 -> 0.26313559
B54: Fruta | C54: 300 | D54: 300 | E54: 300 | F54: 300 | G54: 300 | H54: 1.62 | I54: =(C54*H54)/G54 -> 1.62 | J54: =D54*H54/G54 -> 1.62 | K54: =(E54*H54)/G54 -> 1.62 | L54: =(F54*H54)/G54 -> 1.62
B55: Azucar | C55: 80 | D55: 80 | E55: 90 | F55: 100 | G55: 1000 | H55: 1.25 | I55: =(C55*H55)/G55 -> 0.1 | J55: =D55*H55/G55 -> 0.1 | K55: =(E55*H55)/G55 -> 0.1125 | L55: =(F55*H55)/G55 -> 0.125
I56: =SUM(I50:I55) -> 3.5011864 | J56: =SUM(J50:J55) -> 3.5011864 | K56: =SUM(K50:K55) -> 3.949661 | L56: =SUM(L50:L55) -> 4.8381356
A58: RELLENO | B58: Dulce de leche | C58: 400 | D58: 450 | E58: 500 | F58: 600 | G58: 1000 | H58: 3.85 | I58: =(C58*H58)/G58 -> 1.54 | J58: =D58*H58/G58 -> 1.7325 | K58: =(E58*H58)/G58 -> 1.925 | L58: =(F58*H58)/G58 -> 2.31
A59: D.D.L Y | B59: Nata | C59: 300 | D59: 300 | E59: 400 | F59: 500 | G59: 600 | H59: 2.19 | I59: =(C59*H59)/G59 -> 1.095 | J59: =D59*H59/G59 -> 1.095 | K59: =(E59*H59)/G59 -> 1.46 | L59: =(F59*H59)/G59 -> 1.825
A60: NATA + melocoton | B60: Azucar | C60: 80 | D60: 80 | E60: 90 | F60: 100 | G60: 1000 | H60: 1.25 | I60: =(C60*H60)/G60 -> 0.1 | J60: =D60*H60/G60 -> 0.1 | K60: =(E60*H60)/G60 -> 0.1125 | L60: =(F60*H60)/G60 -> 0.125
B61: Vainilla | C61: 5 | D61: 5 | E61: 7 | F61: 9 | G61: 236 | H61: 6.9 | I61: =(C61*H61)/G61 -> 0.14618644 | J61: =D61*H61/G61 -> 0.14618644 | K61: =(E61*H61)/G61 -> 0.20466102 | L61: =(F61*H61)/G61 -> 0.26313559
B62: Melocoton | C62: 100 | D62: 120 | E62: 150 | F62: 200 | G62: 1000 | H62: 4.69 | I62: =(C62*H62)/G62 -> 0.469 | J62: =D62*H62/G62 -> 0.5628 | K62: =(E62*H62)/G62 -> 0.7035 | L62: =(F62*H62)/G62 -> 0.938
I63: =SUM(I58:I62) -> 3.3501864 | J63: =SUM(J58:J62) -> 3.6364864 | K63: =SUM(K58:K62) -> 4.405661 | L63: =SUM(L58:L62) -> 5.4611356
A66: COBERTURA | B66: Nata | C66: 300 | D66: 350 | E66: 300 | F66: 400 | G66: 600 | H66: 2.19 | I66: =(C66*H66)/G66 -> 1.095 | J66: =D66*H66/G66 -> 1.2775 | K66: =(E66*H66)/G66 -> 1.095 | L66: =(F66*H66)/G66 -> 1.46
A67: CREMA DE | B67: Queso phila | C67: 100 | D67: 120 | E67: 200 | F67: 250 | G67: 250 | H67: 1.1 | I67: =(C67*H67)/G67 -> 0.44 | J67: =D67*H67/G67 -> 0.528 | K67: =(E67*H67)/G67 -> 0.88 | L67: =(F67*H67)/G67 -> 1.1
A68: QUESO | B68: Azucar glass | C68: 50 | D68: 60 | E68: 70 | F68: 90 | G68: 1000 | H68: 4.5 | I68: =(C68*H68)/G68 -> 0.225 | J68: =D68*H68/G68 -> 0.27 | K68: =(E68*H68)/G68 -> 0.315 | L68: =(F68*H68)/G68 -> 0.405
B69: Vainilla | C69: 5 | D69: 5 | E69: 7 | F69: 9 | G69: 236 | H69: 6.9 | I69: =(C69*H69)/G69 -> 0.14618644 | J69: =D69*H69/G69 -> 0.14618644 | K69: =(E69*H69)/G69 -> 0.20466102 | L69: =(F69*H69)/G69 -> 0.26313559
I70: =SUM(I66:I69) -> 1.9061864 | J70: =SUM(J66:J69) -> 2.2216864 | K70: =SUM(K66:K69) -> 2.494661 | L70: =SUM(L66:L69) -> 3.2281356
B72: papel horno | C72: 1 | D72: 1 | E72: 1 | F72: 1 | G72: 20 | H72: 1.13 | I72: =(C72*H72)/G72 -> 0.0565 | J72: =D72*H72/G72 -> 0.0565 | K72: =(C72*H72)/G72 -> 0.0565 | L72: =(F72*H72)/G72 -> 0.0565
B73: Papel plata | C73: 1 | D73: 1 | E73: 1 | F73: 1 | G73: 1000 | H73: 2.05 | I73: =(C73*H73)/G73 -> 0.00205 | J73: =D73*H73/G73 -> 0.00205 | K73: =(C73*H73)/G73 -> 0.00205 | L73: =(F73*H73)/G73 -> 0.00205
B74: Horno | C74: 30 | D74: 30 | E74: 35 | F74: 40 | G74: 60 | H74: 1 | I74: =(C74*H74)/G74 -> 0.5 | J74: =D74*H74/G74 -> 0.5 | K74: =(C74*H74)/G74 -> 0.5 | L74: =(F74*H74)/G74 -> 0.66666667
A75: COSTES | B75: Agua | C75: 12 | D75: 12 | E75: 12 | F75: 12 | G75: 1000 | H75: 1.97 | I75: =(C75*H75)/G75 -> 0.02364 | J75: =D75*H75/G75 -> 0.02364 | K75: =(C75*H75)/G75 -> 0.02364 | L75: =(F75*H75)/G75 -> 0.02364
A76: INDIRECTOS | B76: Batidora | C76: 12 | D76: 12 | E76: 12 | F76: 12 | G76: 60 | H76: 1 | I76: =(C76*H76)/G76 -> 0.2 | J76: =D76*H76/G76 -> 0.2 | K76: =(C76*H76)/G76 -> 0.2 | L76: =(F76*H76)/G76 -> 0.2
I80: =SUM(I72:I79) -> 0.78219 | J80: =SUM(J72:J79) -> 0.78219 | K80: =SUM(K72:K79) -> 0.78219 | L80: =SUM(L72:L79) -> 0.94885667
B83: Topper | C83: 1 | D83: 1 | E83: 1 | F83: 1 | G83: 1 | H83: 1.8 | I83: =(C83*H83)/G83 -> 1.8 | J83: =D83*H83/G83 -> 1.8 | K83: =(C83*H83)/G83 -> 1.8 | L83: =(F83*H83)/G83 -> 1.8
B84: Vela | C84: 1 | D84: 1 | E84: 1 | F84: 1 | G84: 6 | H84: 1 | I84: =(C84*H84)/G84 -> 0.16666667 | J84: =D84*H84/G84 -> 0.16666667 | K84: =(C84*H84)/G84 -> 0.16666667 | L84: =(F84*H84)/G84 -> 0.16666667
B85: Plato 25 cm | C85: 1 | D85: 1 | E85: 1 | F85: 1 | G85: 1 | H85: 0.9 | I85: =(C85*H85)/G85 -> 0.9 | J85: =D85*H85/G85 -> 0.9 | K85: =(C85*H85)/G85 -> 0.9 | L85: =(F85*H85)/G85 -> 0.9
A86: EXTRAS | B86: Caja 25,5 | C86: 1 | D86: 1 | E86: 1 | F86: 1 | G86: 1 | H86: 1.85 | I86: =(C86*H86)/G86 -> 1.85 | J86: =D86*H86/G86 -> 1.85 | K86: =(C86*H86)/G86 -> 1.85 | L86: =(F86*H86)/G86 -> 1.85
B87: Etiqueta | C87: 1 | D87: 1 | E87: 1 | F87: 1 | G87: 500 | H87: 0.85 | I87: =(C87*H87)/G87 -> 0.0017 | J87: =D87*H87/G87 -> 0.0017 | K87: =(C87*H87)/G87 -> 0.0017 | L87: =(F87*H87)/G87 -> 0.0017
B88: Banda | C88: 2 | D88: 2 | E88: 2 | F88: 2 | G88: 2 | H88: 0.18 | I88: =(C88*H88)/G88 -> 0.18 | J88: =D88*H88/G88 -> 0.18 | K88: =(C88*H88)/G88 -> 0.18 | L88: =(F88*H88)/G88 -> 0.18
B89: Sprinkles | C89: 10 | D89: 10 | E89: 10 | F89: 10 | G89: 100 | H89: 6 | I89: =(C89*H89)/G89 -> 0.6 | J89: =D89*H89/G89 -> 0.6 | K89: =(C89*H89)/G89 -> 0.6 | L89: =(F89*H89)/G89 -> 0.6
B90: Decoraciones | C90: 3 | D90: 3 | E90: 3 | F90: 3 | G90: 10 | H90: 1 | I90: =(C90*H90)/G90 -> 0.3 | J90: =D90*H90/G90 -> 0.3 | K90: =(C90*H90)/G90 -> 0.3 | L90: =(F90*H90)/G90 -> 0.3
I91: =SUM(I83:I90) -> 5.7983667 | J91: =SUM(J83:J90) -> 5.7983667 | K91: =SUM(K83:K90) -> 5.7983667 | L91: =SUM(L83:L90) -> 5.7983667
A93: BIZCOCHO | B93: RELLENO | C93: 16 CM | D93: 18 CM | E93: 20 CM | F93: 24 CM
A94: VAINILLA | B94: NATA Y MOUSSE | C94: =SUM(I11+I24+I30+I91+I70+I80) -> 12.460308 | D94: =SUM(J11+J24+J30+J70+J80+J91) -> 13.776105 | E94: =SUM(K11+K24+K30+K70+K91) -> 14.245887 | F94: =SUM(L11+L24+L30+L70+L91) -> 16.461264 | H94: BIZCOCHO | I94: RELLENO | J94: TAMAÑO
A95: CHOCOLATE | B95: NATA Y MOUSSE | C95: =SUM(I19+I24+I30+I91+I70+I80) -> 13.319108 | D95: =SUM(J19+J24+J30+J70+J80+J91) -> 14.353232 | E95: =SUM(K19+K24+K30+K70+K91) -> 15.269937 | F95: =SUM(L11+L24+L30+L70+L91) -> 16.461264 | H95: VAINILLA | I95: NATA Y MOUSSE | J95: 16
A96: VAINILLA | B96: GALLETA | C96: =SUM(I11+I24+I37+I70+I91+I80) -> 12.216495 | D96: =SUM(J11+J24+J37+J70+J80+J91) -> 13.391874 | E96: =SUM(K11+K24+K37+K70+K91) -> 13.967215 | F96: =SUM(L11+L24+L37+L70+L91) -> 16.147733 | H96: CHOCOLATE | I96: NATA Y MOUSSE | J96: 16
A97: CHOCOLATE | B97: GALLETA | C97: =SUM(I19+I24+I37+I70+I91+I80) -> 13.075295 | D97: =SUM(J19+J24+J37+J70+J80+J91) -> 13.969002 | E97: =SUM(K19+K24+K37+K70+K91) -> 14.991265 | F97: =SUM(L19+L24+L37+L70+L91) -> 17.265596
A98: VAINILLA | B98: LIMON | C98: =SUM(I11+I24+I48+I70+I91+I80) -> 14.616911 | D98: =SUM(J11+J24+J48+J70+J91+J80) -> 15.515541 | E98: =SUM(K11+K24+K48+K70+K91) -> 16.656381 | F98: =SUM(L11+L24+L48+L70+L91) -> 20.773566
A99: VAINILLA | B99: DDL Y FRUTA | C99: =SUM(I11+I24+I63+I70+I91+I80) -> 13.610495 | D99: =SUM(J11+J24+J63+J70+J91+J80) -> 14.795424 | E99: =SUM(K11+K24+K63+K70+K91) -> 15.585715 | F99: =SUM(L11+L24+L63+L70+L91) -> 17.990733
A100: VAINILLA | B100: MERMELADA | C100: =SUM(I11+I24+I56+I70+I91*I80) -> 11.716362 | D100: =SUM(J11+J24+J56+J70+J91*J80) -> 12.614992 | E100: =SUM(K11+K24+K56+K70+K91) -> 15.129715 | F100: =SUM(L11+L24+L56+L70+L91) -> 17.367733
A101: CHOCOLATE | B101: MERMELADA | C101: =SUM(I11+I24+I56+I70+I91+I80) -> 13.761495 | D101: =SUM(J11+J24+J56+J70+J91+J80) -> 14.660124 | E101: =SUM(K11+K24+K56+K70+K91) -> 15.129715 | F101: =SUM(L11+L24+L56+L70+L91) -> 17.367733
A104: BIZCOCHO | B104: RELLENO | C104: 18 CM | E104: 20 CM | F104: 22 CM
A105: VAINILLA | B105: NATA Y MOUSSE | C105: 30 | E105: 35 | F105: 40
A106: CHOCOLATE | B106: NATA Y MOUSSE | C106: 30 | E106: 35 | F106: 40
A107: VAINILLA | B107: GALLETA | C107: 30 | E107: 35 | F107: 40
A108: CHOCOLATE | B108: GALLETA | C108: 30 | E108: 35 | F108: 40
A109: VAINILLA | B109: LIMON | C109: 30 | E109: 35 | F109: 40
A110: VAINILLA | B110: DDL Y FRUTA | C110: 30 | E110: 35 | F110: 40
A111: VAINILLA | B111: MERMELADA | C111: 30 | E111: 35 | F111: 40
A112: CHOCOLATE | B112: MERMELADA | C112: 30 | E112: 35 | F112: 40

Sheet TEMATICA GANACHE REDONDA
C3: 16 cm | D3: 18 cm | E3: 20 cm | F3: 22-24 cm | I3: 16 cm | J3: 18 cm | K3: 20 cm | L3: 22-24 cm
B4: INGREDIENTES | C4: CANT 8-10 p | D4: CANT 10-15 p | E4: CANT 18-20 | F4: CANT 20-25 | G4: UNIDADES PAQ | H4: PRECIO | I4: CANT 8-10 p | J4: CANT 10-15 p | K4: CANT 18-20 | L4: CANT 20-25
B5: Harina | C5: 140 | D5: 180 | E5: 240 | F5: 270 | G5: 1000 | H5: 1.07 | I5: =(C5*H5)/G5 -> 0.1498 | J5: =(D5*H5)/G5 -> 0.1926 | K5: =(E5*H5)/G5 -> 0.2568 | L5: =(F5*H5)/G5 -> 0.2889
A6: BiZCOCHO | B6: Huevos | C6: 5 | D6: 6 | E6: 8 | F6: 9 | G6: 12 | H6: 2.5 | I6: =(C6*H6)/G6 -> 1.0416667 | J6: =(D6*H6)/G6 -> 1.25 | K6: =(E6*H6)/G6 -> 1.6666667 | L6: =(F6*H6)/G6 -> 1.875
A7: CHOCOLATE | B7: Azucar | C7: 150 | D7: 180 | E7: 240 | F7: 270 | G7: 1000 | H7: 1.49 | I7: =(C7*H7)/G7 -> 0.2235 | J7: =(D7*H7)/G7 -> 0.2682 | K7: =(E7*H7)/G7 -> 0.3576 | L7: =(F7*H7)/G7 -> 0.4023
B8: Vainilla | C8: 5 | D8: 10 | E8: 10 | F8: 15 | G8: 236 | H8: 6.9 | I8: =(C8*H8)/G8 -> 0.14618644 | J8: =(D8*H8)/G8 -> 0.29237288 | K8: =(E8*H8)/G8 -> 0.29237288 | L8: =(F8*H8)/G8 -> 0.43855932
B9: Cacao | C9: 30 | D9: 40 | E9: 50 | F9: 60 | G9: 250 | H9: 6 | I9: =(C9*H9)/G9 -> 0.72 | J9: =(D9*H9)/G9 -> 0.96 | K9: =(E9*H9)/G9 -> 1.2 | L9: =(F9*H9)/G9 -> 1.44
B10: Maicena | C10: 20 | D10: 30 | E10: 40 | F10: 40 | G10: 400 | H10: 2.99 | I10: =(C10*H10)/G10 -> 0.1495 | J10: =(D10*H10)/G10 -> 0.22425 | K10: =(E10*H10)/G10 -> 0.299 | L10: =(F10*H10)/G10 -> 0.299
I11: =SUM(I5:I10) -> 2.4306531 | J11: =SUM(J5:J10) -> 3.1874229 | K11: =SUM(K5:K10) -> 4.0724395 | L11: =SUM(L5:L10) -> 4.7437593
B13: Azucar | C13: 100 | D13: 150 | E13: 200 | F13: 250 | G13: 1000 | H13: 1.49 | I13: =(C13*H13)/G13 -> 0.149 | J13: =(D13*H13)/G13 -> 0.2235 | K13: =(E13*H13)/G13 -> 0.298 | L13: =(F13*H5)/G5 -> 0.2675
A14: ALMIBAR | B14: Agua | C14: 100 | D14: 150 | E14: 200 | F14: 250 | G14: 1000 | H14: 0.25 | I14: =(C14*H14)/G14 -> 0.025 | J14: =(D14*H14)/G14 -> 0.0375 | K14: =(E14*H14)/G14 -> 0.05 | L14: =(F14*H14)/G14 -> 0.0625
B15: Vainilla | C15: 3 | D15: 5 | E15: 9 | F15: 11 | G15: 236 | H15: 6.9 | I15: =(C15*H15)/G15 -> 0.087711864 | J15: =(D15*H15)/G15 -> 0.14618644 | K15: =(E15*H15)/G15 -> 0.26313559 | L15: =(F15*H15)/G15 -> 0.32161017
I16: =SUM(I13:I15) -> 0.26171186 | J16: =SUM(J13:J15) -> 0.40718644 | K16: =SUM(K13:K15) -> 0.61113559 | L16: =SUM(L13:L15) -> 0.65161017
B18: Nata | C18: 300 | D18: 400 | E18: 500 | F18: 600 | G18: 600 | H18: 2.36 | I18: =(C18*H18)/G18 -> 1.18 | J18: =(D18*H18)/G18 -> 1.5733333 | K18: =(E18*H18)/G18 -> 1.9666667 | L18: =(F18*H18)/G18 -> 2.36
A19: RELLENO | B19: Queso phila | C19: 100 | D19: 150 | E19: 200 | F19: 200 | G19: 250 | H19: 2 | I19: =(C19*H19)/G19 -> 0.8 | J19: =(D19*H19)/G19 -> 1.2 | K19: =(E19*H19)/G19 -> 1.6 | L19: =(F19*H19)/G19 -> 1.6
A20: kinder | B20: KINDER | C20: 108 | D20: 108 | E20: 108 | F20: 150 | G20: 108 | H20: 2.99 | I20: =(C20*H20)/G20 -> 2.99 | J20: =(D20*H20)/G20 -> 2.99 | K20: =(E20*H20)/G20 -> 2.99 | L20: =(F20*H20)/G20 -> 4.1527778
B21: Azucar blanca | C21: 80 | D21: 90 | E21: 100 | F21: 120 | G21: 1000 | H21: 1.49 | I21: =(C21*H21)/G21 -> 0.1192 | J21: =(D21*H21)/G21 -> 0.1341 | K21: =(E21*H21)/G21 -> 0.149 | L21: =(F21*H21)/G21 -> 0.1788
B22: Vainilla | C22: 5 | D22: 7 | E22: 9 | F22: 8 | G22: 236 | H22: 6.9 | I22: =(C22*H22)/G22 -> 0.14618644 | J22: =(D22*H22)/G22 -> 0.20466102 | K22: =(E22*H22)/G22 -> 0.26313559 | L22: =(F22*H22)/G22 -> 0.23389831
I23: =SUM(I18:I22) -> 5.2353864 | J23: =SUM(J18:J22) -> 6.1020943 | K23: =SUM(K18:K22) -> 6.9688023 | L23: =SUM(L18:L22) -> 8.5254761
A25: COBERTURA | B25: Nata | C25: 150 | D25: 200 | E25: 200 | F25: 450 | G25: 600 | H25: 2.36 | I25: =(C25*H25)/G25 -> 0.59 | J25: =(D25*H25)/G25 -> 0.78666667 | K25: =(E25*H25)/G25 -> 0.78666667 | L25: =(F25*H25)/G25 -> 1.77
A26: CREMA DE | B26: CHOCOLATE | C26: 500 | D26: 600 | E26: 600 | F26: 900 | G26: 100 | H26: 1.15 | I26: =(C26*H26)/G26 -> 5.75 | J26: =(D26*H26)/G26 -> 6.9 | K26: =(E26*H26)/G26 -> 6.9 | L26: =(F26*H26)/G26 -> 10.35
A27: GANACHE | B27: KINDER | C27: 0 | D27: 0 | E27: 0 | F27: 0 | G27: 100 | H27: 1.79 | I27: =(C27*H27)/G27 -> 0 | J27: =(D27*H27)/G27 -> 0 | K27: =(E27*H27)/G27 -> 0 | L27: =(F27*H27)/G27 -> 0
B28: Fondant | C28: 200 | D28: 250 | E28: 300 | F28: 350 | G28: 2000 | H28: 10.75 | I28: =(C28*H28)/G28 -> 1.075 | J28: =(D28*H28)/G28 -> 1.34375 | K28: =(E28*H28)/G28 -> 1.6125 | L28: =(F28*H28)/G28 -> 1.88125
I29: =SUM(I25:I28) -> 7.415 | J29: =SUM(J25:J28) -> 9.0304167 | K29: =SUM(K25:K28) -> 9.2991667 | L29: =SUM(L25:L28) -> 14.00125
B31: papel horno | C31: 1 | D31: 1 | E31: 1 | F31: 1 | G31: 20 | H31: 1.13 | I31: =(C31*H31)/G31 -> 0.0565 | J31: =(C31*H31)/G31 -> 0.0565 | K31: =(E31*H31)/G31 -> 0.0565 | L31: =(F31*H31)/G31 -> 0.0565
B32: Papel plata | C32: 1 | D32: 1 | E32: 1 | F32: 1 | G32: 1000 | H32: 2.05 | I32: =(C32*H32)/G32 -> 0.00205 | J32: =(C32*H32)/G32 -> 0.00205 | K32: =(E32*H32)/G32 -> 0.00205 | L32: =(F32*H32)/G32 -> 0.00205
B33: Horno | C33: 30 | D33: 35 | E33: 40 | F33: 40 | G33: 60 | H33: 1 | I33: =(C33*H33)/G33 -> 0.5 | J33: =(C33*H33)/G33 -> 0.5 | K33: =(E33*H33)/G33 -> 0.66666667 | L33: =(F33*H33)/G33 -> 0.66666667
A34: COSTES | B34: Agua | C34: 12 | D34: 12 | E34: 12 | F34: 12 | G34: 1000 | H34: 1.97 | I34: =(C34*H34)/G34 -> 0.02364 | J34: =(C34*H34)/G34 -> 0.02364 | K34: =(E34*H34)/G34 -> 0.02364 | L34: =(F34*H34)/G34 -> 0.02364
A35: INDIRECTOS | B35: Batidora | C35: 12 | D35: 12 | E35: 12 | F35: 12 | G35: 60 | H35: 1 | I35: =(C35*H35)/G35 -> 0.2 | J35: =(C35*H35)/G35 -> 0.2 | K35: =(E35*H35)/G35 -> 0.2 | L35: =(F35*H35)/G35 -> 0.2
I39: =SUM(I31:I38) -> 0.78219 | J39: =SUM(J31:J38) -> 0.78219 | K39: =SUM(K31:K38) -> 0.94885667 | L39: =SUM(L31:L38) -> 0.94885667
B42: Topper | C42: 1 | D42: 1 | E42: 1 | F42: 1 | G42: 1 | H42: 1.8 | I42: =(C42*H42)/G42 -> 1.8 | J42: =(C42*H42)/G42 -> 1.8 | K42: =(E42*H42)/G42 -> 1.8 | L42: =(F42*H42)/G42 -> 1.8
B43: Vela | C43: 1 | D43: 1 | E43: 1 | F43: 1 | G43: 6 | H43: 1 | I43: =(C43*H43)/G43 -> 0.16666667 | J43: =(C43*H43)/G43 -> 0.16666667 | K43: =(E43*H43)/G43 -> 0.16666667 | L43: =(F43*H43)/G43 -> 0.16666667
B44: Plato 25 cm | C44: 1 | D44: 1 | E44: 1 | F44: 0 | G44: 1 | H44: 0.9 | I44: =(C44*H44)/G44 -> 0.9 | J44: =(C44*H44)/G44 -> 0.9 | K44: =(E44*H44)/G44 -> 0.9 | L44: =(F44*H44)/G44 -> 0
A45: EXTRAS | B45: Caja 25,5 | C45: 1 | D45: 1 | E45: 1 | F45: 0 | G45: 1 | H45: 2 | I45: =(C45*H45)/G45 -> 2 | J45: =(C45*H45)/G45 -> 2 | K45: =(E45*H45)/G45 -> 2 | L45: =(F45*H45)/G45 -> 0
B46: Etiqueta | C46: 1 | D46: 1 | E46: 1 | F46: 1 | G46: 500 | H46: 0.85 | I46: =(C46*H46)/G46 -> 0.0017 | J46: =(C46*H46)/G46 -> 0.0017 | K46: =(E46*H46)/G46 -> 0.0017 | L46: =(F46*H46)/G46 -> 0.0017
B47: Banda | C47: 2 | D47: 2 | E47: 2 | F47: 1 | G47: 2 | H47: 0.18 | I47: =(C47*H47)/G47 -> 0.18 | J47: =(C47*H47)/G47 -> 0.18 | K47: =(E47*H47)/G47 -> 0.18 | L47: =(F47*H47)/G47 -> 0.09
B48: plato 28 cm | C48: 0 | D48: 0 | E48: 0 | F48: 1 | G48: 1 | H48: 0.9 | I48: =(C48*H48)/G48 -> 0 | J48: =(C48*H48)/G48 -> 0 | K48: =(E48*H48)/G48 -> 0 | L48: =(F48*H48)/G48 -> 0.9
B49: caja 28 cm | C49: 0 | D49: 0 | E49: 0 | F49: 1 | G49: 1 | H49: 2 | I49: =(C49*H49)/G49 -> 0 | J49: =(C49*H49)/G49 -> 0 | K49: =(E49*H49)/G49 -> 0 | L49: =(F49*H49)/G49 -> 2
B50: Sprinkles | C50: 10 | D50: 10 | E50: 10 | F50: 12 | G50: 100 | H50: 6 | I50: =(C50*H50)/G50 -> 0.6 | J50: =(C50*H50)/G50 -> 0.6 | K50: =(E50*H50)/G50 -> 0.6 | L50: =(F50*H50)/G50 -> 0.72
B51: Decoraciones | C51: 3 | D51: 3 | E51: 3 | F51: 3 | G51: 10 | H51: 10 | I51: =(C51*H51)/G51 -> 3 | J51: =(C51*H51)/G51 -> 3 | K51: =(E51*H51)/G51 -> 3 | L51: =(F51*H51)/G51 -> 3
I52: =SUM(I42:I51) -> 8.6483667 | J52: =SUM(J42:J51) -> 8.6483667 | K52: =SUM(K42:K51) -> 8.6483667 | L52: =SUM(L42:L51) -> 8.6783667
H55: COSTE TOTAL | I55: =SUM(I11+I16+I23+I29+I39+I52) -> 24.773308 | J55: =SUM(J11+J16+J23+J29+J39+J52) -> 28.157677 | K55: =SUM(K11+K16+K23+K29+K39+K52) -> 30.548767 | L55: =SUM(L11+L16+L23+L29+L39+L52) -> 37.549319
H56: VENTA | I56: 45 | J56: 50 | K56: 55 | L56: 65
H57: GANANCIA | I57: =(I56-I55) -> 20.226692 | J57: =(J56-J55) -> 21.842323 | K57: =(K56-K55) -> 24.451233 | L57: =(L56-L55) -> 27.450681

Sheet Dos pisos temática
C3: 16 cm | D3: 18 cm | E3: 20 cm | F3: 22-24 cm | I3: 16 cm | J3: 18 cm | K3: 20 cm | L3: 22-24 cm
B4: INGREDIENTES | C4: CANT 8-10 p | D4: CANT 10-15 p | E4: CANT 18-20 | F4: CANT 20-25 | G4: UNIDADES PAQ | H4: PRECIO | I4: CANT 8-10 p | J4: CANT 10-15 p | K4: CANT 18-20 | L4: CANT 20-25
B5: Harina | C5: 140 | D5: 180 | E5: 240 | F5: 270 | G5: 1000 | H5: 1.07 | I5: =(C5*H5)/G5 -> 0.1498 | J5: =(D5*H5)/G5 -> 0.1926 | K5: =(E5*H5)/G5 -> 0.2568 | L5: =(F5*H5)/G5 -> 0.2889
A6: BiZCOCHO | B6: Huevos | C6: 5 | D6: 6 | E6: 8 | F6: 9 | G6: 12 | H6: 2.5 | I6: =(C6*H6)/G6 -> 1.0416667 | J6: =(D6*H6)/G6 -> 1.25 | K6: =(E6*H6)/G6 -> 1.6666667 | L6: =(F6*H6)/G6 -> 1.875
A7: CHOCOLATE | B7: Azucar | C7: 150 | D7: 180 | E7: 240 | F7: 270 | G7: 1000 | H7: 1.49 | I7: =(C7*H7)/G7 -> 0.2235 | J7: =(D7*H7)/G7 -> 0.2682 | K7: =(E7*H7)/G7 -> 0.3576 | L7: =(F7*H7)/G7 -> 0.4023
B8: Vainilla | C8: 5 | D8: 10 | E8: 10 | F8: 15 | G8: 236 | H8: 6.9 | I8: =(C8*H8)/G8 -> 0.14618644 | J8: =(D8*H8)/G8 -> 0.29237288 | K8: =(E8*H8)/G8 -> 0.29237288 | L8: =(F8*H8)/G8 -> 0.43855932
B9: Cacao | C9: 30 | D9: 40 | E9: 50 | F9: 60 | G9: 250 | H9: 6 | I9: =(C9*H9)/G9 -> 0.72 | J9: =(D9*H9)/G9 -> 0.96 | K9: =(E9*H9)/G9 -> 1.2 | L9: =(F9*H9)/G9 -> 1.44
B10: Maicena | C10: 20 | D10: 30 | E10: 40 | F10: 40 | G10: 400 | H10: 2.99 | I10: =(C10*H10)/G10 -> 0.1495 | J10: =(D10*H10)/G10 -> 0.22425 | K10: =(E10*H10)/G10 -> 0.299 | L10: =(F10*H10)/G10 -> 0.299
I11: =SUM(I5:I10) -> 2.4306531 | J11: =SUM(J5:J10) -> 3.1874229 | K11: =SUM(K5:K10) -> 4.0724395 | L11: =SUM(L5:L10) -> 4.7437593
B13: Azucar | C13: 100 | D13: 150 | E13: 200 | F13: 250 | G13: 1000 | H13: 1.49 | I13: =(C13*H13)/G13 -> 0.149 | J13: =(D13*H13)/G13 -> 0.2235 | K13: =(E13*H13)/G13 -> 0.298 | L13: =(F13*H5)/G5 -> 0.2675
A14: ALMIBAR | B14: Agua | C14: 100 | D14: 150 | E14: 200 | F14: 250 | G14: 1000 | H14: 0.25 | I14: =(C14*H14)/G14 -> 0.025 | J14: =(D14*H14)/G14 -> 0.0375 | K14: =(E14*H14)/G14 -> 0.05 | L14: =(F14*H14)/G14 -> 0.0625
B15: Vainilla | C15: 3 | D15: 5 | E15: 9 | F15: 11 | G15: 236 | H15: 6.9 | I15: =(C15*H15)/G15 -> 0.087711864 | J15: =(D15*H15)/G15 -> 0.14618644 | K15: =(E15*H15)/G15 -> 0.26313559 | L15: =(F15*H15)/G15 -> 0.32161017
I16: =SUM(I13:I15) -> 0.26171186 | J16: =SUM(J13:J15) -> 0.40718644 | K16: =SUM(K13:K15) -> 0.61113559 | L16: =SUM(L13:L15) -> 0.65161017
B18: Nata | C18: 300 | D18: 400 | E18: 500 | F18: 600 | G18: 600 | H18: 2.36 | I18: =(C18*H18)/G18 -> 1.18 | J18: =(D18*H18)/G18 -> 1.5733333 | K18: =(E18*H18)/G18 -> 1.9666667 | L18: =(F18*H18)/G18 -> 2.36
A19: RELLENO | B19: Queso phila | C19: 100 | D19: 150 | E19: 200 | F19: 200 | G19: 250 | H19: 2 | I19: =(C19*H19)/G19 -> 0.8 | J19: =(D19*H19)/G19 -> 1.2 | K19: =(E19*H19)/G19 -> 1.6 | L19: =(F19*H19)/G19 -> 1.6
A20: kinder | B20: KINDER | C20: 108 | D20: 108 | E20: 108 | F20: 150 | G20: 108 | H20: 2.99 | I20: =(C20*H20)/G20 -> 2.99 | J20: =(D20*H20)/G20 -> 2.99 | K20: =(E20*H20)/G20 -> 2.99 | L20: =(F20*H20)/G20 -> 4.1527778
B21: Azucar blanca | C21: 80 | D21: 90 | E21: 100 | F21: 120 | G21: 1000 | H21: 1.49 | I21: =(C21*H21)/G21 -> 0.1192 | J21: =(D21*H21)/G21 -> 0.1341 | K21: =(E21*H21)/G21 -> 0.149 | L21: =(F21*H21)/G21 -> 0.1788
B22: Vainilla | C22: 5 | D22: 7 | E22: 9 | F22: 8 | G22: 236 | H22: 6.9 | I22: =(C22*H22)/G22 -> 0.14618644 | J22: =(D22*H22)/G22 -> 0.20466102 | K22: =(E22*H22)/G22 -> 0.26313559 | L22: =(F22*H22)/G22 -> 0.23389831
I23: =SUM(I18:I22) -> 5.2353864 | J23: =SUM(J18:J22) -> 6.1020943 | K23: =SUM(K18:K22) -> 6.9688023 | L23: =SUM(L18:L22) -> 8.5254761
A25: COBERTURA | B25: Nata | C25: 150 | D25: 200 | E25: 200 | F25: 450 | G25: 600 | H25: 2.36 | I25: =(C25*H25)/G25 -> 0.59 | J25: =(D25*H25)/G25 -> 0.78666667 | K25: =(E25*H25)/G25 -> 0.78666667 | L25: =(F25*H25)/G25 -> 1.77
A26: CREMA DE | B26: CHOCOLATE | C26: 500 | D26: 600 | E26: 600 | F26: 900 | G26: 100 | H26: 1.15 | I26: =(C26*H26)/G26 -> 5.75 | J26: =(D26*H26)/G26 -> 6.9 | K26: =(E26*H26)/G26 -> 6.9 | L26: =(F26*H26)/G26 -> 10.35
A27: GANACHE | B27: KINDER | C27: 0 | D27: 0 | E27: 0 | F27: 0 | G27: 100 | H27: 1.79 | I27: =(C27*H27)/G27 -> 0 | J27: =(D27*H27)/G27 -> 0 | K27: =(E27*H27)/G27 -> 0 | L27: =(F27*H27)/G27 -> 0
B28: Fondant | C28: 200 | D28: 250 | E28: 300 | F28: 350 | G28: 2000 | H28: 10.75 | I28: =(C28*H28)/G28 -> 1.075 | J28: =(D28*H28)/G28 -> 1.34375 | K28: =(E28*H28)/G28 -> 1.6125 | L28: =(F28*H28)/G28 -> 1.88125
I29: =SUM(I25:I28) -> 7.415 | J29: =SUM(J25:J28) -> 9.0304167 | K29: =SUM(K25:K28) -> 9.2991667 | L29: =SUM(L25:L28) -> 14.00125
B31: papel horno | C31: 1 | D31: 1 | E31: 1 | F31: 1 | G31: 20 | H31: 1.13 | I31: =(C31*H31)/G31 -> 0.0565 | J31: =(C31*H31)/G31 -> 0.0565 | K31: =(E31*H31)/G31 -> 0.0565 | L31: =(F31*H31)/G31 -> 0.0565
B32: Papel plata | C32: 1 | D32: 1 | E32: 1 | F32: 1 | G32: 1000 | H32: 2.05 | I32: =(C32*H32)/G32 -> 0.00205 | J32: =(C32*H32)/G32 -> 0.00205 | K32: =(E32*H32)/G32 -> 0.00205 | L32: =(F32*H32)/G32 -> 0.00205
B33: Horno | C33: 30 | D33: 35 | E33: 40 | F33: 40 | G33: 60 | H33: 1 | I33: =(C33*H33)/G33 -> 0.5 | J33: =(C33*H33)/G33 -> 0.5 | K33: =(E33*H33)/G33 -> 0.66666667 | L33: =(F33*H33)/G33 -> 0.66666667
A34: COSTES | B34: Agua | C34: 12 | D34: 12 | E34: 12 | F34: 12 | G34: 1000 | H34: 1.97 | I34: =(C34*H34)/G34 -> 0.02364 | J34: =(C34*H34)/G34 -> 0.02364 | K34: =(E34*H34)/G34 -> 0.02364 | L34: =(F34*H34)/G34 -> 0.02364
A35: INDIRECTOS | B35: Batidora | C35: 12 | D35: 12 | E35: 12 | F35: 12 | G35: 60 | H35: 1 | I35: =(C35*H35)/G35 -> 0.2 | J35: =(C35*H35)/G35 -> 0.2 | K35: =(E35*H35)/G35 -> 0.2 | L35: =(F35*H35)/G35 -> 0.2
I39: =SUM(I31:I38) -> 0.78219 | J39: =SUM(J31:J38) -> 0.78219 | K39: =SUM(K31:K38) -> 0.94885667 | L39: =SUM(L31:L38) -> 0.94885667
B42: Topper | C42: 1 | D42: 1 | E42: 1 | F42: 1 | G42: 1 | H42: 1.8 | I42: =(C42*H42)/G42 -> 1.8 | J42: =(C42*H42)/G42 -> 1.8 | K42: =(E42*H42)/G42 -> 1.8 | L42: =(F42*H42)/G42 -> 1.8
B43: Vela | C43: 1 | D43: 1 | E43: 1 | F43: 1 | G43: 6 | H43: 1 | I43: =(C43*H43)/G43 -> 0.16666667 | J43: =(C43*H43)/G43 -> 0.16666667 | K43: =(E43*H43)/G43 -> 0.16666667 | L43: =(F43*H43)/G43 -> 0.16666667
B44: Plato 25 cm | C44: 1 | D44: 1 | E44: 1 | F44: 0 | G44: 1 | H44: 0.9 | I44: =(C44*H44)/G44 -> 0.9 | J44: =(C44*H44)/G44 -> 0.9 | K44: =(E44*H44)/G44 -> 0.9 | L44: =(F44*H44)/G44 -> 0
A45: EXTRAS | B45: Caja 25,5 | C45: 1 | D45: 1 | E45: 1 | F45: 0 | G45: 1 | H45: 2 | I45: =(C45*H45)/G45 -> 2 | J45: =(C45*H45)/G45 -> 2 | K45: =(E45*H45)/G45 -> 2 | L45: =(F45*H45)/G45 -> 0
B46: Etiqueta | C46: 1 | D46: 1 | E46: 1 | F46: 1 | G46: 500 | H46: 0.85 | I46: =(C46*H46)/G46 -> 0.0017 | J46: =(C46*H46)/G46 -> 0.0017 | K46: =(E46*H46)/G46 -> 0.0017 | L46: =(F46*H46)/G46 -> 0.0017
B47: Banda | C47: 2 | D47: 2 | E47: 2 | F47: 1 | G47: 2 | H47: 0.18 | I47: =(C47*H47)/G47 -> 0.18 | J47: =(C47*H47)/G47 -> 0.18 | K47: =(E47*H47)/G47 -> 0.18 | L47: =(F47*H47)/G47 -> 0.09
B48: plato 28 cm | C48: 0 | D48: 0 | E48: 0 | F48: 1 | G48: 1 | H48: 0.9 | I48: =(C48*H48)/G48 -> 0 | J48: =(C48*H48)/G48 -> 0 | K48: =(E48*H48)/G48 -> 0 | L48: =(F48*H48)/G48 -> 0.9
B49: caja 28 cm | C49: 0 | D49: 0 | E49: 0 | F49: 1 | G49: 1 | H49: 2 | I49: =(C49*H49)/G49 -> 0 | J49: =(C49*H49)/G49 -> 0 | K49: =(E49*H49)/G49 -> 0 | L49: =(F49*H49)/G49 -> 2
B50: Sprinkles | C50: 10 | D50: 10 | E50: 10 | F50: 12 | G50: 100 | H50: 6 | I50: =(C50*H50)/G50 -> 0.6 | J50: =(C50*H50)/G50 -> 0.6 | K50: =(E50*H50)/G50 -> 0.6 | L50: =(F50*H50)/G50 -> 0.72
B51: Decoraciones | C51: 3 | D51: 3 | E51: 3 | F51: 3 | G51: 10 | H51: 10 | I51: =(C51*H51)/G51 -> 3 | J51: =(C51*H51)/G51 -> 3 | K51: =(E51*H51)/G51 -> 3 | L51: =(F51*H51)/G51 -> 3
I52: =SUM(I42:I51) -> 8.6483667 | J52: =SUM(J42:J51) -> 8.6483667 | K52: =SUM(K42:K51) -> 8.6483667 | L52: =SUM(L42:L51) -> 8.6783667
H55: COSTE TOTAL | I55: =SUM(I11+I16+I23+I29+I39+I52) -> 24.773308 | J55: =SUM(J11+J16+J23+J29+J39+J52) -> 28.157677 | K55: =SUM(K11+K16+K23+K29+K39+K52) -> 30.548767 | L55: =SUM(L11+L16+L23+L29+L39+L52) -> 37.549319
H56: VENTA | I56: 45 | J56: 50 | K56: 55 | L56: 65
H57: GANANCIA | I57: =(I56-I55) -> 20.226692 | J57: =(J56-J55) -> 21.842323 | K57: =(K56-K55) -> 24.451233 | L57: =(L56-L55) -> 27.450681

Sheet TARTA FULL CHOCOLATE
D1: TARTA FULL CHOCOLATE
E2: BIZC. CHOCO. RELLENO DE GANACHE Y MOUSSE COB GANACHE
C4: 16 cm | D4: 18 cm | E4: 20 cm | F4: 22-24 cm | I4: 16 cm | J4: 18 cm | K4: 20 cm | L4: 22-24 cm
B5: INGREDIENTES | C5: CANT 8-10 p | D5: CANT 10-15 p | E5: CANT 18-20 | F5: CANT 20-25 | G5: UNIDADES PAQ | H5: PRECIO | I5: CANT 8-10 p | J5: CANT 10-15 p | K5: CANT 18-20 | L5: CANT 20-25
B6: Harina | C6: 140 | D6: 180 | E6: 240 | F6: 270 | G6: 1000 | H6: 1.07 | I6: =(C6*H6)/G6 -> 0.1498 | J6: =(D6*H6)/G6 -> 0.1926 | K6: =(E6*H6)/G6 -> 0.2568 | L6: =(F6*H6)/G6 -> 0.2889
A7: BiZCOCHO | B7: Huevos | C7: 5 | D7: 6 | E7: 8 | F7: 9 | G7: 12 | H7: 2.5 | I7: =(C7*H7)/G7 -> 1.0416667 | J7: =(D7*H7)/G7 -> 1.25 | K7: =(E7*H7)/G7 -> 1.6666667 | L7: =(F7*H7)/G7 -> 1.875
A8: CHOCOLATE | B8: Azucar | C8: 150 | D8: 180 | E8: 240 | F8: 270 | G8: 1000 | H8: 1.49 | I8: =(C8*H8)/G8 -> 0.2235 | J8: =(D8*H8)/G8 -> 0.2682 | K8: =(E8*H8)/G8 -> 0.3576 | L8: =(F8*H8)/G8 -> 0.4023
B9: Vainilla | C9: 5 | D9: 10 | E9: 10 | F9: 15 | G9: 236 | H9: 6.9 | I9: =(C9*H9)/G9 -> 0.14618644 | J9: =(D9*H9)/G9 -> 0.29237288 | K9: =(E9*H9)/G9 -> 0.29237288 | L9: =(F9*H9)/G9 -> 0.43855932
B10: Cacao | C10: 30 | D10: 40 | E10: 50 | F10: 60 | G10: 250 | H10: 6 | I10: =(C10*H10)/G10 -> 0.72 | J10: =(D10*H10)/G10 -> 0.96 | K10: =(E10*H10)/G10 -> 1.2 | L10: =(F10*H10)/G10 -> 1.44
B11: Maicena | C11: 20 | D11: 30 | E11: 40 | F11: 40 | G11: 400 | H11: 2.99 | I11: =(C11*H11)/G11 -> 0.1495 | J11: =(D11*H11)/G11 -> 0.22425 | K11: =(E11*H11)/G11 -> 0.299 | L11: =(F11*H11)/G11 -> 0.299
I12: =SUM(I6:I11) -> 2.4306531 | J12: =SUM(J6:J11) -> 3.1874229 | K12: =SUM(K6:K11) -> 4.0724395 | L12: =SUM(L6:L11) -> 4.7437593
B14: Azucar | C14: 100 | D14: 150 | E14: 200 | F14: 250 | G14: 1000 | H14: 1.49 | I14: =(C14*H14)/G14 -> 0.149 | J14: =(D14*H14)/G14 -> 0.2235 | K14: =(E14*H14)/G14 -> 0.298 | L14: =(F14*H6)/G6 -> 0.2675
A15: ALMIBAR | B15: Agua | C15: 100 | D15: 150 | E15: 200 | F15: 250 | G15: 1000 | H15: 0.25 | I15: =(C15*H15)/G15 -> 0.025 | J15: =(D15*H15)/G15 -> 0.0375 | K15: =(E15*H15)/G15 -> 0.05 | L15: =(F15*H15)/G15 -> 0.0625
B16: Vainilla | C16: 3 | D16: 5 | E16: 9 | F16: 11 | G16: 236 | H16: 6.9 | I16: =(C16*H16)/G16 -> 0.087711864 | J16: =(D16*H16)/G16 -> 0.14618644 | K16: =(E16*H16)/G16 -> 0.26313559 | L16: =(F16*H16)/G16 -> 0.32161017
I17: =SUM(I14:I16) -> 0.26171186 | J17: =SUM(J14:J16) -> 0.40718644 | K17: =SUM(K14:K16) -> 0.61113559 | L17: =SUM(L14:L16) -> 0.65161017
B19: Nata | C19: 400 | D19: 600 | E19: 800 | F19: 900 | G19: 600 | H19: 2.36 | I19: =(C19*H19)/G19 -> 1.5733333 | J19: =(D19*H19)/G19 -> 2.36 | K19: =(E19*H19)/G19 -> 3.1466667 | L19: =(F19*H19)/G19 -> 3.54
A20: RELLENO | B20: Queso phila | C20: 100 | D20: 150 | E20: 200 | F20: 200 | G20: 250 | H20: 2 | I20: =(C20*H20)/G20 -> 0.8 | J20: =(D20*H20)/G20 -> 1.2 | K20: =(E20*H20)/G20 -> 1.6 | L20: =(F20*H20)/G20 -> 1.6
A21: GANACHE | B21: CHOCOLATE | C21: 100 | D21: 200 | E21: 300 | F21: 400 | G21: 100 | H21: 1.19 | I21: =(C21*H21)/G21 -> 1.19 | J21: =(D21*H21)/G21 -> 2.38 | K21: =(E21*H21)/G21 -> 3.57 | L21: =(F21*H21)/G21 -> 4.76
A22: MOUSSE CHOCOLAT | B22: Azucar blanca | C22: 80 | D22: 90 | E22: 100 | F22: 120 | G22: 1000 | H22: 1.49 | I22: =(C22*H22)/G22 -> 0.1192 | J22: =(D22*H22)/G22 -> 0.1341 | K22: =(E22*H22)/G22 -> 0.149 | L22: =(F22*H22)/G22 -> 0.1788
B23: CACAO | C23: 20 | D23: 30 | E23: 40 | F23: 50 | G23: 450 | H23: 5 | I23: =(C23*H23)/G23 -> 0.22222222 | J23: =(D23*H23)/G23 -> 0.33333333 | K23: =(E23*H23)/G23 -> 0.44444444 | L23: =(F23*H23)/G23 -> 0.55555556
I24: =SUM(I19:I23) -> 3.9047556 | J24: =SUM(J19:J23) -> 6.4074333 | K24: =SUM(K19:K23) -> 8.9101111 | L24: =SUM(L19:L23) -> 10.634356
A26: COBERTURA | B26: Nata | C26: 300 | D26: 400 | E26: 450 | F26: 500 | G26: 600 | H26: 2.36 | I26: =(C26*H26)/G26 -> 1.18 | J26: =(D26*H26)/G26 -> 1.5733333 | K26: =(E26*H26)/G26 -> 1.77 | L26: =(F26*H26)/G26 -> 1.9666667
A27: CREMA DE | B27: CHOCOLATE | C27: 300 | D27: 400 | E27: 450 | F27: 500 | G27: 100 | H27: 1.15 | I27: =(C27*H27)/G27 -> 3.45 | J27: =(D27*H27)/G27 -> 4.6 | K27: =(E27*H27)/G27 -> 5.175 | L27: =(F27*H27)/G27 -> 5.75
A28: GANACHE | B28: KINDER | C28: 0 | D28: 0 | E28: 0 | F28: 0 | G28: 100 | H28: 1.79 | I28: =(C28*H28)/G28 -> 0 | J28: =(D28*H28)/G28 -> 0 | K28: =(E28*H28)/G28 -> 0 | L28: =(F28*H28)/G28 -> 0
B29: Fondant | C29: 0 | D29: 0 | E29: 0 | F29: 0 | G29: 2000 | H29: 10.75 | I29: =(C29*H29)/G29 -> 0 | J29: =(D29*H29)/G29 -> 0 | K29: =(E29*H29)/G29 -> 0 | L29: =(F29*H29)/G29 -> 0
I30: =SUM(I26:I29) -> 4.63 | J30: =SUM(J26:J29) -> 6.1733333 | K30: =SUM(K26:K29) -> 6.945 | L30: =SUM(L26:L29) -> 7.7166667
B32: papel horno | C32: 1 | D32: 1 | E32: 1 | F32: 1 | G32: 20 | H32: 1.13 | I32: =(C32*H32)/G32 -> 0.0565 | J32: =(C32*H32)/G32 -> 0.0565 | K32: =(E32*H32)/G32 -> 0.0565 | L32: =(F32*H32)/G32 -> 0.0565
B33: Papel plata | C33: 1 | D33: 1 | E33: 1 | F33: 1 | G33: 1000 | H33: 2.05 | I33: =(C33*H33)/G33 -> 0.00205 | J33: =(C33*H33)/G33 -> 0.00205 | K33: =(E33*H33)/G33 -> 0.00205 | L33: =(F33*H33)/G33 -> 0.00205
B34: Horno | C34: 30 | D34: 35 | E34: 40 | F34: 40 | G34: 60 | H34: 1 | I34: =(C34*H34)/G34 -> 0.5 | J34: =(C34*H34)/G34 -> 0.5 | K34: =(E34*H34)/G34 -> 0.66666667 | L34: =(F34*H34)/G34 -> 0.66666667
A35: COSTES | B35: Agua | C35: 12 | D35: 12 | E35: 12 | F35: 12 | G35: 1000 | H35: 1.97 | I35: =(C35*H35)/G35 -> 0.02364 | J35: =(C35*H35)/G35 -> 0.02364 | K35: =(E35*H35)/G35 -> 0.02364 | L35: =(F35*H35)/G35 -> 0.02364
A36: INDIRECTOS | B36: Batidora | C36: 12 | D36: 12 | E36: 12 | F36: 12 | G36: 60 | H36: 1 | I36: =(C36*H36)/G36 -> 0.2 | J36: =(C36*H36)/G36 -> 0.2 | K36: =(E36*H36)/G36 -> 0.2 | L36: =(F36*H36)/G36 -> 0.2
I40: =SUM(I32:I39) -> 0.78219 | J40: =SUM(J32:J39) -> 0.78219 | K40: =SUM(K32:K39) -> 0.94885667 | L40: =SUM(L32:L39) -> 0.94885667
B43: Topper | C43: 1 | D43: 1 | E43: 1 | F43: 1 | G43: 1 | H43: 1.8 | I43: =(C43*H43)/G43 -> 1.8 | J43: =(C43*H43)/G43 -> 1.8 | K43: =(E43*H43)/G43 -> 1.8 | L43: =(F43*H43)/G43 -> 1.8
B44: Vela | C44: 1 | D44: 1 | E44: 1 | F44: 1 | G44: 6 | H44: 1 | I44: =(C44*H44)/G44 -> 0.16666667 | J44: =(C44*H44)/G44 -> 0.16666667 | K44: =(E44*H44)/G44 -> 0.16666667 | L44: =(F44*H44)/G44 -> 0.16666667
B45: Plato 25 cm | C45: 1 | D45: 1 | E45: 1 | F45: 0 | G45: 1 | H45: 0.9 | I45: =(C45*H45)/G45 -> 0.9 | J45: =(C45*H45)/G45 -> 0.9 | K45: =(E45*H45)/G45 -> 0.9 | L45: =(F45*H45)/G45 -> 0
A46: EXTRAS | B46: Caja 25,5 | C46: 1 | D46: 1 | E46: 1 | F46: 0 | G46: 1 | H46: 2 | I46: =(C46*H46)/G46 -> 2 | J46: =(C46*H46)/G46 -> 2 | K46: =(E46*H46)/G46 -> 2 | L46: =(F46*H46)/G46 -> 0
B47: Etiqueta | C47: 1 | D47: 1 | E47: 1 | F47: 1 | G47: 500 | H47: 0.85 | I47: =(C47*H47)/G47 -> 0.0017 | J47: =(C47*H47)/G47 -> 0.0017 | K47: =(E47*H47)/G47 -> 0.0017 | L47: =(F47*H47)/G47 -> 0.0017
B48: Banda | C48: 2 | D48: 2 | E48: 2 | F48: 1 | G48: 2 | H48: 0.18 | I48: =(C48*H48)/G48 -> 0.18 | J48: =(C48*H48)/G48 -> 0.18 | K48: =(E48*H48)/G48 -> 0.18 | L48: =(F48*H48)/G48 -> 0.09
B49: plato 28 cm | C49: 0 | D49: 0 | E49: 0 | F49: 1 | G49: 1 | H49: 0.9 | I49: =(C49*H49)/G49 -> 0 | J49: =(C49*H49)/G49 -> 0 | K49: =(E49*H49)/G49 -> 0 | L49: =(F49*H49)/G49 -> 0.9
B50: caja 28 cm | C50: 0 | D50: 0 | E50: 0 | F50: 1 | G50: 1 | H50: 2 | I50: =(C50*H50)/G50 -> 0 | J50: =(C50*H50)/G50 -> 0 | K50: =(E50*H50)/G50 -> 0 | L50: =(F50*H50)/G50 -> 2
B51: Sprinkles | C51: 10 | D51: 10 | E51: 10 | F51: 12 | G51: 100 | H51: 6 | I51: =(C51*H51)/G51 -> 0.6 | J51: =(C51*H51)/G51 -> 0.6 | K51: =(E51*H51)/G51 -> 0.6 | L51: =(F51*H51)/G51 -> 0.72
B52: Decoraciones | C52: 3 | D52: 3 | E52: 3 | F52: 3 | G52: 10 | H52: 10 | I52: =(C52*H52)/G52 -> 3 | J52: =(C52*H52)/G52 -> 3 | K52: =(E52*H52)/G52 -> 3 | L52: =(F52*H52)/G52 -> 3
I53: =SUM(I43:I52) -> 8.6483667 | J53: =SUM(J43:J52) -> 8.6483667 | K53: =SUM(K43:K52) -> 8.6483667 | L53: =SUM(L43:L52) -> 8.6783667
H56: COSTE TOTAL | I56: =SUM(I12+I17+I24+I30+I40+I53) -> 20.657677 | J56: =SUM(J12+J17+J24+J30+J40+J53) -> 25.605933 | K56: =SUM(K12+K17+K24+K30+K40+K53) -> 30.13591 | L56: =SUM(L12+L17+L24+L30+L40+L53) -> 33.373615
H57: VENTA | I57: 45 | J57: 50 | K57: 55 | L57: 65
H58: GANANCIA | I58: =(I57-I56) -> 24.342323 | J58: =(J57-J56) -> 24.394067 | K58: =(K57-K56) -> 24.86409 | L58: =(L57-L56) -> 31.626385

Sheet TARTA KINDER
C3: 8-10P | D3: 12-15 P | E3: 20 P | F3: 25P
B4: INGREDIENTES | C4: 16 CM | D4: 18,5 CM | E4: 20 CM | F4: 24 CM | G4: UNIDADES PAQ | H4: PRECIO | I4: COSTO 16 | J4: COSTO 18 | K4: COSTO 20 | L4: COSTO 24
B5: Harina | C5: 140 | D5: 170 | E5: 230 | F5: 260 | G5: 1000 | H5: 1.07 | I5: =(C5*H5)/G5 -> 0.1498 | J5: =D6*H6/G6 -> 1.25 | K5: =(E5*H5)/G5 -> 0.2461 | L5: =(F5*H5)/G5 -> 0.2782
A6: BiZCOCHO | B6: Huevos | C6: 5 | D6: 6 | E6: 8 | F6: 9 | G6: 12 | H6: 2.5 | I6: =(C6*H6)/G6 -> 1.0416667 | J6: =D7*H7/G7 -> 0.225 | K6: =(E6*H6)/G6 -> 1.6666667 | L6: =(F6*H6)/G6 -> 1.875
A7: CHOCOLATE | B7: Azucar | C7: 150 | D7: 180 | E7: 240 | F7: 270 | G7: 1000 | H7: 1.25 | I7: =(C7*H7)/G7 -> 0.1875 | J7: =D8*H8/G8 -> 0.29237288 | K7: =(E7*H7)/G7 -> 0.3 | L7: =(F7*H7)/G7 -> 0.3375
B8: Vainilla | C8: 5 | D8: 10 | E8: 10 | F8: 10 | G8: 236 | H8: 6.9 | I8: =(C8*H8)/G8 -> 0.14618644 | J8: =D9*H9/G9 -> 0.72 | K8: =(E8*H8)/G8 -> 0.29237288 | L8: =(F8*H8)/G8 -> 0.29237288
B9: Cacao | C9: 30 | D9: 30 | E9: 40 | F9: 50 | G9: 250 | H9: 6 | I9: =(C9*H9)/G9 -> 0.72 | J9: =D10*H10/G10 -> 0.07475 | K9: =(E9*H9)/G9 -> 0.96 | L9: =(F9*H9)/G9 -> 1.2
B10: Maicena | C10: 20 | D10: 10 | E10: 10 | F10: 10 | G10: 400 | H10: 2.99 | I10: =(C10*H10)/G10 -> 0.1495 | J10: =D10*H10/G10 -> 0.07475 | K10: =(E10*H10)/G10 -> 0.07475 | L10: =(F10*H10)/G10 -> 0.07475
I11: =SUM(I5:I10) -> 2.3946531 | J11: =SUM(J5:J10) -> 2.6368729 | K11: =SUM(K5:K10) -> 3.5398895 | L11: =SUM(L5:L10) -> 4.0578229
B13: Azucar | C13: 100 | D13: 120 | E13: 150 | F13: 200 | G13: 1000 | H13: 1.25 | I13: =(C13*H13)/G13 -> 0.125 | J13: =D13*H13/G13 -> 0.15 | K13: =(E13*H13)/G13 -> 0.1875 | L13: =(F13*H13)/G13 -> 0.25
A14: ALMIBAR | B14: Agua | C14: 100 | D14: 120 | E14: 150 | F14: 200 | G14: 1000 | H14: 0.25 | I14: =(C14*H14)/G14 -> 0.025 | J14: =D14*H14/G14 -> 0.03 | K14: =(E14*H14)/G14 -> 0.0375 | L14: =(F14*H14)/G14 -> 0.05
B15: Vainilla | C15: 3 | D15: 4 | E15: 5 | F15: 9 | G15: 236 | H15: 6.9 | I15: =(C15*H15)/G15 -> 0.087711864 | J15: =D15*H15/G15 -> 0.11694915 | K15: =(E15*H15)/G15 -> 0.14618644 | L15: =(F15*H15)/G15 -> 0.26313559
I16: =SUM(I13:I15) -> 0.23771186 | J16: =SUM(J13:J15) -> 0.29694915 | K16: =SUM(K13:K15) -> 0.37118644 | L16: =SUM(L13:L15) -> 0.56313559
B18: Nata | C18: 300 | D18: 400 | E18: 500 | F18: 600 | G18: 600 | H18: 2.36 | I18: =(C18*H18)/G18 -> 1.18 | J18: =(D18*H18)/G18 -> 1.5733333 | K18: =(E18*H18)/G18 -> 1.9666667 | L18: =(F18*H18)/G18 -> 2.36
A19: RELLENO | B19: Queso phila | C19: 100 | D19: 150 | E19: 200 | F19: 200 | G19: 250 | H19: 2 | I19: =(C19*H19)/G19 -> 0.8 | J19: =(D19*H19)/G19 -> 1.2 | K19: =(E19*H19)/G19 -> 1.6 | L19: =(F19*H19)/G19 -> 1.6
A20: kinder | B20: KINDER | C20: 108 | D20: 108 | E20: 108 | F20: 150 | G20: 108 | H20: 2.99 | I20: =(C20*H20)/G20 -> 2.99 | J20: =(D20*H20)/G20 -> 2.99 | K20: =(E20*H20)/G20 -> 2.99 | L20: =(F20*H20)/G20 -> 4.1527778
B21: Azucar blanca | C21: 80 | D21: 90 | E21: 100 | F21: 120 | G21: 1000 | H21: 1.49 | I21: =(C21*H21)/G21 -> 0.1192 | J21: =(D21*H21)/G21 -> 0.1341 | K21: =(E21*H21)/G21 -> 0.149 | L21: =(F21*H21)/G21 -> 0.1788
B22: Vainilla | C22: 5 | D22: 7 | E22: 9 | F22: 8 | G22: 236 | H22: 6.9 | I22: =(C22*H22)/G22 -> 0.14618644 | J22: =(D22*H22)/G22 -> 0.20466102 | K22: =(E22*H22)/G22 -> 0.26313559 | L22: =(F22*H22)/G22 -> 0.23389831
I23: =SUM(I18:I22) -> 5.2353864 | J23: =SUM(J18:J22) -> 6.1020943 | K23: =SUM(K18:K22) -> 6.9688023 | L23: =SUM(L18:L22) -> 8.5254761
A25: COBERTURA | B25: Nata | C25: 150 | D25: 200 | E25: 200 | F25: 450 | G25: 600 | H25: 2.36 | I25: =(C25*H25)/G25 -> 0.59 | J25: =(D25*H25)/G25 -> 0.78666667 | K25: =(E25*H25)/G25 -> 0.78666667 | L25: =(F25*H25)/G25 -> 1.77
A26: CREMA DE | B26: CHOCOLATE | C26: 500 | D26: 600 | E26: 600 | F26: 900 | G26: 100 | H26: 1.15 | I26: =(C26*H26)/G26 -> 5.75 | J26: =(D26*H26)/G26 -> 6.9 | K26: =(E26*H26)/G26 -> 6.9 | L26: =(F26*H26)/G26 -> 10.35
A27: GANACHE | B27: KINDER | C27: 0 | D27: 0 | E27: 0 | F27: 0 | G27: 108 | H27: 2.99 | I27: =(C27*H27)/G27 -> 0 | J27: =(D27*H27)/G27 -> 0 | K27: =(E27*H27)/G27 -> 0 | L27: =(F27*H27)/G27 -> 0
B28: KINDER | C28: 200 | D28: 250 | E28: 300 | F28: 300 | G28: 108 | H28: 2.99 | I28: =(C28*H28)/G28 -> 5.537037 | J28: =(D28*H28)/G28 -> 6.9212963 | K28: =(E28*H28)/G28 -> 8.3055556 | L28: =(F28*H28)/G28 -> 8.3055556
I29: =SUM(I25:I28) -> 11.877037 | J29: =SUM(J25:J28) -> 14.607963 | K29: =SUM(K25:K28) -> 15.992222 | L29: =SUM(L25:L28) -> 20.425556
B31: papel horno | C31: 1 | D31: 1 | E31: 1 | F31: 1 | G31: 20 | H31: 1.13 | I31: =(C31*H31)/G31 -> 0.0565 | J31: =D31*H31/G31 -> 0.0565 | K31: =(C31*H31)/G31 -> 0.0565 | L31: =(F31*H31)/G31 -> 0.0565
B32: Papel plata | C32: 1 | D32: 1 | E32: 1 | F32: 1 | G32: 1000 | H32: 2.05 | I32: =(C32*H32)/G32 -> 0.00205 | J32: =D32*H32/G32 -> 0.00205 | K32: =(C32*H32)/G32 -> 0.00205 | L32: =(F32*H32)/G32 -> 0.00205
B33: Horno | C33: 30 | D33: 30 | E33: 35 | F33: 40 | G33: 60 | H33: 1 | I33: =(C33*H33)/G33 -> 0.5 | J33: =D33*H33/G33 -> 0.5 | K33: =(C33*H33)/G33 -> 0.5 | L33: =(F33*H33)/G33 -> 0.66666667
A34: COSTES | B34: Agua | C34: 12 | D34: 12 | E34: 12 | F34: 12 | G34: 1000 | H34: 1.97 | I34: =(C34*H34)/G34 -> 0.02364 | J34: =D34*H34/G34 -> 0.02364 | K34: =(C34*H34)/G34 -> 0.02364 | L34: =(F34*H34)/G34 -> 0.02364
A35: INDIRECTOS | B35: Batidora | C35: 12 | D35: 12 | E35: 12 | F35: 12 | G35: 60 | H35: 1 | I35: =(C35*H35)/G35 -> 0.2 | J35: =D35*H35/G35 -> 0.2 | K35: =(C35*H35)/G35 -> 0.2 | L35: =(F35*H35)/G35 -> 0.2
I39: =SUM(I31:I38) -> 0.78219 | J39: =SUM(J31:J38) -> 0.78219 | K39: =SUM(K31:K38) -> 0.78219 | L39: =SUM(L31:L38) -> 0.94885667
B42: Topper | C42: 1 | D42: 1 | E42: 1 | F42: 1 | G42: 1 | H42: 1.8 | I42: =(C42*H42)/G42 -> 1.8 | J42: =(C42*H42)/G42 -> 1.8 | K42: =(E42*H42)/G42 -> 1.8 | L42: =(F42*H42)/G42 -> 1.8
B43: Vela | C43: 1 | D43: 1 | E43: 1 | F43: 1 | G43: 6 | H43: 1 | I43: =(C43*H43)/G43 -> 0.16666667 | J43: =(C43*H43)/G43 -> 0.16666667 | K43: =(E43*H43)/G43 -> 0.16666667 | L43: =(F43*H43)/G43 -> 0.16666667
B44: Plato 25 cm | C44: 1 | D44: 1 | E44: 1 | F44: 0 | G44: 1 | H44: 0.9 | I44: =(C44*H44)/G44 -> 0.9 | J44: =(C44*H44)/G44 -> 0.9 | K44: =(E44*H44)/G44 -> 0.9 | L44: =(F44*H44)/G44 -> 0
A45: EXTRAS | B45: Caja 25,5 | C45: 1 | D45: 1 | E45: 1 | F45: 0 | G45: 1 | H45: 2 | I45: =(C45*H45)/G45 -> 2 | J45: =(C45*H45)/G45 -> 2 | K45: =(E45*H45)/G45 -> 2 | L45: =(F45*H45)/G45 -> 0
B46: Etiqueta | C46: 1 | D46: 1 | E46: 1 | F46: 1 | G46: 500 | H46: 0.85 | I46: =(C46*H46)/G46 -> 0.0017 | J46: =(C46*H46)/G46 -> 0.0017 | K46: =(E46*H46)/G46 -> 0.0017 | L46: =(F46*H46)/G46 -> 0.0017
B47: Banda | C47: 2 | D47: 2 | E47: 2 | F47: 1 | G47: 2 | H47: 0.18 | I47: =(C47*H47)/G47 -> 0.18 | J47: =(C47*H47)/G47 -> 0.18 | K47: =(E47*H47)/G47 -> 0.18 | L47: =(F47*H47)/G47 -> 0.09
B48: plato 28 cm | C48: 0 | D48: 0 | E48: 0 | F48: 1 | G48: 1 | H48: 0.9 | I48: =(C48*H48)/G48 -> 0 | J48: =(C48*H48)/G48 -> 0 | K48: =(E48*H48)/G48 -> 0 | L48: =(F48*H48)/G48 -> 0.9
B49: caja 28 cm | C49: 0 | D49: 0 | E49: 0 | F49: 1 | G49: 1 | H49: 2 | I49: =(C49*H49)/G49 -> 0 | J49: =(C49*H49)/G49 -> 0 | K49: =(E49*H49)/G49 -> 0 | L49: =(F49*H49)/G49 -> 2
B50: Sprinkles | C50: 10 | D50: 10 | E50: 10 | F50: 12 | G50: 100 | H50: 6 | I50: =(C50*H50)/G50 -> 0.6 | J50: =(C50*H50)/G50 -> 0.6 | K50: =(E50*H50)/G50 -> 0.6 | L50: =(F50*H50)/G50 -> 0.72
B51: Decoraciones | C51: 3 | D51: 3 | E51: 3 | F51: 3 | G51: 10 | H51: 10 | I51: =(C51*H51)/G51 -> 3 | J51: =(C51*H51)/G51 -> 3 | K51: =(E51*H51)/G51 -> 3 | L51: =(F51*H51)/G51 -> 3
I52: =SUM(I42:I51) -> 8.6483667 | J52: =SUM(J42:J51) -> 8.6483667 | K52: =SUM(K42:K51) -> 8.6483667 | L52: =SUM(L42:L51) -> 8.6783667
I53: 8-10 PORCIONES | J53: 12-15 PORCIONES | K53: 20 PORCIONES
H54: COSTE PROD | I54: =SUM(I11+I16+I23+I29+I39+I52) -> 29.175345 | J54: =SUM(J11+J16+J23+J29+J39+J52) -> 33.074436 | K54: =SUM(K11+K16+K23+K29+K39+K52) -> 36.302657 | L54: =SUM(L11+L16+L23+L29+L39+L52) -> 43.199213
H55: PVP | I55: 40 | J55: 45 | K55: 50 | L55: 55
H56: GANACIA | I56: =I55-I54 -> 10.824655 | J56: =J55-J54 -> 11.925564 | K56: =K55-K54 -> 13.697343 | L56: =SUM(L55-L54) -> 11.800787

Sheet TEMATICA FONDANT REDONDA
C3: 16 cm | D3: 18 cm | E3: 20 cm | F3: 22-24 cm | I3: 16 cm | J3: 18 cm | K3: 20 cm | L3: 22-24 cm
B4: INGREDIENTES | C4: CANT 8-10 p | D4: CANT 10-15 p | E4: CANT 18-20 | F4: CANT 20-25 | G4: UNIDADES PAQ | H4: PRECIO | I4: CANT 8-10 p | J4: CANT 10-15 p | K4: CANT 18-20 | L4: CANT 20-25
B5: Harina | C5: 140 | D5: 180 | E5: 240 | F5: 270 | G5: 1000 | H5: 1.07 | I5: =(C5*H5)/G5 -> 0.1498 | J5: =(D5*H5)/G5 -> 0.1926 | K5: =(E5*H5)/G5 -> 0.2568 | L5: =(F5*H5)/G5 -> 0.2889
A6: BiZCOCHO | B6: Huevos | C6: 5 | D6: 6 | E6: 8 | F6: 9 | G6: 12 | H6: 2.5 | I6: =(C6*H6)/G6 -> 1.0416667 | J6: =(D6*H6)/G6 -> 1.25 | K6: =(E6*H6)/G6 -> 1.6666667 | L6: =(F6*H6)/G6 -> 1.875
A7: CHOCOLATE | B7: Azucar | C7: 150 | D7: 180 | E7: 240 | F7: 270 | G7: 1000 | H7: 1.49 | I7: =(C7*H7)/G7 -> 0.2235 | J7: =(D7*H7)/G7 -> 0.2682 | K7: =(E7*H7)/G7 -> 0.3576 | L7: =(F7*H7)/G7 -> 0.4023
B8: Vainilla | C8: 5 | D8: 10 | E8: 10 | F8: 15 | G8: 236 | H8: 6.9 | I8: =(C8*H8)/G8 -> 0.14618644 | J8: =(D8*H8)/G8 -> 0.29237288 | K8: =(E8*H8)/G8 -> 0.29237288 | L8: =(F8*H8)/G8 -> 0.43855932
B9: Cacao | C9: 30 | D9: 40 | E9: 50 | F9: 60 | G9: 250 | H9: 6 | I9: =(C9*H9)/G9 -> 0.72 | J9: =(D9*H9)/G9 -> 0.96 | K9: =(E9*H9)/G9 -> 1.2 | L9: =(F9*H9)/G9 -> 1.44
B10: Maicena | C10: 20 | D10: 30 | E10: 40 | F10: 40 | G10: 400 | H10: 2.99 | I10: =(C10*H10)/G10 -> 0.1495 | J10: =(D10*H10)/G10 -> 0.22425 | K10: =(E10*H10)/G10 -> 0.299 | L10: =(F10*H10)/G10 -> 0.299
I11: =SUM(I5:I10) -> 2.4306531 | J11: =SUM(J5:J10) -> 3.1874229 | K11: =SUM(K5:K10) -> 4.0724395 | L11: =SUM(L5:L10) -> 4.7437593
B13: Azucar | C13: 100 | D13: 150 | E13: 200 | F13: 250 | G13: 1000 | H13: 1.49 | I13: =(C13*H13)/G13 -> 0.149 | J13: =(D13*H13)/G13 -> 0.2235 | K13: =(E13*H13)/G13 -> 0.298 | L13: =(F13*H5)/G5 -> 0.2675
A14: ALMIBAR | B14: Agua | C14: 100 | D14: 150 | E14: 200 | F14: 250 | G14: 1000 | H14: 0.25 | I14: =(C14*H14)/G14 -> 0.025 | J14: =(D14*H14)/G14 -> 0.0375 | K14: =(E14*H14)/G14 -> 0.05 | L14: =(F14*H14)/G14 -> 0.0625
B15: Vainilla | C15: 3 | D15: 5 | E15: 9 | F15: 11 | G15: 236 | H15: 6.9 | I15: =(C15*H15)/G15 -> 0.087711864 | J15: =(D15*H15)/G15 -> 0.14618644 | K15: =(E15*H15)/G15 -> 0.26313559 | L15: =(F15*H15)/G15 -> 0.32161017
I16: =SUM(I13:I15) -> 0.26171186 | J16: =SUM(J13:J15) -> 0.40718644 | K16: =SUM(K13:K15) -> 0.61113559 | L16: =SUM(L13:L15) -> 0.65161017
B18: Nata | C18: 300 | D18: 400 | E18: 500 | F18: 600 | G18: 600 | H18: 2.36 | I18: =(C18*H18)/G18 -> 1.18 | J18: =(D18*H18)/G18 -> 1.5733333 | K18: =(E18*H18)/G18 -> 1.9666667 | L18: =(F18*H18)/G18 -> 2.36
A19: RELLENO | B19: Queso phila | C19: 100 | D19: 150 | E19: 200 | F19: 200 | G19: 250 | H19: 2 | I19: =(C19*H19)/G19 -> 0.8 | J19: =(D19*H19)/G19 -> 1.2 | K19: =(E19*H19)/G19 -> 1.6 | L19: =(F19*H19)/G19 -> 1.6
A20: kinder | B20: KINDER | C20: 108 | D20: 108 | E20: 108 | F20: 150 | G20: 108 | H20: 2.99 | I20: =(C20*H20)/G20 -> 2.99 | J20: =(D20*H20)/G20 -> 2.99 | K20: =(E20*H20)/G20 -> 2.99 | L20: =(F20*H20)/G20 -> 4.1527778
B21: Azucar blanca | C21: 80 | D21: 90 | E21: 100 | F21: 120 | G21: 1000 | H21: 1.49 | I21: =(C21*H21)/G21 -> 0.1192 | J21: =(D21*H21)/G21 -> 0.1341 | K21: =(E21*H21)/G21 -> 0.149 | L21: =(F21*H21)/G21 -> 0.1788
B22: Vainilla | C22: 5 | D22: 7 | E22: 9 | F22: 8 | G22: 236 | H22: 6.9 | I22: =(C22*H22)/G22 -> 0.14618644 | J22: =(D22*H22)/G22 -> 0.20466102 | K22: =(E22*H22)/G22 -> 0.26313559 | L22: =(F22*H22)/G22 -> 0.23389831
I23: =SUM(I18:I22) -> 5.2353864 | J23: =SUM(J18:J22) -> 6.1020943 | K23: =SUM(K18:K22) -> 6.9688023 | L23: =SUM(L18:L22) -> 8.5254761
A25: COBERTURA | B25: Nata | C25: 150 | D25: 200 | E25: 200 | F25: 450 | G25: 600 | H25: 2.36 | I25: =(C25*H25)/G25 -> 0.59 | J25: =(D25*H25)/G25 -> 0.78666667 | K25: =(E25*H25)/G25 -> 0.78666667 | L25: =(F25*H25)/G25 -> 1.77
A26: CREMA DE | B26: CHOCOLATE | C26: 500 | D26: 600 | E26: 600 | F26: 900 | G26: 100 | H26: 1.15 | I26: =(C26*H26)/G26 -> 5.75 | J26: =(D26*H26)/G26 -> 6.9 | K26: =(E26*H26)/G26 -> 6.9 | L26: =(F26*H26)/G26 -> 10.35
A27: GANACHE | B27: KINDER | C27: 0 | D27: 0 | E27: 0 | F27: 0 | G27: 100 | H27: 1.79 | I27: =(C27*H27)/G27 -> 0 | J27: =(D27*H27)/G27 -> 0 | K27: =(E27*H27)/G27 -> 0 | L27: =(F27*H27)/G27 -> 0
B28: Fondant | C28: 600 | D28: 800 | E28: 1000 | F28: 1200 | G28: 2000 | H28: 10.75 | I28: =(C28*H28)/G28 -> 3.225 | J28: =(D28*H28)/G28 -> 4.3 | K28: =(E28*H28)/G28 -> 5.375 | L28: =(F28*H28)/G28 -> 6.45
I29: =SUM(I25:I28) -> 9.565 | J29: =SUM(J25:J28) -> 11.986667 | K29: =SUM(K25:K28) -> 13.061667 | L29: =SUM(L25:L28) -> 18.57
B31: papel horno | C31: 1 | D31: 1 | E31: 1 | F31: 1 | G31: 20 | H31: 1.13 | I31: =(C31*H31)/G31 -> 0.0565 | J31: =(C31*H31)/G31 -> 0.0565 | K31: =(E31*H31)/G31 -> 0.0565 | L31: =(F31*H31)/G31 -> 0.0565
B32: Papel plata | C32: 1 | D32: 1 | E32: 1 | F32: 1 | G32: 1000 | H32: 2.05 | I32: =(C32*H32)/G32 -> 0.00205 | J32: =(C32*H32)/G32 -> 0.00205 | K32: =(E32*H32)/G32 -> 0.00205 | L32: =(F32*H32)/G32 -> 0.00205
B33: Horno | C33: 30 | D33: 35 | E33: 40 | F33: 40 | G33: 60 | H33: 1 | I33: =(C33*H33)/G33 -> 0.5 | J33: =(C33*H33)/G33 -> 0.5 | K33: =(E33*H33)/G33 -> 0.66666667 | L33: =(F33*H33)/G33 -> 0.66666667
A34: COSTES | B34: Agua | C34: 12 | D34: 12 | E34: 12 | F34: 12 | G34: 1000 | H34: 1.97 | I34: =(C34*H34)/G34 -> 0.02364 | J34: =(C34*H34)/G34 -> 0.02364 | K34: =(E34*H34)/G34 -> 0.02364 | L34: =(F34*H34)/G34 -> 0.02364
A35: INDIRECTOS | B35: Batidora | C35: 12 | D35: 12 | E35: 12 | F35: 12 | G35: 60 | H35: 1 | I35: =(C35*H35)/G35 -> 0.2 | J35: =(C35*H35)/G35 -> 0.2 | K35: =(E35*H35)/G35 -> 0.2 | L35: =(F35*H35)/G35 -> 0.2
I39: =SUM(I31:I38) -> 0.78219 | J39: =SUM(J31:J38) -> 0.78219 | K39: =SUM(K31:K38) -> 0.94885667 | L39: =SUM(L31:L38) -> 0.94885667
B42: Topper | C42: 1 | D42: 1 | E42: 1 | F42: 1 | G42: 1 | H42: 1.8 | I42: =(C42*H42)/G42 -> 1.8 | J42: =(C42*H42)/G42 -> 1.8 | K42: =(E42*H42)/G42 -> 1.8 | L42: =(F42*H42)/G42 -> 1.8
B43: Vela | C43: 1 | D43: 1 | E43: 1 | F43: 1 | G43: 6 | H43: 1 | I43: =(C43*H43)/G43 -> 0.16666667 | J43: =(C43*H43)/G43 -> 0.16666667 | K43: =(E43*H43)/G43 -> 0.16666667 | L43: =(F43*H43)/G43 -> 0.16666667
B44: Plato 25 cm | C44: 1 | D44: 1 | E44: 1 | F44: 0 | G44: 1 | H44: 0.9 | I44: =(C44*H44)/G44 -> 0.9 | J44: =(C44*H44)/G44 -> 0.9 | K44: =(E44*H44)/G44 -> 0.9 | L44: =(F44*H44)/G44 -> 0
A45: EXTRAS | B45: Caja 25,5 | C45: 1 | D45: 1 | E45: 1 | F45: 0 | G45: 1 | H45: 2 | I45: =(C45*H45)/G45 -> 2 | J45: =(C45*H45)/G45 -> 2 | K45: =(E45*H45)/G45 -> 2 | L45: =(F45*H45)/G45 -> 0
B46: Etiqueta | C46: 1 | D46: 1 | E46: 1 | F46: 1 | G46: 500 | H46: 0.85 | I46: =(C46*H46)/G46 -> 0.0017 | J46: =(C46*H46)/G46 -> 0.0017 | K46: =(E46*H46)/G46 -> 0.0017 | L46: =(F46*H46)/G46 -> 0.0017
B47: Banda | C47: 2 | D47: 2 | E47: 2 | F47: 1 | G47: 2 | H47: 0.18 | I47: =(C47*H47)/G47 -> 0.18 | J47: =(C47*H47)/G47 -> 0.18 | K47: =(E47*H47)/G47 -> 0.18 | L47: =(F47*H47)/G47 -> 0.09
B48: plato 28 cm | C48: 0 | D48: 0 | E48: 0 | F48: 1 | G48: 1 | H48: 0.9 | I48: =(C48*H48)/G48 -> 0 | J48: =(C48*H48)/G48 -> 0 | K48: =(E48*H48)/G48 -> 0 | L48: =(F48*H48)/G48 -> 0.9
B49: caja 28 cm | C49: 0 | D49: 0 | E49: 0 | F49: 1 | G49: 1 | H49: 2 | I49: =(C49*H49)/G49 -> 0 | J49: =(C49*H49)/G49 -> 0 | K49: =(E49*H49)/G49 -> 0 | L49: =(F49*H49)/G49 -> 2
B50: Sprinkles | C50: 10 | D50: 10 | E50: 10 | F50: 12 | G50: 100 | H50: 6 | I50: =(C50*H50)/G50 -> 0.6 | J50: =(C50*H50)/G50 -> 0.6 | K50: =(E50*H50)/G50 -> 0.6 | L50: =(F50*H50)/G50 -> 0.72
B51: Decoraciones | C51: 3 | D51: 3 | E51: 3 | F51: 3 | G51: 10 | H51: 10 | I51: =(C51*H51)/G51 -> 3 | J51: =(C51*H51)/G51 -> 3 | K51: =(E51*H51)/G51 -> 3 | L51: =(F51*H51)/G51 -> 3
I52: =SUM(I42:I51) -> 8.6483667 | J52: =SUM(J42:J51) -> 8.6483667 | K52: =SUM(K42:K51) -> 8.6483667 | L52: =SUM(L42:L51) -> 8.6783667
H55: COSTE TOTAL | I55: =SUM(I11+I16+I23+I29+I39+I52) -> 26.923308 | J55: =SUM(J11+J16+J23+J29+J39+J52) -> 31.113927 | K55: =SUM(K11+K16+K23+K29+K39+K52) -> 34.311267 | L55: =SUM(L11+L16+L23+L29+L39+L52) -> 42.118069
H56: VENTA | I56: 48 | J56: 55 | K56: 60 | L56: 70
H57: GANANCIA | I57: =(I56-I55) -> 21.076692 | J57: =(J56-J55) -> 23.886073 | K57: =(K56-K55) -> 25.688733 | L57: =(L56-L55) -> 27.881931

Sheet CARROT CAKE
C1: 16CM | D1: 18 CM | E1: 20 CM | F1: 22 CM | I1: 16CM | J1: 18CM | K1: 20CM | L1: 24CM
B2: INGREDIENTES | C2: 8-10 PORCIONES | D2: 12-15 PORCIONES | E2: 18-20 PORCIONES | F2: 25 PORCIONES | G2: UNIDADES PAQ | H2: PRECIO | I2: COSTO 8-10P | J2: COSTO 12-15P | K2: COSTO 18-20P | L2: COSTO 25P
B3: HARINA | C3: 130 | D3: 260 | E3: 260 | F3: 520 | G3: 1000 | H3: 2.19 | I3: =C3*H3/G3 -> 0.2847 | J3: =D3*H3/G3 -> 0.5694 | K3: =E3*H3/G3 -> 0.5694 | L3: =F3*H3/G3 -> 1.1388
B4: ALMENDRA MOLIDA | C4: 40 | D4: 80 | E4: 80 | F4: 160 | G4: 150 | H4: 4 | I4: =C4*H4/G4 -> 1.0666667 | J4: =D4*H4/G4 -> 2.1333333 | K4: =E4*H4/G4 -> 2.1333333 | L4: =F4*H4/G4 -> 4.2666667
B5: ROYAL | C5: 5 | D5: 10 | E5: 10 | F5: 15 | G5: 96 | H5: 2.69 | I5: =C5*H5/G5 -> 0.14010417 | J5: =D5*H5/G5 -> 0.28020833 | K5: =E5*H5/G5 -> 0.28020833 | L5: =F5*H5/G5 -> 0.4203125
B6: BICARBONATO | C6: 5 | D6: 8 | E6: 10 | F6: 15 | G6: 300 | H6: 1.1 | I6: =C6*H6/G6 -> 0.018333333 | J6: =D6*H6/G6 -> 0.029333333 | K6: =E6*H6/G6 -> 0.036666667 | L6: =F6*H6/G6 -> 0.055
B7: AZUCAR MORENA | C7: 80 | D7: 160 | E7: 160 | F7: 320 | G7: 500 | H7: 1.29 | I7: =C7*H7/G7 -> 0.2064 | J7: =D7*H7/G7 -> 0.4128 | K7: =E7*H7/G7 -> 0.4128 | L7: =F7*H7/G7 -> 0.8256
B8: AZUCAR BLANCA | C8: 80 | D8: 160 | E8: 160 | F8: 320 | G8: 1000 | H8: 1.49 | I8: =C8*H8/G8 -> 0.1192 | J8: =D8*H8/G8 -> 0.2384 | K8: =E8*H8/G8 -> 0.2384 | L8: =F8*H8/G8 -> 0.4768
B9: ACEITE GIR | C9: 90 | D9: 180 | E9: 180 | F9: 260 | G9: 1000 | H9: 1.56 | I9: =C9*H9/G9 -> 0.1404 | J9: =D9*H9/G9 -> 0.2808 | K9: =E9*H9/G9 -> 0.2808 | L9: =F9*H9/G9 -> 0.4056
B10: HUEVOS | C10: 2 | D10: 3 | E10: 3 | F10: 6 | G10: 12 | H10: 2.5 | I10: =C10*H10/G10 -> 0.41666667 | J10: =D10*H10/G10 -> 0.625 | K10: =E10*H10/G10 -> 0.625 | L10: =F10*H10/G10 -> 1.25
B11: LECHE | C11: 50 | D11: 100 | E11: 100 | F11: 200 | G11: 1000 | H11: 0.9 | I11: =C11*H11/G11 -> 0.045 | J11: =D11*H11/G11 -> 0.09 | K11: =E11*H11/G11 -> 0.09 | L11: =F11*H11/G11 -> 0.18
B12: ZANAHORIA | C12: 90 | D12: 180 | E12: 180 | F12: 260 | G12: 1000 | H12: 1.21 | I12: =C12*H12/G12 -> 0.1089 | J12: =D12*H12/G12 -> 0.2178 | K12: =E12*H12/G12 -> 0.2178 | L12: =F12*H12/G12 -> 0.3146
B13: VAINILLA | C13: 5 | D13: 5 | E13: 10 | F13: 20 | G13: 236 | H13: 6.9 | I13: =C13*H13/G13 -> 0.14618644 | J13: =D13*H13/G13 -> 0.14618644 | K13: =E13*H13/G13 -> 0.29237288 | L13: =F13*H13/G13 -> 0.58474576
B14: CANELA | C14: 2 | D14: 1 | E14: 1 | F14: 4 | G14: 45 | H14: 0.87 | I14: =C14*H14/G14 -> 0.038666667 | J14: =D14*H14/G14 -> 0.019333333 | K14: =E14*H14/G14 -> 0.019333333 | L14: =F14*H14/G14 -> 0.077333333
... B18: VINAGRE | C18: 5 | D18: 5 | E18: 5 | F18: 5 | G18: 1000 | H18: 0.9 | I18: =C18*H18/G18 -> 0.0045 | J18: =D18*H18/G18 -> 0.0045 | K18: =E18*H18/G18 -> 0.0045 | L18: =F18*H18/G18 -> 0.0045
I19: =SUM(I3:I18) -> 2.8087073 | J19: =SUM(J3:J18) -> 5.1380614 | K19: =SUM(K3:K18) -> 5.3465812 | L19: =SUM(L3:L18) -> 10.180542
B23: Nata | C23: 300 | D23: 350 | E23: 300 | F23: 400 | G23: 600 | H23: 2.19 | I23: =(C23*H23)/G23 -> 1.095 | J23: =D23*H23/G23 -> 1.2775 | K23: =(E23*H23)/G23 -> 1.095 | L23: =(F23*H23)/G23 -> 1.46
B24: Queso phila | C24: 100 | D24: 120 | E24: 200 | F24: 250 | G24: 250 | H24: 1.1 | I24: =(C24*H24)/G24 -> 0.44 | J24: =D24*H24/G24 -> 0.528 | K24: =(E24*H24)/G24 -> 0.88 | L24: =(F24*H24)/G24 -> 1.1
B25: Azucar glass | C25: 50 | D25: 60 | E25: 70 | F25: 90 | G25: 1000 | H25: 4.5 | I25: =(C25*H25)/G25 -> 0.225 | J25: =D25*H25/G25 -> 0.27 | K25: =(E25*H25)/G25 -> 0.315 | L25: =(F25*H25)/G25 -> 0.405
B26: Vainilla | C26: 5 | D26: 5 | E26: 7 | F26: 9 | G26: 236 | H26: 6.9 | I26: =(C26*H26)/G26 -> 0.14618644 | J26: =D26*H26/G26 -> 0.14618644 | K26: =(E26*H26)/G26 -> 0.20466102 | L26: =(F26*H26)/G26 -> 0.26313559
I27: =SUM(I23:I26) -> 1.9061864 | J27: =SUM(J23:J26) -> 2.2216864 | K27: =SUM(K23:K26) -> 2.494661 | L27: =SUM(L23:L26) -> 3.2281356
B30: Nata | C30: 300 | D30: 350 | E30: 300 | F30: 400 | G30: 600 | H30: 2.19 | I30: =(C30*H30)/G30 -> 1.095 | J30: =D30*H30/G30 -> 1.2775 | K30: =(E30*H30)/G30 -> 1.095 | L30: =(F30*H30)/G30 -> 1.46
B31: Queso phila | C31: 100 | D31: 120 | E31: 200 | F31: 250 | G31: 250 | H31: 1.1 | I31: =(C31*H31)/G31 -> 0.44 | J31: =D31*H31/G31 -> 0.528 | K31: =(E31*H31)/G31 -> 0.88 | L31: =(F31*H31)/G31 -> 1.1
B32: Azucar glass | C32: 50 | D32: 60 | E32: 70 | F32: 90 | G32: 1000 | H32: 4.5 | I32: =(C32*H32)/G32 -> 0.225 | J32: =D32*H32/G32 -> 0.27 | K32: =(E32*H32)/G32 -> 0.315 | L32: =(F32*H32)/G32 -> 0.405
B33: Vainilla | C33: 5 | D33: 5 | E33: 7 | F33: 9 | G33: 236 | H33: 6.9 | I33: =(C33*H33)/G33 -> 0.14618644 | J33: =D33*H33/G33 -> 0.14618644 | K33: =(E33*H33)/G33 -> 0.20466102 | L33: =(F33*H33)/G33 -> 0.26313559
I34: =SUM(I30:I33) -> 1.9061864 | J34: =SUM(J30:J33) -> 2.2216864 | K34: =SUM(K30:K33) -> 2.494661 | L34: =SUM(L30:L33) -> 3.2281356
B37: papel horno | C37: 1 | D37: 1 | E37: 1 | F37: 1 | G37: 20 | H37: 1.13 | I37: =C37*H37/G37 -> 0.0565 | J37: =D37*H37/G37 -> 0.0565 | K37: =E37*H37/G37 -> 0.0565 | L37: =F37*H37/G37 -> 0.0565
B38: Papel plata | C38: 1 | D38: 1 | E38: 1 | F38: 1 | G38: 1000 | H38: 2.05 | I38: =C38*H38/G38 -> 0.00205 | J38: =D38*H38/G38 -> 0.00205 | K38: =E38*H38/G38 -> 0.00205 | L38: =F38*H38/G38 -> 0.00205
B39: Horno | C39: 30 | D39: 35 | E39: 40 | F39: 45 | G39: 60 | H39: 1 | I39: =C39*H39/G39 -> 0.5 | J39: =D39*H39/G39 -> 0.58333333 | K39: =E39*H39/G39 -> 0.66666667 | L39: =F39*H39/G39 -> 0.75
B40: Agua | C40: 12 | D40: 12 | E40: 12 | F40: 12 | G40: 1000 | H40: 1.97 | I40: =C40*H40/G40 -> 0.02364 | J40: =D40*H40/G40 -> 0.02364 | K40: =E40*H40/G40 -> 0.02364 | L40: =F40*H40/G40 -> 0.02364
B41: Batidora | C41: 12 | D41: 12 | E41: 12 | F41: 12 | G41: 60 | H41: 1 | I41: =C41*H41/G41 -> 0.2 | J41: =D41*H41/G41 -> 0.2 | K41: =E41*H41/G41 -> 0.2 | L41: =F41*H41/G41 -> 0.2
I42: =SUM(I37:I41) -> 0.78219 | J42: =SUM(J37:J41) -> 0.86552333 | K42: =SUM(K37:K41) -> 0.94885667 | L42: =SUM(L37:L41) -> 1.03219
B45: Topper | C45: 1 | D45: 1 | E45: 1 | F45: 1 | G45: 1 | H45: 1.8 | I45: =(C45*H45)/G45 -> 1.8 | J45: =D45*H45/G45 -> 1.8 | K45: =(C45*H45)/G45 -> 1.8 | L45: =(F45*H45)/G45 -> 1.8
B46: Vela | C46: 1 | D46: 1 | E46: 1 | F46: 1 | G46: 6 | H46: 1 | I46: =(C46*H46)/G46 -> 0.16666667 | J46: =D46*H46/G46 -> 0.16666667 | K46: =(C46*H46)/G46 -> 0.16666667 | L46: =(F46*H46)/G46 -> 0.16666667
B47: Plato 25 cm | C47: 1 | D47: 1 | E47: 1 | F47: 1 | G47: 1 | H47: 0.9 | I47: =(C47*H47)/G47 -> 0.9 | J47: =D47*H47/G47 -> 0.9 | K47: =(C47*H47)/G47 -> 0.9 | L47: =(F47*H47)/G47 -> 0.9
B48: Caja 25,5 | C48: 1 | D48: 1 | E48: 1 | F48: 1 | G48: 1 | H48: 1.85 | I48: =(C48*H48)/G48 -> 1.85 | J48: =D48*H48/G48 -> 1.85 | K48: =(C48*H48)/G48 -> 1.85 | L48: =(F48*H48)/G48 -> 1.85
B49: Etiqueta | C49: 1 | D49: 1 | E49: 1 | F49: 1 | G49: 500 | H49: 0.85 | I49: =(C49*H49)/G49 -> 0.0017 | J49: =D49*H49/G49 -> 0.0017 | K49: =(C49*H49)/G49 -> 0.0017 | L49: =(F49*H49)/G49 -> 0.0017
B50: Banda | C50: 2 | D50: 2 | E50: 2 | F50: 2 | G50: 2 | H50: 0.18 | I50: =(C50*H50)/G50 -> 0.18 | J50: =D50*H50/G50 -> 0.18 | K50: =(C50*H50)/G50 -> 0.18 | L50: =(F50*H50)/G50 -> 0.18
B51: Sprinkles | C51: 10 | D51: 10 | E51: 10 | F51: 10 | G51: 100 | H51: 6 | I51: =(C51*H51)/G51 -> 0.6 | J51: =D51*H51/G51 -> 0.6 | K51: =(C51*H51)/G51 -> 0.6 | L51: =(F51*H51)/G51 -> 0.6
B52: Decoraciones | C52: 3 | D52: 3 | E52: 3 | F52: 3 | G52: 10 | H52: 1 | I52: =(C52*H52)/G52 -> 0.3 | J52: =D52*H52/G52 -> 0.3 | K52: =(C52*H52)/G52 -> 0.3 | L52: =(F52*H52)/G52 -> 0.3
I53: =SUM(I45:I52) -> 5.7983667 | J53: =SUM(J45:J52) -> 5.7983667 | K53: =SUM(K45:K52) -> 5.7983667 | L53: =SUM(L45:L52) -> 5.7983667
H55: COSTE PROD | I55: =SUM(I19+I27+I34+I42+I53) -> 13.201637 | J55: =SUM(J19+J27+J34+J42+J53) -> 16.245324 | K55: =SUM(K19+K27+K34+K42+K53) -> 17.083127 | L55: =SUM(L19+L27+L34+L42+L53) -> 23.467369
H56: PVP | I56: 25 | J56: 30 | K56: 40 | L56: 50
H57: GANANCIA | I57: =SUM(I56-I55) -> 11.798363 | J57: =SUM(J56-J55) -> 13.754676 | K57: =SUM(K56-K55) -> 22.916873 | L57: =SUM(L56-L55) -> 26.532631

Sheet CHAJA
B3: INGREDIENTES | C3: CANT 8-10 p | D3: CANT 12-15 | E3: CANT 18-20 p | F3: CANT 25-28 | G3: UNIDADES PAQ | H3: PRECIO | I3: COSTO 8-10 p | J3: COSTO 12-15 | K3: COSTO 18-20 p | L3: COSTO 25-28
A5: BIZCOCHO | B5: Harina | C5: 150 | D5: 180 | E5: 240 | F5: 270 | G5: 1000 | H5: 1.07 | I5: =(C5*H5)/G5 -> 0.1605 | J5: =D6*H6/G6 -> 1.25 | K5: =(E5*H5)/G5 -> 0.2568 | L5: =(F5*H5)/G5 -> 0.2889
A6: VAINILLA | B6: Huevos | C6: 5 | D6: 6 | E6: 8 | F6: 9 | G6: 12 | H6: 2.5 | I6: =(C6*H6)/G6 -> 1.0416667 | J6: =D7*H7/G7 -> 0.2682 | K6: =(E6*H6)/G6 -> 1.6666667 | L6: =(F6*H6)/G6 -> 1.875
B7: Azucar | C7: 150 | D7: 180 | E7: 240 | F7: 270 | G7: 1000 | H7: 1.49 | I7: =(C7*H7)/G7 -> 0.2235 | J7: =D8*H8/G8 -> 0.29237288 | K7: =(E7*H7)/G7 -> 0.3576 | L7: =(F7*H7)/G7 -> 0.4023
B8: Vainilla | C8: 5 | D8: 10 | E8: 10 | F8: 15 | G8: 236 | H8: 6.9 | I8: =(C8*H8)/G8 -> 0.14618644 | J8: =D8*H8/G8 -> 0.29237288 | K8: =(E8*H8)/G8 -> 0.29237288 | L8: =(F8*H8)/G8 -> 0.43855932
I9: =SUM(I5:I8) -> 1.5718531 | J9: =SUM(J5:J8) -> 2.1029458 | K9: =SUM(K5:K8) -> 2.5734395 | L9: =SUM(L5:L8) -> 3.0047593
B11: Azucar | C11: 100 | D11: 120 | E11: 150 | F11: 200 | G11: 1000 | H11: 1.49 | I11: =(C11*H11)/G11 -> 0.149 | J11: =D11*H11/G11 -> 0.1788 | K11: =(E11*H11)/G11 -> 0.2235 | L11: =(F11*H11)/G11 -> 0.298
A12: ALMIBAR | B12: Agua | C12: 100 | D12: 120 | E12: 150 | F12: 200 | G12: 1000 | H12: 0.25 | I12: =(C12*H12)/G12 -> 0.025 | J12: =D12*H12/G12 -> 0.03 | K12: =(E12*H12)/G12 -> 0.0375 | L12: =(F12*H12)/G12 -> 0.05
B13: Vainilla | C13: 3 | D13: 4 | E13: 5 | F13: 9 | G13: 236 | H13: 6.9 | I13: =(C13*H13)/G13 -> 0.087711864 | J13: =D13*H13/G13 -> 0.11694915 | K13: =(E13*H13)/G13 -> 0.14618644 | L13: =(F13*H13)/G13 -> 0.26313559
I14: =SUM(I11:I13) -> 0.26171186 | J14: =SUM(J11:J13) -> 0.32574915 | K14: =SUM(K11:K13) -> 0.40718644 | L14: =SUM(L11:L13) -> 0.61113559
A16: RELLENO | B16: Dulce de leche | C16: 400 | D16: 450 | E16: 500 | F16: 600 | G16: 1000 | H16: 4 | I16: =(C16*H16)/G16 -> 1.6 | J16: =D16*H16/G16 -> 1.8 | K16: =(E16*H16)/G16 -> 2 | L16: =(F16*H16)/G16 -> 2.4
A17: D.D.L Y | B17: Nata | C17: 300 | D17: 300 | E17: 400 | F17: 500 | G17: 600 | H17: 2.36 | I17: =(C17*H17)/G17 -> 1.18 | J17: =D17*H17/G17 -> 1.18 | K17: =(E17*H17)/G17 -> 1.5733333 | L17: =(F17*H17)/G17 -> 1.9666667
A18: NATA + melocoton | B18: Azucar | C18: 80 | D18: 80 | E18: 90 | F18: 100 | G18: 1000 | H18: 1.49 | I18: =(C18*H18)/G18 -> 0.1192 | J18: =D18*H18/G18 -> 0.1192 | K18: =(E18*H18)/G18 -> 0.1341 | L18: =(F18*H18)/G18 -> 0.149
B19: Vainilla | C19: 5 | D19: 5 | E19: 7 | F19: 9 | G19: 236 | H19: 6.9 | I19: =(C19*H19)/G19 -> 0.14618644 | J19: =D19*H19/G19 -> 0.14618644 | K19: =(E19*H19)/G19 -> 0.20466102 | L19: =(F19*H19)/G19 -> 0.26313559
B20: Melocoton | C20: 100 | D20: 120 | E20: 150 | F20: 200 | G20: 1000 | H20: 4.69 | I20: =(C20*H20)/G20 -> 0.469 | J20: =D20*H20/G20 -> 0.5628 | K20: =(E20*H20)/G20 -> 0.7035 | L20: =(F20*H20)/G20 -> 0.938
I21: =SUM(I16:I20) -> 3.5143864 | J21: =SUM(J16:J20) -> 3.8081864 | K21: =SUM(K16:K20) -> 4.6155944 | L21: =SUM(L16:L20) -> 5.7168023
A23: COBERTURA | B23: Nata | C23: 300 | D23: 350 | E23: 300 | F23: 400 | G23: 600 | H23: 2.36 | I23: =(C23*H23)/G23 -> 1.18 | J23: =D23*H23/G23 -> 1.3766667 | K23: =(E23*H23)/G23 -> 1.18 | L23: =(F23*H23)/G23 -> 1.5733333
A24: CREMA DE | B24: Queso phila | C24: 100 | D24: 120 | E24: 200 | F24: 250 | G24: 250 | H24: 2.5 | I24: =(C24*H24)/G24 -> 1 | J24: =D24*H24/G24 -> 1.2 | K24: =(E24*H24)/G24 -> 2 | L24: =(F24*H24)/G24 -> 2.5
A25: QUESO | B25: Azucar glass | C25: 50 | D25: 60 | E25: 70 | F25: 90 | G25: 1000 | H25: 5 | I25: =(C25*H25)/G25 -> 0.25 | J25: =D25*H25/G25 -> 0.3 | K25: =(E25*H25)/G25 -> 0.35 | L25: =(F25*H25)/G25 -> 0.45
B26: Vainilla | C26: 5 | D26: 5 | E26: 7 | F26: 9 | G26: 236 | H26: 6.9 | I26: =(C26*H26)/G26 -> 0.14618644 | J26: =D26*H26/G26 -> 0.14618644 | K26: =(E26*H26)/G26 -> 0.20466102 | L26: =(F26*H26)/G26 -> 0.26313559
I27: =SUM(I23:I26) -> 2.5761864 | J27: =SUM(J23:J26) -> 3.0228531 | K27: =SUM(K23:K26) -> 3.734661 | L27: =SUM(L23:L26) -> 4.7864689
B29: papel horno | C29: 1 | D29: 1 | E29: 1 | F29: 1 | G29: 20 | H29: 1.13 | I29: =(C29*H29)/G29 -> 0.0565 | J29: =D29*H29/G29 -> 0.0565 | K29: =(C29*H29)/G29 -> 0.0565 | L29: =(F29*H29)/G29 -> 0.0565
B30: Papel plata | C30: 1 | D30: 1 | E30: 1 | F30: 1 | G30: 1000 | H30: 2.05 | I30: =(C30*H30)/G30 -> 0.00205 | J30: =D30*H30/G30 -> 0.00205 | K30: =(C30*H30)/G30 -> 0.00205 | L30: =(F30*H30)/G30 -> 0.00205
B31: Horno | C31: 30 | D31: 30 | E31: 35 | F31: 40 | G31: 60 | H31: 1 | I31: =(C31*H31)/G31 -> 0.5 | J31: =D31*H31/G31 -> 0.5 | K31: =(C31*H31)/G31 -> 0.5 | L31: =(F31*H31)/G31 -> 0.66666667
A32: COSTES | B32: Agua | C32: 12 | D32: 12 | E32: 12 | F32: 12 | G32: 1000 | H32: 1.97 | I32: =(C32*H32)/G32 -> 0.02364 | J32: =D32*H32/G32 -> 0.02364 | K32: =(C32*H32)/G32 -> 0.02364 | L32: =(F32*H32)/G32 -> 0.02364
A33: INDIRECTOS | B33: Batidora | C33: 12 | D33: 12 | E33: 12 | F33: 12 | G33: 60 | H33: 1 | I33: =(C33*H33)/G33 -> 0.2 | J33: =D33*H33/G33 -> 0.2 | K33: =(C33*H33)/G33 -> 0.2 | L33: =(F33*H33)/G33 -> 0.2
B34: CLARAS | C34: 2 | D34: 2 | E34: 2 | F34: 22 | G34: 12 | H34: 2.5 | I34: =(C34*H34)/G34 -> 0.41666667 | J34: =D34*H34/G34 -> 0.41666667 | K34: =(C34*H34)/G34 -> 0.41666667 | L34: =(F34*H34)/G34 -> 4.5833333
I37: =SUM(I29:I36) -> 1.1988567 | J37: =SUM(J29:J36) -> 1.1988567 | K37: =SUM(K29:K36) -> 1.1988567 | L37: =SUM(L29:L36) -> 5.53219
B40: Topper | C40: 1 | D40: 1 | E40: 1 | F40: 1 | G40: 1 | H40: 1.8 | I40: =(C40*H40)/G40 -> 1.8 | J40: =D40*H40/G40 -> 1.8 | K40: =(C40*H40)/G40 -> 1.8 | L40: =(F40*H40)/G40 -> 1.8
B41: Vela | C41: 1 | D41: 1 | E41: 1 | F41: 1 | G41: 6 | H41: 1 | I41: =(C41*H41)/G41 -> 0.16666667 | J41: =D41*H41/G41 -> 0.16666667 | K41: =(C41*H41)/G41 -> 0.16666667 | L41: =(F41*H41)/G41 -> 0.16666667
B42: Plato 25 cm | C42: 1 | D42: 1 | E42: 1 | F42: 1 | G42: 1 | H42: 0.9 | I42: =(C42*H42)/G42 -> 0.9 | J42: =D42*H42/G42 -> 0.9 | K42: =(C42*H42)/G42 -> 0.9 | L42: =(F42*H42)/G42 -> 0.9
A43: EXTRAS | B43: Caja 25,5 | C43: 1 | D43: 1 | E43: 1 | F43: 1 | G43: 1 | H43: 2 | I43: =(C43*H43)/G43 -> 2 | J43: =D43*H43/G43 -> 2 | K43: =(C43*H43)/G43 -> 2 | L43: =(F43*H43)/G43 -> 2
B44: Etiqueta | C44: 1 | D44: 1 | E44: 1 | F44: 1 | G44: 500 | H44: 0.85 | I44: =(C44*H44)/G44 -> 0.0017 | J44: =D44*H44/G44 -> 0.0017 | K44: =(C44*H44)/G44 -> 0.0017 | L44: =(F44*H44)/G44 -> 0.0017
B45: Banda | C45: 2 | D45: 2 | E45: 2 | F45: 2 | G45: 2 | H45: 0.18 | I45: =(C45*H45)/G45 -> 0.18 | J45: =D45*H45/G45 -> 0.18 | K45: =(C45*H45)/G45 -> 0.18 | L45: =(F45*H45)/G45 -> 0.18
B46: Sprinkles | C46: 10 | D46: 10 | E46: 10 | F46: 10 | G46: 100 | H46: 6 | I46: =(C46*H46)/G46 -> 0.6 | J46: =D46*H46/G46 -> 0.6 | K46: =(C46*H46)/G46 -> 0.6 | L46: =(F46*H46)/G46 -> 0.6
B47: Decoraciones | C47: 3 | D47: 3 | E47: 3 | F47: 3 | G47: 10 | H47: 1 | I47: =(C47*H47)/G47 -> 0.3 | J47: =D47*H47/G47 -> 0.3 | K47: =(C47*H47)/G47 -> 0.3 | L47: =(F47*H47)/G47 -> 0.3
I48: =SUM(I40:I47) -> 5.9483667 | J48: =SUM(J40:J47) -> 5.9483667 | K48: =SUM(K40:K47) -> 5.9483667 | L48: =SUM(L40:L47) -> 5.9483667
H50: COSTE PROD | I50: =SUM(I9+I14+I21+I27+I37+I48) -> 15.071361 | J50: =SUM(J9+J14+J21+J27+J37+J48) -> 16.406958 | K50: =SUM(K9+K14+K21+K27+K37+K48) -> 18.478105 | L50: =SUM(L9+L14+L21+L27+L37+L48) -> 25.599723
H51: PVP | I51: 30 | J51: 35 | K51: 40 | L51: 45
H52: GANANCIA | I52: =I51-I50 -> 14.928639 | J52: =J51-J50 -> 18.593042 | K52: =K51-K50 -> 21.521895 | L52: =L51-L50 -> 19.400277

Sheet CUPCAKES RED VELVET
A2: RED VELVET MAT PRIMA MASA
B3: INGREDIENTES | C3: CANT X 24 | D3: CANT X 12 | E3: PRECIO | F3: CANT PAQUETE | G3: COSTE 24 | H3: COSTE 12
B4: LECHE | C4: 100 | D4: 50 | E4: 1 | F4: 1000 | G4: =(C4*E4/F4) -> 0.1 | H4: =SUM(D4*E4/F4) -> 0.05
B5: HARINA REPOSTERA | C5: 240 | D5: 120 | E5: 1.09 | F5: 1000 | G5: =(C5*E5/F5) -> 0.2616 | H5: =SUM(D5*E5/F5) -> 0.1308
B6: SAL | C6: 5 | D6: 3 | E6: 0.4 | F6: 1000 | G6: =(C6*E6/F6) -> 0.002 | H6: =SUM(D6*E6/F6) -> 0.0012
B7: BICARBONATO | C7: 5 | D7: 3 | E7: 0.6 | F7: 1000 | G7: =(C7*E7/F7) -> 0.003 | H7: =SUM(D7*E7/F7) -> 0.0018
B8: VINAGRE | C8: 5 | D8: 3 | E8: 0.9 | F8: 1000 | G8: =(C8*E8/F8) -> 0.0045 | H8: =SUM(D8*E8/F8) -> 0.0027
A9: BIZCOCHO | B9: ROYAL | C9: 10 | D9: 5 | E9: 28.02 | F9: 1000 | G9: =(C9*E9/F9) -> 0.2802 | H9: =SUM(D9*E9/F9) -> 0.1401
A10: RED VELVET | B10: CACAO | C10: 30 | D10: 15 | E10: 5 | F10: 250 | G10: =(C10*E10/F10) -> 0.6 | H10: =SUM(D10*E10/F10) -> 0.3
B11: HUEVOS | C11: 3 | D11: 2 | E11: 3 | F11: 12 | G11: =(C11*E11/F11) -> 0.75 | H11: =SUM(D11*E11/F11) -> 0.5
B12: AZUCAR BLANCA | C12: 250 | D12: 125 | E12: 1.45 | F12: 1000 | G12: =(C12*E12/F12) -> 0.3625 | H12: =SUM(D12*E12/F12) -> 0.18125
B13: ACEITE GIRASOL | C13: 240 | D13: 125 | E13: 1.8 | F13: 1000 | G13: =(C13*E13/F13) -> 0.432 | H13: =SUM(D13*E13/F13) -> 0.225
B14: VAINILLA | C14: 10 | D14: 5 | E14: 6.9 | F14: 236 | G14: =(C14*E14/F14) -> 0.29237288 | H14: =SUM(D14*E14/F14) -> 0.14618644
B15: COLORANTE ROJO | C15: 10 | D15: 10 | E15: 2.4 | F15: 25 | G15: =(C15*E15/F15) -> 0.96 | H15: =SUM(D15*E15/F15) -> 0.96
B16: LIMON | C16: 1 | D16: 1 | E16: 1 | F16: 1 | G16: =(C16*E16/F16) -> 1 | H16: =SUM(D16*E16/F16) -> 1
G17: =SUM(G4:G16) -> 5.0481729 | H17: =SUM(H4:H16) -> 3.6390364
A18: FROSTING DE QUESO CREMA
B19: QUESO CREMA | C19: 200 | D19: 100 | E19: 1.25 | F19: 250 | G19: =(C19*E19/F19) -> 1 | H19: =SUM(D19*E19/F19) -> 0.5
B20: NATA | C20: 300 | D20: 150 | E20: 2.39 | F20: 600 | G20: =(C20*E20/F20) -> 1.195 | H20: =SUM(D20*E20/F20) -> 0.5975
B21: VAINILLA | C21: 10 | D21: 5 | E21: 6.9 | F21: 236 | G21: =(C21*E21/F21) -> 0.29237288 | H21: =SUM(D21*E21/F21) -> 0.14618644
B22: AZUCAR | C22: 80 | D22: 40 | E22: 1.49 | F22: 1000 | G22: =(C22*E22/F22) -> 0.1192 | H22: =SUM(D22*E22/F22) -> 0.0596
B23: CACAO | C23: 30 | D23: 15 | E23: 5 | F23: 250 | G23: =(C23*E23/F23) -> 0.6 | H23: =SUM(D23*E23/F23) -> 0.3
G24: =SUM(G19:G23) -> 3.2065729 | H24: =SUM(H19:H23) -> 1.6032864
A25: FROSTING GANACHE BLANCO
B26: NATA | C26: 200 | D26: 100 | E26: 2.39 | F26: 600 | G26: =(C26*E26/F26) -> 0.79666667 | H26: =SUM(D26*E26/F26) -> 0.39833333
B27: CHOCOLATE BLANCO | C27: 300 | D27: 150 | E27: 1.15 | F27: 100 | G27: =(C27*E27/F27) -> 3.45 | H27: =SUM(D27*E27/F27) -> 1.725
B28: COLORANTES | C28: 10 | D28: 5 | E28: 2.34 | F28: 25 | G28: =(C28*E28/F28) -> 0.936 | H28: =SUM(D28*E28/F28) -> 0.468
G29: =SUM(G26:G27) -> 4.2466667 | H29: =SUM(H26:H27) -> 2.1233333
A31: EXTRAS | B31: DECORACIONES | C31: 1 | D31: 1 | E31: 5 | F31: 1 | G31: =(C31*E31/F31) -> 5 | H31: =SUM(D31*E31/(F31)) -> 5
B32: PIROTINES | C32: 24 | D32: 12 | E32: 7 | F32: 300 | G32: =(C32*E32/F32) -> 0.56 | H32: =SUM(D32*E32/(F32)) -> 0.28
B33: CAJA 12 | C33: 2 | D33: 1 | E33: 19 | F33: 16 | G33: =(C33*E33/F33) -> 2.375 | H33: =SUM(D33*E33/(F33)) -> 1.1875
B34: ETIQUETAS | C34: 3 | D34: 2 | E34: 2.5 | F34: 100 | G34: =(C34*E34/F34) -> 0.075 | H34: =SUM(D34*E34/(F34)) -> 0.05
B35: VARIOS PACK | C35: 1 | D35: 1 | E35: 1 | F35: 1 | G35: =(C35*E35/F35) -> 1 | H35: =SUM(D35*E35/(F35)) -> 1
G36: =SUM(G31:G35) -> 9.01 | H36: =SUM(H31:H35) -> 7.5175
C39: COSTE 24 CREMA DE QUESO | D39: =SUM(G17+G24+G36) -> 17.264746
C40: COSTE 12 CREMA DE QUESO | D40: =SUM(H17+H24+H36) -> 12.759823
C41: COSTE 12 GANACHE | D41: =SUM(H17+H29+H36) -> 13.27987
C42: COSTE 24 GANACHE | D42: =SUM(G17+G29+G36) -> 18.30484

Sheet CUPCAKES CHOCOLATE
A2: CHOCOLATE MASA
B3: INGREDIENTES | C3: CANT X 24 | D3: CANT X 12 | E3: PRECIO | F3: CANT PAQUETE | G3: COSTE 24 | H3: COSTE 12
B4: MANTECA | C4: 100 | E4: 2.39 | F4: 250 | G4: =(C4*E4/F4) -> 0.956 | H4: =SUM(D4*E4/F4) -> 0
B5: AZUCAR BLANCA | C5: 100 | E5: 1.49 | F5: 1000 | G5: =(C5*E5/F5) -> 0.149 | H5: =SUM(D5*E5/F5) -> 0
B6: AZUCAR MORENA | C6: 60 | E6: 1.99 | F6: 1000 | G6: =(C6*E6/F6) -> 0.1194 | H6: =SUM(D6*E6/F6) -> 0
B7: HUEVOS | C7: 2 | E7: 5.75 | F7: 24 | G7: =(C7*E7/F7) -> 0.47916667 | H7: =SUM(D7*E7/F7) -> 0
B8: LECHE ENTERA | C8: 140 | E8: 0.97 | F8: 1000 | G8: =(C8*E8/F8) -> 0.1358 | H8: =SUM(D8*E8/F8) -> 0
A9: MASA | B9: CACAO | C9: 40 | E9: 6.75 | F9: 250 | G9: =(C9*E9/F9) -> 1.08 | H9: =SUM(D9*E9/F9) -> 0
A10: CHOCOLATE | B10: HARINA | C10: 140 | E10: 1.09 | F10: 1000 | G10: =(C10*E10/F10) -> 0.1526 | H10: =SUM(D10*E10/F10) -> 0
B11: ROYAL | C11: 3 | E11: 0.9 | F11: 90 | G11: =(C11*E11/F11) -> 0.03 | H11: =SUM(D11*E11/F11) -> 0
B12: VAINILLA | C12: 3 | E12: 6.9 | F12: 236 | G12: =(C12*E12/F12) -> 0.087711864 | H12: =SUM(D12*E12/F12) -> 0
B13: SAL | C13: 2 | E13: 0.4 | F13: 1000 | G13: =(C13*E13/F13) -> 0.0008 | H13: =SUM(D13*E13/F13) -> 0
G17: =SUM(G4:G16) -> 3.1904785 | H17: =SUM(H4:H16) -> 0
A18: FROSTING DE QUESO CREMA
B19: QUESO CREMA | C19: 200 | D19: 100 | E19: 1.25 | F19: 250 | G19: =(C19*E19/F19) -> 1 | H19: =SUM(D19*E19/F19) -> 0.5
B20: NATA | C20: 300 | D20: 150 | E20: 2.39 | F20: 600 | G20: =(C20*E20/F20) -> 1.195 | H20: =SUM(D20*E20/F20) -> 0.5975
B21: VAINILLA | C21: 10 | D21: 5 | E21: 6.9 | F21: 236 | G21: =(C21*E21/F21) -> 0.29237288 | H21: =SUM(D21*E21/F21) -> 0.14618644
B22: AZUCAR | C22: 80 | D22: 40 | E22: 1.49 | F22: 1000 | G22: =(C22*E22/F22) -> 0.1192 | H22: =SUM(D22*E22/F22) -> 0.0596
B23: CACAO | C23: 30 | D23: 15 | E23: 5 | F23: 250 | G23: =(C23*E23/F23) -> 0.6 | H23: =SUM(D23*E23/F23) -> 0.3
G24: =SUM(G19:G23) -> 3.2065729 | H24: =SUM(H19:H23) -> 1.6032864
A25: FROSTING GANACHE BLANCO
B26: NATA | C26: 200 | D26: 100 | E26: 2.39 | F26: 600 | G26: =(C26*E26/F26) -> 0.79666667 | H26: =SUM(D26*E26/F26) -> 0.39833333
B27: CHOCOLATE BLANCO | C27: 300 | D27: 150 | E27: 1.15 | F27: 100 | G27: =(C27*E27/F27) -> 3.45 | H27: =SUM(D27*E27/F27) -> 1.725
B28: COLORANTES | C28: 10 | D28: 5 | E28: 2.34 | F28: 25 | G28: =(C28*E28/F28) -> 0.936 | H28: =SUM(D28*E28/F28) -> 0.468
G29: =SUM(G26:G27) -> 4.2466667 | H29: =SUM(H26:H27) -> 2.1233333
A31: EXTRAS | B31: DECORACIONES | C31: 1 | D31: 1 | E31: 5 | F31: 1 | G31: =(C31*E31/F31) -> 5 | H31: =SUM(D31*E31/(F31)) -> 5
B32: PIROTINES | C32: 24 | D32: 12 | E32: 7 | F32: 300 | G32: =(C32*E32/F32) -> 0.56 | H32: =SUM(D32*E32/(F32)) -> 0.28
B33: CAJA 12 | C33: 2 | D33: 1 | E33: 19 | F33: 16 | G33: =(C33*E33/F33) -> 2.375 | H33: =SUM(D33*E33/(F33)) -> 1.1875
B34: ETIQUETAS | C34: 3 | D34: 2 | E34: 2.5 | F34: 100 | G34: =(C34*E34/F34) -> 0.075 | H34: =SUM(D34*E34/(F34)) -> 0.05
B35: VARIOS PACK | C35: 1 | D35: 1 | E35: 1 | F35: 1 | G35: =(C35*E35/F35) -> 1 | H35: =SUM(D35*E35/(F35)) -> 1
G36: =SUM(G31:G35) -> 9.01 | H36: =SUM(H31:H35) -> 7.5175
C39: COSTE 24 CREMA DE QUESO | D39: =SUM(G17+G24+G36) -> 15.407051
C40: COSTE 12 CREMA DE QUESO | D40: =SUM(H17+H24+H36) -> 9.1207864
C41: COSTE 12 GANACHE | D41: =SUM(H17+H29+H36) -> 9.6408333
C42: COSTE 24 GANACHE | D42: =SUM(G17+G29+G36) -> 16.447145

Sheet LEMON PIE
B1: LEMON PIE
A3: MASA SABLEE
A4: INGREDIENTES | B4: CANTIDAD 22 | C4: CANTIDAD 20 | D4: UNIDADES | E4: PRECIO | F4: COSTO 22 | G4: COSTO 20 | I4: DE ESTA RECETA SALE UNA TARTA DE 22 CM
A6: Mantequilla | B6: 100 | C6: 100 | D6: 1000 | E6: 2.56 | F6: =B6*E6/D6 -> 0.256 | G6: =C6*E6/D6 -> 0.256 | I6: PARA 20 CM HACER MEDIA DE LEMON CURD
A7: Azucar glass | B7: 80 | C7: 80 | D7: 1000 | E7: 5 | F7: =B7*E7/D7 -> 0.4 | G7: =C7*E7/D7 -> 0.4
A8: Huevos | B8: 1 | C8: 1 | D8: 12 | E8: 2.5 | F8: =B8*E8/D8 -> 0.20833333 | G8: =C8*E8/D8 -> 0.20833333 | K8: PVP
A9: Harina | B9: 180 | C9: 180 | D9: 1000 | E9: 1.46 | F9: =B9*E9/D9 -> 0.2628 | G9: =C9*E9/D9 -> 0.2628 | I9: COSTE 20 CM | J9: =SUM(G13+G25+F36+G45+G55) -> 8.7700185 | K9: 20
A10: Vainilla | B10: 5 | C10: 5 | D10: 200 | E10: 6.9 | F10: =B10*E10/D10 -> 0.1725 | G10: =C10*E10/D10 -> 0.1725 | I10: COSTE 22 CM | J10: =SUM(F13+F25+F36+F45+F55) -> 8.2423852 | K10: 22
A11: Citricos | B11: 100 | C11: 100 | D11: 1000 | E11: 2.6 | F11: =B11*E11/D11 -> 0.26 | G11: =C11*E11/D11 -> 0.26
A12: Cacao | B12: 0 | C12: 0 | D12: 450 | E12: 4.99 | F12: =B12*E12/D12 -> 0 | G12: =C12*E12/D12 -> 0
F13: =SUM(F6:F12) -> 1.5596333 | G13: =SUM(G6:G12) -> 1.5596333
A15: LEMON CURD
A16: INGREDIENTES | B16: CANTIDAD | D16: UNIDADES | E16: PRECIO | F16: COSTO 22 CM | G16: COSTO 20
A18: Yemas | B18: 4 | C18: 2 | D18: 12 | E18: 2.56 | F18: =B18*E18/D18 -> 0.85333333 | G18: =C18*E18/D18 -> 0.42666667
A19: Leche | B19: 500 | C19: 250 | D19: 1000 | E19: 1 | F19: =B19*E19/D19 -> 0.5 | G19: =C19*E19/D19 -> 0.25
A20: Azucar | B20: 120 | C20: 60 | D20: 1000 | E20: 1.49 | F20: =B20*E20/D20 -> 0.1788 | G20: =C20*E20/D20 -> 0.0894
A21: Maicena | B21: 50 | C21: 35 | D21: 1000 | E21: 3 | F21: =B21*E21/D21 -> 0.15 | G21: =C21*E21/D21 -> 0.105
A22: zumo limon | B22: 100 | C22: 70 | D22: 100 | E22: 2 | F22: =B22*E22/D22 -> 2 | G22: =C22*E22/D22 -> 1.4
A23: manteca | B23: 50 | C23: 30 | D23: 250 | E23: 2.56 | F23: =B23*E23/D23 -> 0.512 | G23: =C23*E23/D23 -> 0.3072
A24: vainilla | B24: 3 | C24: 3 | D24: 236 | E24: 6.9 | F24: =B24*E24/D24 -> 0.087711864 | G24: =C24*E24/D24 -> 0.087711864
F25: =SUM(F18:F24) -> 4.2818452 | G25: =SUM(G18:G24) -> 2.6659785
A27: MERENGUE
A28: INGREDIENTES | B28: CANTIDAD | D28: UNIDADES | E28: PRECIO | F28: COSTO
A29: CLARAS | B29: 3 | D29: 12 | E29: 2.56 | F29: =B29*E29/D29 -> 0.64
A30: AZUCAR | B30: 240 | D30: 1000 | E30: 1.49 | F30: =B30*E30/D30 -> 0.3576
A31: AGUA | B31: 60 | D31: 1000 | E31: 1 | F31: =B31*E31/D31 -> 0.06
B32: 0 | D32: 1000 | E32: 3 | F32: =B32*E32/D32 -> 0
B33: 0 | D33: 100 | E33: 2 | F33: =B33*E33/D33 -> 0
B34: 0 | D34: 250 | E34: 2.56 | F34: =B34*E34/D34 -> 0
B35: 0 | D35: 236 | E35: 6.9 | F35: =B35*E35/D35 -> 0
F36: =SUM(F29:F35) -> 1.0576
A37: GASTOS INDIRECTOS
A38: INGREDIENTES | B38: CANTIDAD | D38: UNIDADES | E38: PRECIO | F38: COSTO | G38: COSTO 20
A39: Papel horno | B39: 1 | C39: 1 | D39: 20 | E39: 1.13 | F39: =B39*E39/D39 -> 0.0565 | G39: =C39*E39/D39 -> 0.0565
A40: Gastos herram | B40: 1 | C40: 1 | D40: 100 | E40: 10 | F40: =B40*E40/D40 -> 0.1 | G40: =C40*E40/D40 -> 0.1
A41: Horno | B41: 30 | C41: 30 | D41: 60 | E41: 1 | F41: =B41*E41/D41 -> 0.5 | G41: =C41*E41/D41 -> 0.5
A42: Agua | B42: 12 | C42: 12 | D42: 1000 | E42: 1.97 | F42: =B42*E42/D42 -> 0.02364 | G42: =C42*E42/D42 -> 0.02364
A43: Batidora | B43: 15 | C43: 15 | D43: 60 | E43: 1 | F43: =B43*E43/D43 -> 0.25 | G43: =C43*E43/D43 -> 0.25
A44: MANGAS | B44: 2 | C44: 2 | D44: 20 | E44: 3 | F44: =B44*E44/D44 -> 0.3 | G44: =C44*E44/D44 -> 0.3
F45: =SUM(F39:F44) -> 1.23014 | G45: =SUM(G39:G44) -> 1.23014
A46: PACKAGING
A47: INGREDIENTES | B47: CANTIDAD | D47: UNIDADES | E47: PRECIO | F47: COSTO 22 | G47: COSTO 20
A48: PLATO 22 | B48: 0 | C48: 1 | D48: 1 | E48: 2.2 | F48: =B48*E48/D48 -> 0 | G48: =C48*E48/D48 -> 2.2
A49: PLATO 25 | B49: 1 | C49: 0 | D49: 20 | E49: 1.13 | F49: =B49*E49/D49 -> 0.0565 | G49: =C49*E49/D49 -> 0
A50: CAJA 20 | B50: 0 | C50: 0 | D50: 100 | E50: 10 | F50: =B50*E50/D50 -> 0 | G50: =C50*E50/D50 -> 0
A51: CAJA 25 | B51: 1 | C51: 1 | D51: 60 | E51: 1 | F51: =B51*E51/D51 -> 0.016666667 | G51: =C51*E51/D51 -> 0.016666667
A52: ETIQUETAS | B52: 2 | C52: 2 | D52: 100 | E52: 2 | F52: =B52*E52/D52 -> 0.04 | G52: =C52*E52/D52 -> 0.04
B53: 0 | D53: 60 | E53: 1 | F53: =B53*E53/D53 -> 0 | G53: =C53*E53/D53 -> 0
D54: 1 | E54: 10 | F54: =B54*E54/D54 -> 0 | G54: =C54*E54/D54 -> 0
F55: =SUM(F48:F54) -> 0.11316667 | G55: =SUM(G48:G54) -> 2.2566667

Sheet KEYLIME PIE
B1: PIE CITRICO | E1: RECETA FLOR
A3: INGREDIENTES | B3: CANTIDAD | C3: UNIDADES | D3: PRECIO | E3: COSTO | G3: INGREDIENTES | H3: CANTIDAD | I3: UNIDADES | J3: PRECIO | K3: COSTO
G4: CAJA | H4: 1 | I4: 1 | J4: 2.2 | K4: =H4*J4/I4 -> 2.2
A5: Galletas | B5: 240 | C5: 735 | D5: 1.65 | E5: =B5*D5/C5 -> 0.53877551 | F5: 1 paquete entero | G5: Papel horno | H5: 1 | I5: 20 | J5: 1.13 | K5: =H5*J5/I5 -> 0.0565
A6: Manteca | B6: 130 | C6: 250 | D6: 2.56 | E6: =B6*D6/C6 -> 1.3312 | G6: Gastos herram | H6: 1 | I6: 100 | J6: 10 | K6: =H6*J6/I6 -> 0.1
A7: Huevos | B7: 3 | C7: 12 | D7: 2.5 | E7: =B7*D7/C7 -> 0.625 | F7: yemas solo | G7: Horno | H7: 30 | I7: 60 | J7: 1 | K7: =H7*J7/I7 -> 0.5
A8: Maicena | B8: 10 | C8: 400 | D8: 2.99 | E8: =B8*D8/C8 -> 0.07475 | G8: Agua | H8: 12 | I8: 1000 | J8: 1.97 | K8: =H8*J8/I8 -> 0.02364
A9: Vainilla | B9: 10 | C9: 236 | D9: 6.9 | E9: =B9*D9/C9 -> 0.29237288 | G9: Batidora | H9: 15 | I9: 60 | J9: 1 | K9: =H9*J9/I9 -> 0.25
A10: Citricos | B10: 80 | C10: 1000 | D10: 2.71 | E10: =B10*D10/C10 -> 0.2168 | G10: HS TRABAJO | I10: 1 | J10: 10 | K10: =H10*J10/I10 -> 0
A11: Leche condensada | B11: 450 | C11: 450 | D11: 2.59 | E11: =B11*D11/C11 -> 2.59 | K11: =SUM(K4:K10) -> 3.13014
A12: Nata | B12: 200 | C12: 600 | D12: 2.36 | E12: =B12*D12/C12 -> 0.78666667
E14: =SUM(E5:E12) -> 6.4555651 | G14: TOTAL COSTE | H14: PVP
F16: 20 cm | G16: =SUM(E14+E28+K11) -> 15.480405 | H16: 22 | I16: =H16-G16 -> 6.5195949
A17: MATERIAL | B17: CANTIDAD | C17: UNIDADES | D17: PRECIO | E17: COSTO
A19: Caja | B19: 1 | C19: 1 | D19: 2.2 | E19: =B19*D19/C19 -> 2.2
A20: Plato | B20: 1 | C20: 1 | D20: 0.9 | E20: =B20*D20/C20 -> 0.9
A21: Banda | B21: 1 | C21: 2 | D21: 0.18 | E21: =B21*D21/C21 -> 0.09
A22: Topper | B22: 1 | C22: 1 | D22: 1.75 | E22: =B22*D22/C22 -> 1.75
A23: Vela | B23: 1 | C23: 12 | D23: 1.2 | E23: =B23*D23/C23 -> 0.1
A24: Mangas | B24: 2 | C24: 40 | D24: 6.7 | E24: =B24*D24/C24 -> 0.335
A25: Lavados | B25: 10 | C25: 1000 | D25: 1.97 | E25: =B25*D25/C25 -> 0.0197
A26: Horno | B26: 30 | C26: 60 | D26: 1 | E26: =B26*D26/C26 -> 0.5
E28: =SUM(E19:E26) -> 5.8947

Sheet BROWNIE
B1: BROWNIE
A2: MASA
A3: INGREDIENTES | B3: CANTIDAD 20 P | C3: UNIDADES | D3: PRECIO | E3: COSTO
A5: Mantequilla | B5: 125 | C5: 1000 | D5: 2.56 | E5: =B5*D5/C5 -> 0.32
A6: Azucar glass | B6: 130 | C6: 1000 | D6: 5 | E6: =B6*D6/C6 -> 0.65
A7: Huevos | B7: 2 | C7: 12 | D7: 1.5 | E7: =B7*D7/C7 -> 0.25 | H7: COSTE 20P | I7: PVP | J7: PROFIT
A8: Harina | B8: 50 | C8: 1000 | D8: 1.46 | E8: =B8*D8/C8 -> 0.073 | H8: =SUM(E12+E25) -> 10.154478 | I8: 20 | J8: =SUM(I8-H8) -> 9.8455222
A9: Vainilla | B9: 10 | C9: 200 | D9: 6.9 | E9: =B9*D9/C9 -> 0.345
A10: Chocolate | B10: 200 | C10: 100 | D10: 1.2 | E10: =B10*D10/C10 -> 2.4
A11: Cacao | B11: 20 | C11: 450 | D11: 4.99 | E11: =B11*D11/C11 -> 0.22177778
E12: =SUM(E5:E11) -> 4.2597778
A13: COSTES INDIRECTOS
A14: MATERIAL | B14: CANTIDAD | C14: UNIDADES | D14: PRECIO | E14: COSTO
A16: Caja | B16: 1 | C16: 1 | D16: 2.2 | E16: =B16*D16/C16 -> 2.2
A17: Plato | B17: 1 | C17: 1 | D17: 0.9 | E17: =B17*D17/C17 -> 0.9
A18: Banda | B18: 1 | C18: 2 | D18: 0.18 | E18: =B18*D18/C18 -> 0.09
A19: Topper | B19: 1 | C19: 1 | D19: 1.75 | E19: =B19*D19/C19 -> 1.75
A20: Vela | B20: 1 | C20: 12 | D20: 1.2 | E20: =B20*D20/C20 -> 0.1
A21: Mangas | B21: 2 | C21: 40 | D21: 6.7 | E21: =B21*D21/C21 -> 0.335
A22: Lavados | B22: 10 | C22: 1000 | D22: 1.97 | E22: =B22*D22/C22 -> 0.0197
A23: Horno | B23: 30 | C23: 60 | D23: 1 | E23: =B23*D23/C23 -> 0.5
E25: =SUM(E16:E23) -> 5.8947

Sheet ALFAJORES
A2: MASA TAPAS
A3: INGREDIENTES | B3: CANTIDAD | C3: UNIDADES | D3: PRECIO | E3: COSTO
A5: Mantequilla | B5: 100 | C5: 1000 | D5: 2.56 | E5: =B5*D5/C5 -> 0.256
A6: Azucar glass | B6: 100 | C6: 1000 | D6: 5 | E6: =B6*D6/C6 -> 0.5
A7: Huevos | B7: 1 | C7: 12 | D7: 2.5 | E7: =B7*D7/C7 -> 0.20833333 | G7: =SUM(E12+E20+E33) -> 12.825311
A8: Harina | B8: 250 | C8: 1000 | D8: 1.46 | E8: =B8*D8/C8 -> 0.365
A9: Vainilla | B9: 5 | C9: 200 | D9: 6.9 | E9: =B9*D9/C9 -> 0.1725
A10: Citricos | B10: 10 | C10: 1000 | D10: 1 | E10: =B10*D10/C10 -> 0.01
A11: Cacao | B11: 20 | C11: 450 | D11: 4.99 | E11: =B11*D11/C11 -> 0.22177778
E12: =SUM(E5:E11) -> 1.7336111
B13: RELLENOS
A14: INGREDIENTES | B14: CANTIDAD | C14: UNIDADES | D14: PRECIO | E14: COSTO
A16: Dulce de leche | B16: 300 | C16: 1000 | D16: 4.99 | E16: =B16*D16/C16 -> 1.497
A17: Chocolate blanco | B17: 200 | C17: 100 | D17: 1.15 | E17: =B17*D17/C17 -> 2.3
A18: Chocolate negro | B18: 200 | C18: 100 | D18: 1.15 | E18: =B18*D18/C18 -> 2.3
A19: Mermelada | C19: 240 | D19: 2 | E19: =B19*D19/C19 -> 0
E20: =SUM(E16:E19) -> 6.097
A21: COSTES INDIRECTOS
A22: MATERIAL | B22: CANTIDAD | C22: UNIDADES | D22: PRECIO | E22: COSTO
A24: Caja | B24: 1 | C24: 1 | D24: 2.2 | E24: =B24*D24/C24 -> 2.2
A25: Plato | B25: 0 | C25: 1 | D25: 0.9 | E25: =B25*D25/C25 -> 0
A26: Banda | B26: 1 | C26: 2 | D26: 0.18 | E26: =B26*D26/C26 -> 0.09
A27: Topper | B27: 1 | C27: 1 | D27: 1.75 | E27: =B27*D27/C27 -> 1.75
A28: Vela | B28: 1 | C28: 12 | D28: 1.2 | E28: =B28*D28/C28 -> 0.1
A29: Mangas | B29: 2 | C29: 40 | D29: 6.7 | E29: =B29*D29/C29 -> 0.335
A30: Lavados | B30: 10 | C30: 1000 | D30: 1.97 | E30: =B30*D30/C30 -> 0.0197
A31: Horno | B31: 30 | C31: 60 | D31: 1 | E31: =B31*D31/C31 -> 0.5
E33: =SUM(E24:E31) -> 4.9947
